Workbook

Sheet DAILY WEEKLY EXPENSES
E2: 30 DECEMBER - 5 JANUARY 2025 | M2: =E2 -> 30 DECEMBER - 5 JANUARY 2025 | V2: =M2 -> 30 DECEMBER - 5 JANUARY 2025
C3: SHOPS | D3: DAILY CASH INCOME | E3: WEEKLY INCOME | F3: ELECTRICITY | G3: FUEL/TOLL | H3: BAKELS | I3: CHIPKINS | J3: BAKERSBIN | K3: CAVALIERI | L3: WASI | M3: OBC | N3: MAKRO | O3: WAGES | P3: T/BANTU SWEETS | Q3: SHOPRITE | R3: COMPANY EXPENSES | S3: SPICE AND PACK | T3: KIA TRUCK PAYM REF | U3: GIFT TRUCK | V3: HYPER SWEETS | W3: OTHER | Y3: TOTALS
B4: 45656 | F4: 1500 | G4: =725.31+400 -> 1125.31 | L4: 6995.64 | N4: 679.8 | P4: =32+146 -> 178 | Q4: 439.88 | W4: 194.96 | X4: AE BARB | Y4: =SUM(F4:X8) -> 11121.58 | Z4: =B4 -> 45656
B5: MON | W5: 7.99 | X5: FAMILY STORE | Z5: MON
D8: =SUM(D4:D6) -> 0 | E8: =SUM(E4:E6) -> 0
B9: 45657 | G9: =79+79+744.67+1000 -> 1902.67 | J9: 3176 | L9: 5765.73 | P9: 90 | Q9: 286.9 | W9: 252 | X9: BACK 2 BASICS | Y9: =SUM(F9:W14) -> 19033.53 | Z9: =B9 -> 45657
B10: TUES | W10: 990.23 | X10: PNP | Z10: TUES
W11: 570 | X11: SOAP CENTRE
W12: 6000 | X12: HEIDEL EGGS
D14: =SUM(D9:D11) -> 0 | E14: =SUM(E9:E11) -> 0
B15: 45658 | G15: 1100 | Y15: =SUM(F15:X21) -> 1100 | Z15: =B15 -> 45658
B16: WED
D21: =SUM(D15:D20) -> 0 | E21: =SUM(E15:E20) -> 0
B22: 45659 | G22: 300 | L22: 6147.5 | W22: 131.98 | X22: PNP | Y22: =SUM(F22:W29) -> 14166.73 | Z22: =B22 -> 45659
B23: THU | W23: 7587.25 | X23: ACE
Z26: THU
D29: =SUM(D22:D28) -> 0 | E29: =SUM(E22:E28) -> 0
B30: 45660 | G30: 704.64 | Q30: 469.89 | Y30: =SUM(F30:W33) -> 1174.53 | Z30: =B30 -> 45660
B31: FRI
D33: =SUM(D30:D32) -> 0 | E33: =SUM(E30:E32) -> 0
B34: 45661 | F34: 1500 | G34: 750 | L34: 5716.55 | O34: =11710+6300 -> 18010 | Q34: 209.93 | Y34: =SUM(F34:W40) -> 26186.48 | Z34: =B34 -> 45661
B35: SAT | Z35: SAT
D40: =SUM(D34:D39) -> 0 | E40: =SUM(E34:E39) -> 0
B41: 45662 | W41: 178.98 | X41: PNP | Y41: =SUM(F41:W44) -> 408.15 | Z41: =B41 -> 45662
B42: SUN | W42: 189.17 | X42: AE BARB CS | Z42: SUN
W43: 40 | X43: REFUSE BAGS
D44: =SUM(D41:D43) -> 0 | E44: =SUM(E41:E43) -> 0
D47: =SUM(D44,D40,D33,D29,D21,D14,D8) -> 0 | E47: =SUM(E44,E40,E33,E29,E21,E14,E8) -> 0 | F47: =SUM(F4:F46) -> 3000 | G47: =SUM(G4:G46) -> 5882.62 | H47: =SUM(H4:H46) -> 0 | I47: =SUM(I4:I46) -> 0 | J47: =SUM(J4:J46) -> 3176 | K47: =SUM(K4:K46) -> 0 | L47: =SUM(L4:L46) -> 24625.42 | M47: =SUM(M4:M46) -> 0 | ... S47: =SUM(S4:S46) -> 0 | U47: =SUM(U8:U46) -> 0 | V47: =SUM(V4:V46) -> 0 | W47: =SUM(W4:W46) -> 16142.56 | Y47: =SUM(Y4:Y44) -> 73191
C48: SHOPS | D48: DAILY CASH INCOME | E48: WEEKLY INCOME | F48: ELECTRICITY | G48: FUEL/TOLL | H48: BAKELS | I48: CHIPKINS | J48: BAKERSBIN | K48: CAVALIERI | L48: WASI | M48: SARS | N48: MAKRO | O48: WAGES | P48: T/BANTU SWEETS | Q48: SHOPRITE | R48: COMPANY EXPENSES | S48: SPICE AND PACK | T48: KIA TRUCK PAYM REF | U48: GIFT TRUCK | V48: HYPER SWEETS | W48: OTHER | Y48: TOTALS
E49: =M49 -> 30 DECEMBER - 5 JANUARY 2025 | M49: =V49 -> 30 DECEMBER - 5 JANUARY 2025 | V49: =V2 -> 30 DECEMBER - 5 JANUARY 2025
E51: 6 - 12 JANUARY 2025 | M51: =E51 -> 6 - 12 JANUARY 2025 | V51: =M51 -> 6 - 12 JANUARY 2025
C52: SHOPS | D52: DAILY CASH INCOME | E52: WEEKLY INCOME | F52: ELECTRICITY | G52: FUEL/TOLL | H52: BAKELS | I52: CHIPKINS | J52: BAKERSBIN | K52: CAVALIERI | L52: WASI | M52: OBC | N52: MAKRO | O52: WAGES | P52: T/BANTU SWEETS | Q52: SHOPRITE | R52: COMPANY EXPENSES | S52: SPICE AND PACK | T52: KIA TRUCK PAYM REF | U52: GIFT TRUCK | V52: HYPER SWEETS | W52: OTHER | Y52: TOTALS
B53: 45663 | G53: 575.18 | K53: 575 | L53: 6021.55 | N53: 1733.8 | O53: 12725 | Q53: 299.9 | V53: 2472 | W53: 289 | X53: SHOP 2 SHOP | Y53: =SUM(F53:X57) -> 25261.43 | Z53: =B53 -> 45663
B54: MON | W54: 570 | X54: SOAP CENTRE | Z54: MON
D57: =SUM(D53:D55) -> 0 | E57: =SUM(E53:E55) -> 0
B58: 45664 | G58: =804.52+1500+79+79+400 -> 2862.52 | I58: 28014 | L58: 7522.57 | W58: =258.35 -> 258.35 | X58: ae barb cs | Y58: =SUM(F58:W63) -> 44910.4 | Z58: =B58 -> 45664
B59: TUES | W59: 51 | X59: AE CAROLINA | Z59: TUES
W60: 115 | X60: AE CAROLINA
W61: 86.96 | X61: PROBUILD
W62: 6000 | X62: HEIDEL EGGS
D63: =SUM(D58:D60) -> 0 | E63: =SUM(E58:E60) -> 0
B64: 45665 | G64: 800 | Y64: =SUM(F64:X70) -> 800 | Z64: =B64 -> 45665
B65: WED
D70: =SUM(D64:D69) -> 0 | E70: =SUM(E64:E69) -> 0
B71: 45666 | G71: =999.22+79+79 -> 1157.22 | L71: 6691.45 | Q71: 299.9 | W71: 25 | X71: HOME & PARTY STORE | Y71: =SUM(F71:W78) -> 20124.8 | Z71: =B71 -> 45666
B72: THU | W72: =27.99+94.99 -> 122.98 | X72: PNP
W73: 7587.25 | X73: ACE
W74: 4241 | X74: POINT S
Z75: THU
D78: =SUM(D71:D77) -> 0 | E78: =SUM(E71:E77) -> 0
B79: 45667 | G79: 804.72 | Y79: =SUM(F79:W82) -> 804.72 | Z79: =B79 -> 45667
B80: FRI
D82: =SUM(D79:D81) -> 0 | E82: =SUM(E79:E81) -> 0
B83: 45668 | G83: 728.14 | O83: 6700 | W83: 2650 | X83: DUNLOP | Y83: =SUM(F83:W89) -> 10078.14 | Z83: =B83 -> 45668
B84: SAT | Z84: SAT
D89: =SUM(D83:D88) -> 0 | E89: =SUM(E83:E88) -> 0
B90: 45669 | F90: 1500 | L90: =19.99+5010.59 -> 5030.58 | Q90: 494.83 | W90: 133 | X90: AE BARB | Y90: =SUM(F90:W93) -> 7158.41 | Z90: =B90 -> 45669
B91: SUN | Z91: SUN
D93: =SUM(D90:D92) -> 0 | E93: =SUM(E90:E92) -> 0
D96: =SUM(D93,D89,D82,D78,D70,D63,D57) -> 0 | E96: =SUM(E93,E89,E82,E78,E70,E63,E57) -> 0 | F96: =SUM(F53:F95) -> 1500 | G96: =SUM(G53:G95) -> 6927.78 | H96: =SUM(H53:H95) -> 0 | I96: =SUM(I53:I95) -> 28014 | J96: =SUM(J53:J95) -> 0 | K96: =SUM(K53:K95) -> 575 | L96: =SUM(L53:L95) -> 25266.15 | M96: =SUM(M53:M95) -> 0 | ... S96: =SUM(S53:S95) -> 0 | U96: =SUM(U57:U95) -> 0 | V96: =SUM(V53:V95) -> 2472 | W96: =SUM(W53:W95) -> 22129.54 | Y96: =SUM(Y53:Y93) -> 109137.9
C97: SHOPS | D97: DAILY CASH INCOME | E97: WEEKLY INCOME | F97: ELECTRICITY | G97: FUEL/TOLL | H97: BAKELS | I97: CHIPKINS | J97: BAKERSBIN | K97: CAVALIERI | L97: WASI | M97: SARS | N97: MAKRO | O97: WAGES | P97: T/BANTU SWEETS | Q97: SHOPRITE | R97: COMPANY EXPENSES | S97: SPICE AND PACK | T97: KIA TRUCK PAYM REF | U97: GIFT TRUCK | V97: HYPER SWEETS | W97: OTHER | Y97: TOTALS
E98: =M98 -> 6 - 12 JANUARY 2025 | M98: =V98 -> 6 - 12 JANUARY 2025 | V98: =V51 -> 6 - 12 JANUARY 2025
E100: 13 - 19 JANUARY 2025 | M100: =E100 -> 13 - 19 JANUARY 2025 | V100: =M100 -> 13 - 19 JANUARY 2025
C101: SHOPS | D101: DAILY CASH INCOME | E101: WEEKLY INCOME | F101: ELECTRICITY | G101: FUEL/TOLL | H101: BAKELS | I101: CHIPKINS | J101: BAKERSBIN | K101: CAVALIERI | L101: WASI | M101: OBC | N101: MAKRO | O101: WAGES | P101: T/BANTU SWEETS | Q101: SHOPRITE | R101: COMPANY EXPENSES | S101: SPICE AND PACK | T101: KIA TRUCK PAYM REF | U101: GIFT TRUCK | V101: HYPER SWEETS | W101: OTHER | Y101: TOTALS
B102: 45670 | G102: 300 | L102: =1110+5383.56 -> 6493.56 | Q102: 314.91 | V102: 672 | W102: 870 | X102: SOAP CENTRE | Y102: =SUM(F102:X106) -> 8650.47 | Z102: =B102 -> 45670
B103: MON | Z103: MON
D106: =SUM(D102:D104) -> 0 | E106: =SUM(E102:E104) -> 0
B107: 45671 | G107: =300+775.96+79+79 -> 1233.96 | L107: 6880.59 | O107: 11325 | Q107: 244.93 | W107: 137 | X107: AFROLO | Y107: =SUM(F107:W112) -> 27762.42 | Z107: =B107 -> 45671
B108: TUES | W108: 60 | X108: BACK2BASICS | Z108: TUES
W109: 80.94 | X109: CRAZY STORE
W110: 7800 | X110: HEIDEL EGGS
D112: =SUM(D107:D109) -> 0 | E112: =SUM(E107:E109) -> 0
B113: 45672 | G113: 850.16 | Y113: =SUM(F113:X119) -> 850.16 | Z113: =B113 -> 45672
B114: WED
D119: =SUM(D113:D118) -> 0 | E119: =SUM(E113:E118) -> 0
B120: 45673 | L120: 5978.5 | Q120: 314.91 | W120: 88 | X120: family store | Y120: =SUM(F120:W127) -> 8910.49 | Z120: =B120 -> 45673
B121: THU | W121: 2529.08 | X121: ACE
Z124: THU
D127: =SUM(D120:D126) -> 0 | E127: =SUM(E120:E126) -> 0
B128: 45674 | G128: 800 | Y128: =SUM(F128:W131) -> 800 | Z128: =B128 -> 45674
B129: FRI
D131: =SUM(D128:D130) -> 0 | E131: =SUM(E128:E130) -> 0
B132: 45675 | F132: 1500 | L132: 6462.58 | P132: 25.9 | Q132: 349.9 | W132: 520 | X132: POINT S | Y132: =SUM(F132:W138) -> 8858.38 | Z132: =B132 -> 45675
B133: SAT | Z133: SAT
D138: =SUM(D132:D137) -> 0 | E138: =SUM(E132:E137) -> 0
B139: 45676 | Y139: =SUM(F139:W142) -> 0 | Z139: =B139 -> 45676
B140: SUN | Z140: SUN
D142: =SUM(D139:D141) -> 0 | E142: =SUM(E139:E141) -> 0
D145: =SUM(D142,D138,D131,D127,D119,D112,D106) -> 0 | E145: =SUM(E142,E138,E131,E127,E119,E112,E106) -> 0 | F145: =SUM(F102:F144) -> 1500 | G145: =SUM(G102:G144) -> 3184.12 | H145: =SUM(H102:H144) -> 0 | I145: =SUM(I102:I144) -> 0 | J145: =SUM(J102:J144) -> 0 | K145: =SUM(K102:K144) -> 0 | L145: =SUM(L102:L144) -> 25815.23 | M145: =SUM(M102:M144) -> 0 | ... S145: =SUM(S102:S144) -> 0 | U145: =SUM(U106:U144) -> 0 | V145: =SUM(V102:V144) -> 672 | W145: =SUM(W102:W144) -> 12085.02 | Y145: =SUM(Y102:Y142) -> 55831.92
C146: SHOPS | D146: DAILY CASH INCOME | E146: WEEKLY INCOME | F146: ELECTRICITY | G146: FUEL/TOLL | H146: BAKELS | I146: CHIPKINS | J146: BAKERSBIN | K146: CAVALIERI | L146: WASI | M146: SARS | N146: MAKRO | O146: WAGES | P146: T/BANTU SWEETS | Q146: SHOPRITE | R146: COMPANY EXPENSES | S146: SPICE AND PACK | T146: KIA TRUCK PAYM REF | U146: GIFT TRUCK | V146: HYPER SWEETS | W146: OTHER | Y146: TOTALS
E147: =M147 -> 13 - 19 JANUARY 2025 | M147: =V147 -> 13 - 19 JANUARY 2025 | V147: =V100 -> 13 - 19 JANUARY 2025
E149: 20 - 26 JANUARY 2025 | M149: =E149 -> 20 - 26 JANUARY 2025 | V149: =M149 -> 20 - 26 JANUARY 2025
C150: SHOPS | D150: DAILY CASH INCOME | E150: WEEKLY INCOME | F150: ELECTRICITY | G150: FUEL/TOLL | H150: BAKELS | I150: CHIPKINS | J150: BAKERSBIN | K150: CAVALIERI | L150: WASI | M150: OBC | N150: MAKRO | O150: WAGES | P150: T/BANTU SWEETS | Q150: SHOPRITE | R150: COMPANY EXPENSES | S150: SPICE AND PACK | T150: KIA TRUCK PAYM REF | U150: GIFT TRUCK | V150: HYPER SWEETS | W150: OTHER | Y150: TOTALS
B151: 45677 | G151: 1501.06 | L151: 4667.64 | O151: 6700 | P151: 180 | Q151: 139.96 | W151: 826 | X151: SOAP CENTRE | Y151: =SUM(F151:X155) -> 14014.66 | Z151: =B151 -> 45677
B152: MON | Z152: MON
D155: =SUM(D151:D153) -> 0 | E155: =SUM(E151:E153) -> 0
B156: 45678 | G156: =1119.53+79+79 -> 1277.53 | I156: 24276.5 | L156: 3997.68 | Y156: =SUM(F156:W161) -> 29551.71 | Z156: =B156 -> 45678
B157: TUES | Z157: TUES
D161: =SUM(D156:D158) -> 0 | E161: =SUM(E156:E158) -> 0
B162: 45679 | G162: 800 | N162: 1153.3 | W162: 476.75 | X162: LOWVELD PACKAGING | Y162: =SUM(F162:X168) -> 2430.05 | Z162: =B162 -> 45679
...

Sheet MONTHLY EXPENSES
C1: MONTHLY EXPENSES
A2: WEEKLY DATES | C2: ELEC | D2: FUEL/TOLL GATES | E2: HYPER SWEETS | F2: CHIPKINS | G2: BAKERSBIN | H2: CAVALIRI | I2: SHOPRITE | J2: WASI | K2: SPICE& PACK | L2: MAKRO | M2: WAGES | N2: OTHERS | O2: WEEKLY DATES | Q2: TOTALS
A3: 30 DEC - 5 JAN 2025 | C3: ='DAILY WEEKLY EXPENSES'!F47 -> 3000 | D3: ='DAILY WEEKLY EXPENSES'!G47 -> 5882.62 | E3: ='DAILY WEEKLY EXPENSES'!V47 -> 0 | F3: ='DAILY WEEKLY EXPENSES'!I47 -> 0 | G3: ='DAILY WEEKLY EXPENSES'!J47 -> 3176 | H3: ='DAILY WEEKLY EXPENSES'!K47 -> 0 | I3: ='DAILY WEEKLY EXPENSES'!Q47 -> 1406.6 | J3: ='DAILY WEEKLY EXPENSES'!L47 -> 24625.42 | K3: ='DAILY WEEKLY EXPENSES'!S47 -> 0 | L3: ='DAILY WEEKLY EXPENSES'!N47 -> 679.8 | M3: ='DAILY WEEKLY EXPENSES'!O47 -> 18010 | N3: ='DAILY WEEKLY EXPENSES'!W47 -> 16142.56 | O3: =A3 -> 30 DEC - 5 JAN 2025 | Q3: =SUM(C3:N3) -> 72923
A4: 6 - 12 JAN 2025 | C4: ='DAILY WEEKLY EXPENSES'!F96 -> 1500 | D4: ='DAILY WEEKLY EXPENSES'!G96 -> 6927.78 | E4: ='DAILY WEEKLY EXPENSES'!V96 -> 2472 | F4: ='DAILY WEEKLY EXPENSES'!I96 -> 28014 | G4: ='DAILY WEEKLY EXPENSES'!J96 -> 0 | H4: ='DAILY WEEKLY EXPENSES'!K96 -> 575 | I4: ='DAILY WEEKLY EXPENSES'!Q96 -> 1094.63 | J4: ='DAILY WEEKLY EXPENSES'!L96 -> 25266.15 | K4: ='DAILY WEEKLY EXPENSES'!S96 -> 0 | L4: ='DAILY WEEKLY EXPENSES'!N96 -> 1733.8 | M4: ='DAILY WEEKLY EXPENSES'!N96 -> 1733.8 | N4: ='DAILY WEEKLY EXPENSES'!W96 -> 22129.54 | O4: =A4 -> 6 - 12 JAN 2025 | Q4: =SUM(C4:N4) -> 91446.7
A5: 13 - 19 JAN 2025 | C5: ='DAILY WEEKLY EXPENSES'!F145 -> 1500 | D5: ='DAILY WEEKLY EXPENSES'!G145 -> 3184.12 | E5: ='DAILY WEEKLY EXPENSES'!V145 -> 672 | F5: ='DAILY WEEKLY EXPENSES'!I145 -> 0 | G5: ='DAILY WEEKLY EXPENSES'!J145 -> 0 | H5: ='DAILY WEEKLY EXPENSES'!K145 -> 0 | I5: ='DAILY WEEKLY EXPENSES'!Q145 -> 1224.65 | J5: ='DAILY WEEKLY EXPENSES'!L145 -> 25815.23 | K5: ='DAILY WEEKLY EXPENSES'!S145 -> 0 | L5: ='DAILY WEEKLY EXPENSES'!N145 -> 0 | M5: ='DAILY WEEKLY EXPENSES'!O145 -> 11325 | N5: ='DAILY WEEKLY EXPENSES'!W145 -> 12085.02 | O5: =A5 -> 13 - 19 JAN 2025 | Q5: =SUM(C5:N5) -> 55806.02
A6: 20 - 26 JAN 2025 | C6: ='DAILY WEEKLY EXPENSES'!F194 -> 0 | D6: ='DAILY WEEKLY EXPENSES'!G194 -> 6266.54 | E6: ='DAILY WEEKLY EXPENSES'!V194 -> 0 | F6: ='DAILY WEEKLY EXPENSES'!I194 -> 24276.5 | G6: ='DAILY WEEKLY EXPENSES'!J194 -> 0 | H6: ='DAILY WEEKLY EXPENSES'!K194 -> 0 | I6: ='DAILY WEEKLY EXPENSES'!Q194 -> 489.86 | J6: ='DAILY WEEKLY EXPENSES'!L194 -> 21064.3 | K6: ='DAILY WEEKLY EXPENSES'!S194 -> 9739.66 | L6: ='DAILY WEEKLY EXPENSES'!N194 -> 1153.3 | M6: ='DAILY WEEKLY EXPENSES'!O194 -> 22760 | N6: ='DAILY WEEKLY EXPENSES'!W194 -> 4298.34 | O6: =A6 -> 20 - 26 JAN 2025 | Q6: =SUM(C6:N6) -> 90048.5
A7: WEEKLY TOTALS | C7: =SUM(C3:C6) -> 6000 | D7: =SUM(D3:D6) -> 22261.06 | E7: =SUM(E3:E6) -> 3144 | F7: =SUM(F3:F6) -> 52290.5 | G7: =SUM(G3:G6) -> 3176 | H7: =SUM(H3:H6) -> 575 | I7: =SUM(I3:I6) -> 4215.74 | J7: =SUM(J3:J6) -> 96771.1 | ... N7: =SUM(N3:N6) -> 54655.46 | O7: =SUM(C7:N7) -> 310224.22 | P7: JANUARY | Q7: =SUM(Q3:Q6) -> 310224.22
A8: WEEKLY DATES | C8: ELEC | D8: FUEL/TOLL GATES | E8: HYPER SWEETS | F8: CHIPKINS | G8: BAKERSBIN | H8: CAVALIRI | I8: SHOPRITE | J8: WASI | K8: SPICE& PACK | L8: MAKRO | M8: WAGES | N8: OTHERS | O8: WEEKLY DATES | Q8: TOTALS
A9: 27 JAN - 2 FEB 2025 | C9: ='DAILY WEEKLY EXPENSES'!F243 -> 3000 | D9: ='DAILY WEEKLY EXPENSES'!G243 -> 4947.15 | E9: ='DAILY WEEKLY EXPENSES'!V243 -> 0 | F9: ='DAILY WEEKLY EXPENSES'!I243 -> 12186.33 | G9: ='DAILY WEEKLY EXPENSES'!J243 -> 0 | H9: ='DAILY WEEKLY EXPENSES'!K243 -> 0 | I9: ='DAILY WEEKLY EXPENSES'!Q243 -> 489.86 | J9: ='DAILY WEEKLY EXPENSES'!L243 -> 24346.18 | K9: ='DAILY WEEKLY EXPENSES'!S243 -> 7157.54 | L9: ='DAILY WEEKLY EXPENSES'!N243 -> 0 | M9: ='DAILY WEEKLY EXPENSES'!O243 -> 6900 | N9: ='DAILY WEEKLY EXPENSES'!W243 -> 7855.33 | O9: =A9 -> 27 JAN - 2 FEB 2025 | Q9: =SUM(C9:N9) -> 66882.39
A10: 3 - 9 FEB 2025 | C10: ='DAILY WEEKLY EXPENSES'!F292 -> 1500 | D10: ='DAILY WEEKLY EXPENSES'!G292 -> 4158 | E10: ='DAILY WEEKLY EXPENSES'!V292 -> 1200 | F10: ='DAILY WEEKLY EXPENSES'!I292 -> 24863 | G10: ='DAILY WEEKLY EXPENSES'!J292 -> 0 | H10: ='DAILY WEEKLY EXPENSES'!I292 -> 24863 | I10: ='DAILY WEEKLY EXPENSES'!Q292 -> 944.73 | J10: ='DAILY WEEKLY EXPENSES'!L292 -> 27106.96 | K10: ='DAILY WEEKLY EXPENSES'!S292 -> 7157.54 | L10: ='DAILY WEEKLY EXPENSES'!N292 -> 509.8 | M10: ='DAILY WEEKLY EXPENSES'!O292 -> 18755 | N10: ='DAILY WEEKLY EXPENSES'!W292 -> 10939.81 | O10: =A10 -> 3 - 9 FEB 2025 | Q10: =SUM(C10:N10) -> 121997.84
A11: 10 - 16 FEB 2025 | C11: ='DAILY WEEKLY EXPENSES'!F341 -> 3902.44 | D11: ='DAILY WEEKLY EXPENSES'!G341 -> 7127.17 | E11: ='DAILY WEEKLY EXPENSES'!V341 -> 0 | F11: ='DAILY WEEKLY EXPENSES'!I341 -> 1840 | G11: ='DAILY WEEKLY EXPENSES'!J341 -> 0 | H11: ='DAILY WEEKLY EXPENSES'!K341 -> 575 | I11: ='DAILY WEEKLY EXPENSES'!Q341 -> 1745.91 | J11: ='DAILY WEEKLY EXPENSES'!L341 -> 30395.05 | K11: ='DAILY WEEKLY EXPENSES'!S341 -> 0 | L11: ='DAILY WEEKLY EXPENSES'!N341 -> 1228.8 | M11: ='DAILY WEEKLY EXPENSES'!O341 -> 0 | N11: ='DAILY WEEKLY EXPENSES'!W341 -> 13918.69 | O11: =A11 -> 10 - 16 FEB 2025 | Q11: =SUM(C11:N11) -> 60733.06
A12: 17 - 23 FEB 2025 | C12: ='DAILY WEEKLY EXPENSES'!F390 -> 3000 | D12: ='DAILY WEEKLY EXPENSES'!G390 -> 5156.93 | E12: ='DAILY WEEKLY EXPENSES'!V390 -> 0 | F12: ='DAILY WEEKLY EXPENSES'!I390 -> 26460.13 | G12: ='DAILY WEEKLY EXPENSES'!J390 -> 0 | H12: ='DAILY WEEKLY EXPENSES'!K390 -> 0 | I12: ='DAILY WEEKLY EXPENSES'!Q390 -> 1230.81 | J12: ='DAILY WEEKLY EXPENSES'!L390 -> 22313.06 | K12: ='DAILY WEEKLY EXPENSES'!S390 -> 5731.95 | L12: ='DAILY WEEKLY EXPENSES'!N390 -> 0 | M12: ='DAILY WEEKLY EXPENSES'!O390 -> 6900 | N12: ='DAILY WEEKLY EXPENSES'!W390 -> 3194.54 | O12: =A12 -> 17 - 23 FEB 2025 | Q12: =SUM(C12:N12) -> 73987.42
A13: WEEKLY TOTALS | C13: =SUM(C9:C12) -> 11402.44 | D13: =SUM(D9:D12) -> 21389.25 | E13: =SUM(E9:E12) -> 1200 | F13: =SUM(F9:F12) -> 65349.46 | G13: =SUM(G9:G12) -> 0 | H13: =SUM(H9:H12) -> 25438 | I13: =SUM(I9:I12) -> 4411.31 | J13: =SUM(J9:J12) -> 104161.25 | ... N13: =SUM(N9:N12) -> 35908.37 | O13: =SUM(C13:N13) -> 323600.71 | P13: FEBRUARY | Q13: =SUM(Q9:Q12) -> 323600.71
A14: WEEKLY DATES | C14: ELEC | D14: FUEL/TOLL GATES | E14: HYPER SWEETS | F14: CHIPKINS | G14: BAKERSBIN | H14: CAVALIRI | I14: SHOPRITE | J14: WASI | K14: SPICE& PACK | L14: MAKRO | M14: WAGES | N14: OTHERS | O14: WEEKLY DATES | Q14: TOTALS
A15: 24 FEB - 2 MAR 2025 | C15: ='DAILY WEEKLY EXPENSES'!F439 -> 1500 | D15: ='DAILY WEEKLY EXPENSES'!G439 -> 4000.17 | E15: ='DAILY WEEKLY EXPENSES'!V439 -> 1200 | F15: ='DAILY WEEKLY EXPENSES'!I439 -> 10521.58 | G15: ='DAILY WEEKLY EXPENSES'!J439 -> 0 | H15: ='DAILY WEEKLY EXPENSES'!K439 -> 575 | I15: ='DAILY WEEKLY EXPENSES'!Q439 -> 1279.72 | J15: ='DAILY WEEKLY EXPENSES'!L439 -> 34524.15 | K15: ='DAILY WEEKLY EXPENSES'!S439 -> 7157.54 | L15: ='DAILY WEEKLY EXPENSES'!N439 -> 2588.9 | M15: ='DAILY WEEKLY EXPENSES'!O439 -> 14530 | N15: ='DAILY WEEKLY EXPENSES'!W439 -> 7074.16 | O15: =A15 -> 24 FEB - 2 MAR 2025 | Q15: =SUM(C15:N15) -> 84951.22
A16: 3 - 9 MAR 2025 | C16: ='DAILY WEEKLY EXPENSES'!F489 -> 0 | D16: ='DAILY WEEKLY EXPENSES'!G489 -> 5952.33 | E16: ='DAILY WEEKLY EXPENSES'!V489 -> 0 | F16: ='DAILY WEEKLY EXPENSES'!I489 -> 10039.5 | G16: ='DAILY WEEKLY EXPENSES'!J489 -> 0 | H16: ='DAILY WEEKLY EXPENSES'!K489 -> 0 | I16: ='DAILY WEEKLY EXPENSES'!Q489 -> 1123.72 | J16: ='DAILY WEEKLY EXPENSES'!L489 -> 33226.06 | K16: ='DAILY WEEKLY EXPENSES'!S489 -> 0 | L16: ='DAILY WEEKLY EXPENSES'!N489 -> 3258.8 | M16: ='DAILY WEEKLY EXPENSES'!O489 -> 18610 | N16: ='DAILY WEEKLY EXPENSES'!W489 -> 3822.89 | O16: =A16 -> 3 - 9 MAR 2025 | Q16: =SUM(C16:N16) -> 76033.3
A17: 10 - 16 MAR 2025 | C17: ='DAILY WEEKLY EXPENSES'!F539 -> 3000 | D17: ='DAILY WEEKLY EXPENSES'!G539 -> 3445.24 | E17: ='DAILY WEEKLY EXPENSES'!V539 -> 1200 | F17: ='DAILY WEEKLY EXPENSES'!I539 -> 19333.8 | G17: ='DAILY WEEKLY EXPENSES'!J539 -> 0 | H17: ='DAILY WEEKLY EXPENSES'!K539 -> 0 | I17: ='DAILY WEEKLY EXPENSES'!Q539 -> 1349.7 | J17: ='DAILY WEEKLY EXPENSES'!L539 -> 27534.52 | K17: ='DAILY WEEKLY EXPENSES'!S539 -> 4771.7 | L17: ='DAILY WEEKLY EXPENSES'!N539 -> 0 | M17: ='DAILY WEEKLY EXPENSES'!O539 -> 17855 | N17: ='DAILY WEEKLY EXPENSES'!W539 -> 1359.98 | O17: =A17 -> 10 - 16 MAR 2025 | Q17: =SUM(C17:N17) -> 79849.94
A18: 17-23 MAR 2025 | C18: ='DAILY WEEKLY EXPENSES'!F591 -> 0 | D18: ='DAILY WEEKLY EXPENSES'!G591 -> 5200.37 | E18: ='DAILY WEEKLY EXPENSES'!V591 -> 0 | F18: ='DAILY WEEKLY EXPENSES'!I591 -> 18571.13 | G18: ='DAILY WEEKLY EXPENSES'!J591 -> 0 | H18: ='DAILY WEEKLY EXPENSES'!K591 -> 4906.73 | I18: ='DAILY WEEKLY EXPENSES'!Q591 -> 1329.71 | J18: ='DAILY WEEKLY EXPENSES'!L591 -> 25320.34 | K18: ='DAILY WEEKLY EXPENSES'!S591 -> 7157.54 | L18: ='DAILY WEEKLY EXPENSES'!N591 -> 778 | M18: ='DAILY WEEKLY EXPENSES'!O591 -> 0 | N18: ='DAILY WEEKLY EXPENSES'!W591 -> 5353.95 | O18: =A18 -> 17-23 MAR 2025 | Q18: =SUM(C18:N18) -> 68617.77
A19: WEEKLY TOTALS | C19: =SUM(C15:C18) -> 4500 | D19: =SUM(D15:D18) -> 18598.11 | E19: =SUM(E15:E18) -> 2400 | F19: =SUM(F15:F18) -> 58466.01 | G19: =SUM(G15:G18) -> 0 | H19: =SUM(H15:H18) -> 5481.73 | I19: =SUM(I15:I18) -> 5082.85 | J19: =SUM(J15:J18) -> 120605.07 | ... N19: =SUM(N15:N18) -> 17610.98 | O19: =SUM(C19:N19) -> 309452.23 | P19: MARCH | Q19: =SUM(Q15:Q18) -> 309452.23
A20: WEEKLY DATES | C20: ELEC | D20: FUEL/TOLL GATES | E20: HYPER SWEETS | F20: CHIPKINS | G20: BAKERSBIN | H20: CAVALIRI | I20: SHOPRITE | J20: WASI | K20: SPICE& PACK | L20: MAKRO | M20: WAGES | N20: OTHERS | O20: WEEKLY DATES | Q20: TOTALS
A21: 24 - 30 MAR 2025 | C21: ='DAILY WEEKLY EXPENSES'!F641 -> 1500 | D21: ='DAILY WEEKLY EXPENSES'!G641 -> 4361.61 | E21: ='DAILY WEEKLY EXPENSES'!V641 -> 600 | F21: ='DAILY WEEKLY EXPENSES'!I641 -> 4358.5 | G21: ='DAILY WEEKLY EXPENSES'!J641 -> 0 | H21: ='DAILY WEEKLY EXPENSES'!K641 -> 575 | I21: ='DAILY WEEKLY EXPENSES'!Q641 -> 1664.63 | J21: ='DAILY WEEKLY EXPENSES'!L641 -> 34564.89 | K21: ='DAILY WEEKLY EXPENSES'!S641 -> 7157.54 | L21: ='DAILY WEEKLY EXPENSES'!N641 -> 1327.8 | M21: ='DAILY WEEKLY EXPENSES'!O641 -> 16235 | N21: ='DAILY WEEKLY EXPENSES'!W641 -> 1431.12 | O21: =A21 -> 24 - 30 MAR 2025 | Q21: =SUM(C21:N21) -> 73776.09
A22: 31 MAR - 6 APR 2025 | C22: ='DAILY WEEKLY EXPENSES'!F691 -> 1600 | D22: ='DAILY WEEKLY EXPENSES'!G691 -> 5378.04 | E22: ='DAILY WEEKLY EXPENSES'!V691 -> 0 | F22: ='DAILY WEEKLY EXPENSES'!I691 -> 21959.25 | G22: ='DAILY WEEKLY EXPENSES'!J691 -> 0 | H22: ='DAILY WEEKLY EXPENSES'!K691 -> 0 | I22: ='DAILY WEEKLY EXPENSES'!Q691 -> 1599.66 | J22: ='DAILY WEEKLY EXPENSES'!L691 -> 20183.88 | K22: ='DAILY WEEKLY EXPENSES'!S691 -> 7157.54 | L22: ='DAILY WEEKLY EXPENSES'!N691 -> 0 | M22: ='DAILY WEEKLY EXPENSES'!O691 -> 18670 | N22: ='DAILY WEEKLY EXPENSES'!W691 -> 5485.78 | O22: =A22 -> 31 MAR - 6 APR 2025 | Q22: =SUM(C22:N22) -> 82034.15
A23: 7 - 13 APR 2025 | C23: ='DAILY WEEKLY EXPENSES'!F741 -> 1500 | D23: ='DAILY WEEKLY EXPENSES'!G741 -> 3857.89 | E23: ='DAILY WEEKLY EXPENSES'!V741 -> 0 | F23: ='DAILY WEEKLY EXPENSES'!I741 -> 19859.13 | G23: ='DAILY WEEKLY EXPENSES'!H741 -> 0 | H23: ='DAILY WEEKLY EXPENSES'!K741 -> 548.32 | I23: ='DAILY WEEKLY EXPENSES'!Q741 -> 799.84 | J23: ='DAILY WEEKLY EXPENSES'!L741 -> 28241.97 | K23: ='DAILY WEEKLY EXPENSES'!S741 -> 7157.54 | L23: ='DAILY WEEKLY EXPENSES'!N741 -> 0 | M23: ='DAILY WEEKLY EXPENSES'!O741 -> 14820 | N23: ='DAILY WEEKLY EXPENSES'!W741 -> 2448.24 | O23: =A23 -> 7 - 13 APR 2025 | Q23: =SUM(C23:N23) -> 79232.93
A24: 14 - 20 APR 2025 | C24: ='DAILY WEEKLY EXPENSES'!F791 -> 1500 | D24: ='DAILY WEEKLY EXPENSES'!G791 -> 6557.04 | E24: ='DAILY WEEKLY EXPENSES'!V791 -> 0 | F24: ='DAILY WEEKLY EXPENSES'!I791 -> 33752.5 | G24: ='DAILY WEEKLY EXPENSES'!J791 -> 0 | H24: ='DAILY WEEKLY EXPENSES'!K791 -> 548.32 | I24: ='DAILY WEEKLY EXPENSES'!Q791 -> 2401.47 | J24: ='DAILY WEEKLY EXPENSES'!L791 -> 45594.09 | K24: ='DAILY WEEKLY EXPENSES'!S791 -> 7157.54 | L24: ='DAILY WEEKLY EXPENSES'!N791 -> 1005 | M24: ='DAILY WEEKLY EXPENSES'!O791 -> 0 | N24: ='DAILY WEEKLY EXPENSES'!W791 -> 4592.97 | O24: =A24 -> 14 - 20 APR 2025 | Q24: =SUM(C24:N24) -> 103108.93
A25: WEEKLY TOTALS | C25: =SUM(C21:C24) -> 6100 | D25: =SUM(D21:D24) -> 20154.58 | E25: =SUM(E21:E24) -> 600 | F25: =SUM(F21:F24) -> 79929.38 | G25: =SUM(G21:G24) -> 0 | H25: =SUM(H21:H24) -> 1671.64 | I25: =SUM(I21:I24) -> 6465.6 | J25: =SUM(J21:J24) -> 128584.83 | ... O25: =SUM(O21:O24) -> 0 | P25: APRIL | Q25: =SUM(Q21:Q24) -> 338152.1
A26: WEEKLY DATES | C26: ELEC | D26: FUEL/TOLL GATES | E26: HYPER SWEETS | F26: CHIPKINS | G26: BAKERSBIN | H26: CAVALIRI | I26: SHOPRITE | J26: WASI | K26: SPICE& PACK | L26: MAKRO | M26: WAGES | N26: OTHERS | O26: WEEKLY DATES | Q26: TOTALS
A27: 21 - 27 APR 2025 | C27: ='DAILY WEEKLY EXPENSES'!F841 -> 1500 | D27: ='DAILY WEEKLY EXPENSES'!G841 -> 5328.95 | E27: ='DAILY WEEKLY EXPENSES'!V841 -> 0 | F27: ='DAILY WEEKLY EXPENSES'!I841 -> 0 | G27: ='DAILY WEEKLY EXPENSES'!J841 -> 0 | H27: ='DAILY WEEKLY EXPENSES'!K841 -> 0 | I27: ='DAILY WEEKLY EXPENSES'!Q841 -> 1790.2 | J27: ='DAILY WEEKLY EXPENSES'!L841 -> 29274.16 | K27: ='DAILY WEEKLY EXPENSES'!S841 -> 7157.54 | L27: ='DAILY WEEKLY EXPENSES'!N841 -> 5733.9 | M27: ='DAILY WEEKLY EXPENSES'!O841 -> 43235 | N27: ='DAILY WEEKLY EXPENSES'!W841 -> 807.99 | O27: =A27 -> 21 - 27 APR 2025 | Q27: =SUM(C27:N27) -> 94827.74
A28: 28 APR - 4 MAY 2025 | C28: ='DAILY WEEKLY EXPENSES'!F891 -> 1500 | D28: ='DAILY WEEKLY EXPENSES'!G891 -> 5181.15 | E28: ='DAILY WEEKLY EXPENSES'!V891 -> 0 | F28: ='DAILY WEEKLY EXPENSES'!I891 -> 20531.88 | G28: ='DAILY WEEKLY EXPENSES'!J891 -> 0 | H28: ='DAILY WEEKLY EXPENSES'!K891 -> 0 | I28: ='DAILY WEEKLY EXPENSES'!Q891 -> 2302.39 | J28: ='DAILY WEEKLY EXPENSES'!L891 -> 38351.6 | K28: ='DAILY WEEKLY EXPENSES'!S891 -> 7157.54 | L28: ='DAILY WEEKLY EXPENSES'!N891 -> 0 | M28: ='DAILY WEEKLY EXPENSES'!O891 -> 19450 | N28: ='DAILY WEEKLY EXPENSES'!W891 -> 1384.96 | O28: =A28 -> 28 APR - 4 MAY 2025 | Q28: =SUM(C28:N28) -> 95859.52
O29: =A29 -> 0 | Q29: =SUM(C29:N29) -> 0
O30: =A30 -> 0 | Q30: =SUM(C30:N30) -> 0
A31: WEEKLY TOTALS | C31: =SUM(C27:C30) -> 3000 | D31: =SUM(D27:D30) -> 10510.1 | E31: =SUM(E27:E30) -> 0 | F31: =SUM(F27:F30) -> 20531.88 | G31: =SUM(G27:G30) -> 0 | H31: =SUM(H27:H30) -> 0 | I31: =SUM(I27:I30) -> 4092.59 | J31: =SUM(J27:J30) -> 67625.76 | ... O31: =SUM(O27:O30) -> 0 | P31: MAY | Q31: =SUM(Q27:Q30) -> 190687.26
A32: WEEKLY DATES | C32: ELEC | D32: FUEL/TOLL GATES | E32: HYPER SWEETS | F32: CHIPKINS | G32: BAKERSBIN | H32: CAVALIRI | I32: SHOPRITE | J32: WASI | K32: SPICE& PACK | L32: MAKRO | M32: WAGES | N32: OTHERS | O32: WEEKLY DATES | Q32: TOTALS
O33: =A33 -> 0 | Q33: =SUM(C33:N33) -> 0
O34: =A34 -> 0 | Q34: =SUM(C34:N34) -> 0
O35: =A35 -> 0 | Q35: =SUM(C35:N35) -> 0
O36: =A36 -> 0 | Q36: =SUM(C36:N36) -> 0
A37: WEEKLY TOTALS | C37: =SUM(C33:C36) -> 0 | D37: =SUM(D33:D36) -> 0 | E37: =SUM(E33:E36) -> 0 | F37: =SUM(F33:F36) -> 0 | G37: =SUM(G33:G36) -> 0 | H37: =SUM(H33:H36) -> 0 | I37: =SUM(I33:I36) -> 0 | J37: =SUM(J33:J36) -> 0 | ... O37: =SUM(O33:O36) -> 0 | P37: JUNE | Q37: =SUM(Q33:Q36) -> 0
A38: WEEKLY DATES | C38: ELEC | D38: FUEL/TOLL GATES | E38: HYPER SWEETS | F38: CHIPKINS | G38: BAKERSBIN | H38: CAVALIRI | I38: SHOPRITE | J38: WASI | K38: SPICE& PACK | L38: MAKRO | M38: WAGES | N38: OTHERS | O38: WEEKLY DATES | Q38: TOTALS
O39: =A39 -> 0 | Q39: =SUM(C39:N39) -> 0
O40: =A40 -> 0 | Q40: =SUM(C40:N40) -> 0
O41: =A41 -> 0 | Q41: =SUM(C41:N41) -> 0
O42: =A42 -> 0 | Q42: =SUM(C42:N42) -> 0
A43: WEEKLY TOTALS | C43: =SUM(C39:C42) -> 0 | D43: =SUM(D39:D42) -> 0 | E43: =SUM(E39:E42) -> 0 | F43: =SUM(F39:F42) -> 0 | G43: =SUM(G39:G42) -> 0 | H43: =SUM(H39:H42) -> 0 | I43: =SUM(I39:I42) -> 0 | J43: =SUM(J39:J42) -> 0 | ... O43: =SUM(O39:O42) -> 0 | P43: JULY | Q43: =SUM(Q39:Q42) -> 0
A44: WEEKLY DATES | C44: ELEC | D44: FUEL/TOLL GATES | E44: HYPER SWEETS | F44: CHIPKINS | G44: BAKERSBIN | H44: CAVALIRI | I44: SHOPRITE | J44: WASI | K44: SPICE& PACK | L44: MAKRO | M44: WAGES | N44: OTHERS | O44: WEEKLY DATES | Q44: TOTALS
O45: =A45 -> 0 | Q45: =SUM(C45:N45) -> 0
O46: =A46 -> 0 | Q46: =SUM(C46:N46) -> 0
O47: =A47 -> 0 | Q47: =SUM(C47:N47) -> 0
O48: =A48 -> 0 | Q48: =SUM(C48:N48) -> 0
A49: WEEKLY TOTALS | C49: =SUM(C45:C48) -> 0 | D49: =SUM(D45:D48) -> 0 | E49: =SUM(E45:E48) -> 0 | F49: =SUM(F45:F48) -> 0 | G49: =SUM(G45:G48) -> 0 | H49: =SUM(H45:H48) -> 0 | I49: =SUM(I45:I48) -> 0 | J49: =SUM(J45:J48) -> 0 | ... O49: =SUM(O45:O48) -> 0 | P49: AUGUST | Q49: =SUM(Q45:Q48) -> 0
A50: WEEKLY DATES | C50: ELEC | D50: FUEL/TOLL GATES | E50: HYPER SWEETS | F50: CHIPKINS | G50: BAKERSBIN | H50: CAVALIRI | I50: SHOPRITE | J50: WASI | K50: SPICE& PACK | L50: MAKRO | M50: WAGES | N50: OTHERS | O50: WEEKLY DATES | Q50: TOTALS
O51: =A51 -> 0 | Q51: =SUM(C51:N51) -> 0
O52: =A52 -> 0 | Q52: =SUM(C52:N52) -> 0
O53: =A53 -> 0 | Q53: =SUM(C53:N53) -> 0
O54: =A54 -> 0 | Q54: =SUM(C54:N54) -> 0
A55: WEEKLY TOTALS | C55: =SUM(C51:C54) -> 0 | D55: =SUM(D51:D54) -> 0 | E55: =SUM(E51:E54) -> 0 | F55: =SUM(F51:F54) -> 0 | G55: =SUM(G51:G54) -> 0 | H55: =SUM(H51:H54) -> 0 | I55: =SUM(I51:I54) -> 0 | J55: =SUM(J51:J54) -> 0 | ... O55: =SUM(O51:O54) -> 0 | P55: SEPTEMBER | Q55: =SUM(Q51:Q54) -> 0
A56: WEEKLY DATES | C56: ELEC | D56: FUEL/TOLL GATES | E56: HYPER SWEETS | F56: CHIPKINS | G56: BAKERSBIN | H56: CAVALIRI | I56: SHOPRITE | J56: WASI | K56: SPICE& PACK | L56: MAKRO | M56: WAGES | N56: OTHERS | O56: WEEKLY DATES | Q56: TOTALS
O57: =A57 -> 0 | Q57: =SUM(C57:N57) -> 0
O58: =A58 -> 0 | Q58: =SUM(C58:N58) -> 0
O59: =A59 -> 0 | Q59: =SUM(C59:N59) -> 0
O60: =A60 -> 0 | Q60: =SUM(C60:N60) -> 0
A61: WEEKLY TOTALS | C61: =SUM(C57:C60) -> 0 | D61: =SUM(D57:D60) -> 0 | E61: =SUM(E57:E60) -> 0 | F61: =SUM(F57:F60) -> 0 | G61: =SUM(G57:G60) -> 0 | H61: =SUM(H57:H60) -> 0 | I61: =SUM(I57:I60) -> 0 | J61: =SUM(J57:J60) -> 0 | ... O61: =SUM(O57:O60) -> 0 | P61: OCTOBER | Q61: =SUM(Q57:Q60) -> 0
A62: WEEKLY DATES | C62: ELEC | D62: FUEL/TOLL GATES | E62: HYPER SWEETS | F62: CHIPKINS | G62: BAKERSBIN | H62: CAVALIRI | I62: SHOPRITE | J62: WASI | K62: SPICE& PACK | L62: MAKRO | M62: WAGES | N62: OTHERS | O62: WEEKLY DATES | Q62: TOTALS
O63: =A63 -> 0 | Q63: =SUM(C63:N63) -> 0
O64: =A64 -> 0 | Q64: =SUM(C64:N64) -> 0
O65: =A65 -> 0 | Q65: =SUM(C65:N65) -> 0
O66: =A66 -> 0 | Q66: =SUM(C66:N66) -> 0
A67: WEEKLY TOTALS | C67: =SUM(C63:C66) -> 0 | D67: =SUM(D63:D66) -> 0 | E67: =SUM(E63:E66) -> 0 | F67: =SUM(F63:F66) -> 0 | G67: =SUM(G63:G66) -> 0 | H67: =SUM(H63:H66) -> 0 | I67: =SUM(I63:I66) -> 0 | J67: =SUM(J63:J66) -> 0 | ... O67: =SUM(O63:O66) -> 0 | P67: NOVEMBER | Q67: =SUM(Q63:Q66) -> 0
A68: WEEKLY DATES | C68: ELEC | D68: FUEL/TOLL GATES | E68: HYPER SWEETS | F68: CHIPKINS | G68: BAKERSBIN | H68: CAVALIRI | I68: SHOPRITE | J68: WASI | K68: SPICE& PACK | L68: MAKRO | M68: WAGES | N68: OTHERS | O68: WEEKLY DATES | Q68: TOTALS
O69: =A69 -> 0 | Q69: =SUM(C69:N69) -> 0
O70: =A70 -> 0 | Q70: =SUM(C70:N70) -> 0
O71: =A71 -> 0 | Q71: =SUM(C71:N71) -> 0
O72: =A72 -> 0 | Q72: =SUM(C72:N72) -> 0
A73: WEEKLY TOTALS | C73: =SUM(C69:C72) -> 0 | D73: =SUM(D69:D72) -> 0 | E73: =SUM(E69:E72) -> 0 | F73: =SUM(F69:F72) -> 0 | G73: =SUM(G69:G72) -> 0 | H73: =SUM(H69:H72) -> 0 | I73: =SUM(I69:I72) -> 0 | J73: =SUM(J69:J72) -> 0 | ... O73: =SUM(O69:O72) -> 0 | P73: DECEMBER | Q73: =SUM(Q69:Q72) -> 0

Sheet DAILY WEEKLY EXPENSES STOCK
B2: Week | C2: 30 DECEMBER - 5 JANUARY 2025 | L2: =C2 -> 30 DECEMBER - 5 JANUARY 2025 | AI2: =L2 -> 30 DECEMBER - 5 JANUARY 2025 | AW2: =AI2 -> 30 DECEMBER - 5 JANUARY 2025 | AX2: 22 - 28 MARCH 2021
G3: Flour | I3: Wsugar | K3: Bsugar | M3: Oil | O3: Eggs | Q3: Ricoffy | S3: Wspoon | U3: IcingS | W3: Bpowder | Y3: Bicarb | AA3: Cocoa | AC3: Milk | AE3: Carrots | AG3: Ccheese | AI3: Salt | AK3: Vanilla | AM3: Lemon Juice | AO3: Choc Slabs | AQ3: Van Slabs | AS3: Cinnamon | AU3: Red Cherries | AW3: Domes | AY3: Bases | BA3: Vinegar | BC3: Pecan Nuts | BE3: Cremora
B4: Date | C4: Total | F4: Supplier | G4: 12.5kg | I4: 10kg | K4: 10kg | M4: 5LITRES | O4: 180 | Q4: 750G | S4: 25kg | U4: 25kg | W4: 20kg | Y4: 25kg | AA4: 25kg | AC4: 6 x 1litres | AE4: 5kg | AG4: 5kg | AI4: 1kg | AK4: 3 LITRE | AM4: 2 L | AO4: 20 | AQ4: 20 | AS4: 5kg | AU4: 6 KG | AW4: 100 | AY4: 100 | BA4: 5litres | BC4: 10kg | BE4: 750G
C5: Amount | E5: OTHERS | F5: Price item | G5: 151 | I5: 167.99 | K5: 144.99 | M5: 169.99 | O5: 274.99 | Q5: 135 | S5: 910.5 | U5: 460.75 | W5: 1048.95 | Y5: 772.8 | AA5: 3450 | AC5: 99.99 | AE5: 29.99 | AG5: 548 | AI5: 4.99 | AK5: 132.25 | AM5: 47.99 | AO5: 560 | AQ5: 560 | AS5: 613.5 | AU5: 313.9 | AW5: 405.8 | AY5: 218.99 | BA5: 24.99 | BC5: 1425 | BE5: 54.99
B6: 45656 | C6: 1125.31 | E6: DIESEL
C7: 194.96 | E7: AE BARB
C8: 1500 | E8: ELECTRICITY
C9: 7.99 | E9: FAMILY STORE
C10: 439.88 | F10: SHOPRITE | AE10: 10 | AF10: 299.9 | AK10: 2 | AL10: 139.98
C11: 679.8 | F11: MAKRO | AK11: 4 | AL11: 679.8
C12: 6995.64 | F12: WASI | G12: 9 | H12: 1259.91 | I12: 2 | J12: 409.98 | K12: 4 | L12: 727.96 | M12: 12 | N12: 1739.88 | O12: 18 | P12: =1820+520 -> 2340 | W12: 6 | X12: 329.94 | AM12: 1 | AN12: 49.99 | BA12: 1 | BB12: 27.99 | BE12: 1 | BF12: 59.99
C13: =32+146 -> 178 | E13: TBANTU
B16: MON
C17: =SUM(C6:C16) -> 11121.58
B18: 45657 | C18: =79+79+744.67+1000 -> 1902.67 | E18: DIESEL/TOLL GATES
C19: 3176 | F19: BAKERSBIN | AW19: 2 | AX19: 1969 | AY19: 2 | AZ19: 1207
C20: 252 | E20: BACK 2 BASICS
C21: 5765.73 | F21: WASI | G21: 4 | H21: 559.96 | I21: 2 | J21: 409.98 | K21: 8 | L21: 1455.92 | M21: 8 | N21: 1159.92 | O21: 5 | P21: 1850 | W21: 4 | X21: 219.96 | BE21: 1 | BF21: 59.99
C22: 286.9 | F22: SHOPRITE | AE22: 9 | AF22: 269.91
C23: 990.23 | E23: PNP
C24: 570 | E24: SOAP CENTRE
C25: 90 | E25: TBANTU
B26: TUE | C26: 6000 | F26: EGGS | O26: 10 | P26: 6000
C27: =SUM(C18:C26) -> 19033.53
B28: 45658 | C28: 1100 | E28: DIESEL
B29: WED
C30: =SUM(C28:C29) -> 1100
B31: 45659 | C31: 300 | E31: DIESEL
C32: 131.98 | F32: PNP | W32: 2 | X32: 131.98
C33: 6147.5 | F33: WASI | G33: 12 | H33: 1643.88 | I33: 6 | J33: 617.94 | K33: 6 | L33: 1091.94 | M33: 12 | N33: 1739.88 | W33: 6 | X33: 539.94 | AC33: 4 | AD33: 395.96 | AI33: 2 | AJ33: 11.98 | BA33: 1 | BB33: 55.98
B34: THU | C34: 7587.25 | F34: ACE | AW34: 15 | AX34: 4578.83 | AY34: 15 | AZ34: 3008.42
C35: =SUM(C31:C34) -> 14166.73
B36: 45660 | C36: 704.64 | E36: DIESEL
C37: 469.89 | F37: SHOPRITE | AC37: 2 | AD37: 199.98 | AE37: 6 | AF37: =AE37*29.99 -> 179.94 | BA37: 3 | BB37: 89.97
B41: FRI
C42: =SUM(C36:C41) -> 1174.53
B43: 45661 | C43: 18010 | E43: WAGES
C44: 750 | E44: DIESEL
C45: 1500 | E45: ELECTRICITY
C46: 209.93 | F46: SHOPRITE | AE46: 5 | AF46: 149.95
C47: 5716.55 | F47: WASI | G47: 8 | H47: 1095.92 | I47: 4 | J47: 411.96 | K47: 6 | L47: 1091.94 | M47: 12 | N47: 1739.88 | Q47: 1 | R47: 134.99 | W47: 6 | X47: 539.94 | AC47: 6 | AD47: 593.94 | AM47: 1 | AN47: 49.99 | BE47: 1 | BF47: 57.99
B50: SAT
C51: =SUM(C43:C50) -> 26186.48
B52: 45662 | C52: 189.17 | E52: AE BARB CS
C53: 178.98 | E53: PNP
C54: 40 | E54: WAS STORE
B58: SUN
C59: =SUM(C52:C58) -> 408.15
B60: WEEKLY GRAND TOTAL | G60: =SUM(G17:G58) -> 24 | H60: =SUM(H17:H58) -> 3299.76 | I60: =SUM(I17:I58) -> 12 | J60: =SUM(J17:J58) -> 1439.88 | K60: =SUM(K17:K58) -> 20 | L60: =SUM(L17:L58) -> 3639.8 | M60: =SUM(M17:M58) -> 32 | N60: =SUM(N17:N58) -> 4639.68 | ... AD60: =SUM(AD17:AD58) -> 1189.88 | AE60: =SUM(AE17:AE59) -> 20 | AF60: =SUM(AF17:AF59) -> 599.8 | AG60: =SUM(AG17:AG59) -> 0 | AH60: =SUM(AH17:AH59) -> 0 | AI60: =SUM(AI17:AI59) -> 2 | AJ60: =SUM(AJ17:AJ59) -> 11.98 | AK60: =SUM(AK17:AK59) -> 0 | AL60: =SUM(AL17:AL59) -> 0 | ... BF60: =SUM(BF17:BF59) -> 117.98
C61: =SUM(C59,C51,C42,C35,C30,C27,C17) -> 73191 | G61: Flour | I61: Wsugar | K61: Bsugar | M61: Oil | O61: Eggs | Q61: Ricoffy | S61: Wspoon | U61: IcingS | W61: Bpowder | Y61: Bicarb | AA61: Cocoa | AC61: Milk | AE61: Carrots | AG61: Ccheese | AI61: Salt | AK61: Vanilla | AM61: Lemon Juice | AO61: Choc Slabs | AQ61: Van Slabs | AS61: Cinnamon | AU61: Red Cherries | AW61: Domes | AY61: Bases | BA61: Vinegar | BC61: Pecan Nuts | BE61: Cremora
G62: 12.5kg | I62: 10kg | K62: 10kg | M62: 5LITRES | O62: 180 | Q62: 750G | S62: 25kg | U62: 25kg | W62: 20kg | Y62: 25kg | AA62: 25kg | AC62: 6 x 1litres | AE62: 5kg | AG62: 5kg | AI62: 1kg | AK62: 3 LITRE | AM62: 2 L | AO62: 20 | AQ62: 20 | AS62: 5kg | AU62: 6 KG | AW62: 100 | AY62: 100 | BA62: 5litres | BC62: 10kg | BE62: 750G
G63: 151 | I63: 167.99 | K63: 144.99 | M63: 169.99 | O63: 274.99 | Q63: 102.99 | S63: 910.5 | U63: 460.75 | W63: 1048.95 | Y63: 772.8 | AA63: 3450 | AC63: 89.99 | AE63: 39.99 | AG63: 498 | AI63: 4.99 | AK63: 132.25 | AM63: 47.99 | AO63: 560 | AQ63: 560 | AS63: 613.5 | AU63: 313.9 | AW63: 405.8 | AY63: 218.99 | BA63: 24.99 | BC63: 1425 | BE63: 54.99
C64: =L64 -> 30 DECEMBER - 5 JANUARY 2025 | L64: =AL64 -> 30 DECEMBER - 5 JANUARY 2025 | AL64: =AW64 -> 30 DECEMBER - 5 JANUARY 2025 | AW64: =AW2 -> 30 DECEMBER - 5 JANUARY 2025 | AX64: 22 - 28 MARCH 2021
B66: Week | C66: 6 - 12 JANUARY 2025 | L66: =C66 -> 6 - 12 JANUARY 2025 | AI66: =L66 -> 6 - 12 JANUARY 2025 | AW66: =AI66 -> 6 - 12 JANUARY 2025 | AX66: 22 - 28 MARCH 2021
G67: Flour | I67: Wsugar | K67: Bsugar | M67: Oil | O67: Eggs | Q67: Ricoffy | S67: Wspoon | U67: IcingS | W67: Bpowder | Y67: Bicarb | AA67: Cocoa | AC67: Milk | AE67: Carrots | AG67: Ccheese | AI67: Salt | AK67: Vanilla | AM67: Lemon Juice | AO67: Choc Slabs | AQ67: Van Slabs | AS67: Cinnamon | AU67: Red Cherries | AW67: Domes | AY67: Bases | BA67: Vinegar | BC67: Pecan Nuts | BE67: Cremora
B68: Date | C68: Total | F68: Supplier | G68: 12.5kg | I68: 10kg | K68: 10kg | M68: 5LITRES | O68: 180 | Q68: 750G | S68: 25kg | U68: 25kg | W68: 20kg | Y68: 25kg | AA68: 25kg | AC68: 6 x 1litres | AE68: 5kg | AG68: 5kg | AI68: 1kg | AK68: 3 LITRE | AM68: 2 L | AO68: 20 | AQ68: 20 | AS68: 5kg | AU68: 6 KG | AW68: 100 | AY68: 100 | BA68: 5litres | BC68: 10kg | BE68: 750G
C69: Amount | E69: OTHERS | F69: Price item | G69: 151 | I69: 167.99 | K69: 144.99 | M69: 169.99 | O69: 274.99 | Q69: 135 | S69: 910.5 | U69: 460.75 | W69: 1048.95 | Y69: 772.8 | AA69: 3450 | AC69: 99.99 | AE69: 29.99 | AG69: 548 | AI69: 4.99 | AK69: 132.25 | AM69: 47.99 | AO69: 560 | AQ69: 560 | AS69: 613.5 | AU69: 313.9 | AW69: 405.8 | AY69: 218.99 | BA69: 24.99 | BC69: 1425 | BE69: 54.99
B70: 45663 | C70: 575.18 | E70: DIESEL
C71: 289 | E71: FAMILY STORE | O71: 3 | P71: 289
C72: 575 | F72: CAVALIERI | AG72: 1 | AH72: 575
C73: 299.9 | F73: SHOPRITE | AE73: 10 | AF73: 299.9
C74: 2472 | F74: HYPER SWEETS | AO74: 40 | AP74: 1200 | AQ74: 40 | AR74: 1200
C75: 570 | E75: SOAP CENTRE
C76: 6021.55 | F76: WASI | G76: 10 | H76: 1369.9 | I76: 4 | J76: 411.96 | K76: 8 | L76: 1455.92 | M76: 12 | N76: 1739.88 | W76: 6 | X76: 539.94 | AC76: 4 | AD76: 395.96 | BE76: 1 | BF76: 57.99
C77: 1733.8 | F77: MAKRO | AK77: 5 | AL77: 849.75
C78: 12725 | E78: WAGES
B80: MON
C81: =SUM(C70:C80) -> 25261.43
B82: 45664 | C82: 2862.52 | E82: DIESL/TOLL GATES
C83: =258.35 -> 258.35 | E83: ae barb cs
C84: 51 | E84: AE CAROLINA
C85: 115 | E85: AE CAROLINA
C86: 86.96 | E86: PROBUILD
C87: 6000 | F87: HEIDEL EGGS | O87: 10 | P87: 6000
C88: 7522.57 | F88: WASI | G88: 8 | H88: 1095.92 | I88: 6 | J88: 617.94 | K88: 8 | L88: 1455.92 | M88: 10 | N88: 1449.9 | W88: 5 | X88: 449.95 | AC88: 5 | AD88: 494.95 | BE88: 1 | BF88: 57.99
C89: 28014 | F89: CHIPKINS | S89: 6 | T89: =3312+1587 -> 4899 | U89: 25 | V89: 13225 | AA89: 2 | AB89: 8050
B90: TUE
C91: =SUM(C82:C90) -> 44910.4
B92: 45665 | C92: 800 | E92: diesel
B93: WED
C94: =SUM(C92:C93) -> 800
B95: 45666 | C95: 1157.22 | E95: diesel/toll gates
C96: 25 | E96: HOME & PARTY STORE
C97: 122.98 | F97: PNP | AC97: 1 | AD97: 94.99
C98: 299.9 | F98: SHOPRITE | AE98: 10 | AF98: 299.9
C99: 6691.45 | F99: WASI | G99: 10 | H99: 1369.9 | I99: 6 | J99: 617.94 | K99: 8 | L99: 1455.92 | M99: 12 | N99: 1739.88 | Q99: 2 | R99: 269.98 | W99: 6 | X99: 281.94 | BA99: 2 | BB99: 55.98 | BE99: 1 | BF99: 57.99
C100: 7587.25 | F100: ACE | AW100: 15 | AX100: 4578.83 | AY100: 15 | AZ100: 3008.42
C101: 4241 | E101: POINT S
B104: THU
C105: =SUM(C95:C104) -> 20124.8
B106: 45667 | C106: 804.72 | E106: DIESEL
B111: FRI
C112: =SUM(C106:C111) -> 804.72
B113: 45668 | C113: 728.14 | E113: DIESEL
C114: 2650 | E114: DUNLOP
C115: 6700 | E115: WAGES
B120: SAT
C121: =SUM(C113:C120) -> 10078.14
B122: 45669 | C122: 1633 | E122: AE ABRB/ELECTRICITY
C123: =19.99+5010.59 -> 5030.58 | F123: WASI | G123: 10 | H123: 1399.9 | I123: 4 | J123: 411.96 | K123: 6 | L123: 1091.94 | M123: 8 | N123: 1199.92 | W123: 6 | X123: 257.94 | AC123: 5 | AD123: 494.95 | BA123: 1 | BB123: 27.99 | BE123: 1 | BF123: 75.99
...

Sheet MONTHLY STOCK
A2: MONTHLY STOCK
A3: 45658 | C3: STOCK | F3: Flour | H3: Wsugar | J3: Bsugar | L3: Oil | N3: Eggs | P3: Ricoffy | R3: Wspoon | T3: IcingS | V3: Bpowder | X3: Bicarb | Z3: Cocoa | AB3: Milk | AD3: Carrots | AF3: Ccheese | AH3: Salt | AJ3: Vanilla | AL3: Lemon Juice | AN3: Choc Slabs | AP3: Van Slabs | AR3: Cinnamon | AT3: Red Cherries | AV3: Domes | AX3: Bases | AZ3: Vinegar | BB3: Pecan Nuts | BD3: Cremora
F4: 12.5kg | H4: 10kg | J4: 10kg | L4: 5LITRES | N4: 180 | P4: 750G | R4: 25kg | T4: 25kg | V4: 20kg | X4: 25kg | Z4: 25kg | AB4: 6 x 1litres | AD4: 5kg | AF4: 5kg | AH4: 1kg | AJ4: 3 LITRE | AL4: 2 L | AN4: 20 | AP4: 20 | AR4: 5kg | AT4: 6 KG | AV4: 100 | AX4: 100 | AZ4: 5litres | BB4: 10kg | BD4: 750G
C5: WEEKLY DATES | F5: QUANTITY | G5: TOTALS | H5: QUANTITY | I5: TOTALS | J5: QUANTITY | K5: TOTALS | L5: QUANTITY | M5: TOTALS | N5: QUANTITY | O5: TOTALS | P5: QUANTITY | Q5: TOTALS | R5: QUANTITY | S5: TOTALS | T5: QUANTITY | U5: TOTALS | V5: QUANTITY | W5: TOTALS | X5: QUANTITY | Y5: TOTALS | Z5: QUANTITY | AA5: TOTALS | AB5: QUANTITY | AC5: TOTALS | AD5: QUANTITY | AE5: TOTALS | AF5: QUANTITY | AG5: TOTALS | AH5: QUANTITY | AI5: TOTALS | AJ5: QUANTITY | AK5: TOTALS | AL5: QUANTITY | AM5: TOTALS | AN5: QUANTITY | AO5: TOTALS | AP5: QUANTITY | AQ5: TOTALS | AR5: QUANTITY | AS5: TOTALS | AT5: QUANTITY | AU5: TOTALS | AV5: QUANTITY | AW5: TOTALS | AX5: QUANTITY | AY5: TOTALS | AZ5: QUANTITY | BA5: TOTALS | BB5: QUANTITY | BC5: TOTALS | BD5: QUANTITY | BE5: TOTALS
C6: 30 DEC - 5 JAN 2025 | F6: ='DAILY WEEKLY EXPENSES STOCK'!G60 -> 24 | G6: ='DAILY WEEKLY EXPENSES STOCK'!H60 -> 3299.76 | H6: ='DAILY WEEKLY EXPENSES STOCK'!I60 -> 12 | I6: ='DAILY WEEKLY EXPENSES STOCK'!J60 -> 1439.88 | J6: ='DAILY WEEKLY EXPENSES STOCK'!K60 -> 20 | K6: ='DAILY WEEKLY EXPENSES STOCK'!L60 -> 3639.8 | L6: ='DAILY WEEKLY EXPENSES STOCK'!M60 -> 32 | M6: ='DAILY WEEKLY EXPENSES STOCK'!N60 -> 4639.68 | ... BE6: ='DAILY WEEKLY EXPENSES STOCK'!BF60 -> 117.98
C7: 6 - 12 JAN 2025 | F7: ='DAILY WEEKLY EXPENSES STOCK'!G130 -> 28 | G7: ='DAILY WEEKLY EXPENSES STOCK'!H130 -> 3865.72 | H7: ='DAILY WEEKLY EXPENSES STOCK'!I130 -> 16 | I7: ='DAILY WEEKLY EXPENSES STOCK'!J130 -> 1647.84 | J7: ='DAILY WEEKLY EXPENSES STOCK'!K130 -> 22 | K7: ='DAILY WEEKLY EXPENSES STOCK'!L130 -> 4003.78 | L7: ='DAILY WEEKLY EXPENSES STOCK'!M130 -> 30 | M7: ='DAILY WEEKLY EXPENSES STOCK'!N130 -> 4389.7 | ... BE7: ='DAILY WEEKLY EXPENSES STOCK'!BF130 -> 191.97
C8: 13 - 19 JAN 2025 | F8: 29 | G8: 3972.71 | H8: 11 | I8: 1540.89 | J8: 22 | K8: 4003.78 | L8: 31 | M8: 4645.75 | N8: 18 | O8: 9725 | P8: 1 | Q8: 134.99 | R8: 0 | S8: 0 | T8: 0 | U8: 0 | V8: 16 | W8: 687.84 | X8: 0 | Y8: 0 | Z8: 0 | AA8: 0 | AB8: 19 | AC8: 1880.81 | AD8: 26 | AE8: 909.74 | AF8: 0 | AG8: 0 | AH8: 2 | AI8: 11.98 | AJ8: 0 | AK8: 0 | AL8: 0 | AM8: 0 | AN8: 0 | AO8: 0 | AP8: 0 | AQ8: 0 | AR8: 0 | AS8: 0 | AT8: 0 | AU8: 0 | AV8: 0 | AW8: 0 | AX8: 0 | AY8: 0 | AZ8: 5 | BA8: 139.95 | BB8: 0 | BC8: 0 | BD8: 3 | BE8: 227.97
C9: 20 - 26 JAN 2025 | F9: 24 | G9: 3287.76 | H9: 12 | I9: 1235.88 | J9: 20 | K9: 3639.8 | L9: 32 | M9: 5023.68 | N9: 0 | O9: 0 | P9: 2 | Q9: 269.98 | R9: 0 | S9: 0 | T9: 0 | U9: 0 | V9: 14 | W9: 601.86 | X9: 0 | Y9: 0 | Z9: 0 | AA9: 0 | AB9: 18 | AC9: 1777.82 | AD9: 10 | AE9: 349.9 | AF9: 0 | AG9: 0 | AH9: 2 | AI9: 11.98 | AJ9: 0 | AK9: 0 | AL9: 1 | AM9: 49.99 | AN9: 0 | AO9: 0 | AP9: 0 | AQ9: 0 | AR9: 0 | AS9: 0 | AT9: 0 | AU9: 0 | AV9: 20 | AW9: 4149.3 | AX9: 20 | AY9: 4149.3 | AZ9: 3 | BA9: 80.97 | BB9: 0 | BC9: 0 | BD9: 2 | BE9: 151.98
C10: GRAND TOTALS | F10: =SUM(F6:F9) -> 105 | G10: =SUM(G6:G9) -> 14425.95 | H10: =SUM(H6:H9) -> 51 | I10: =SUM(I6:I9) -> 5864.49 | J10: =SUM(J6:J9) -> 84 | K10: =SUM(K6:K9) -> 15287.16 | L10: =SUM(L6:L9) -> 125 | M10: =SUM(M6:M9) -> 18698.81 | ... BE10: =SUM(BE6:BE9) -> 689.9
A11: 45689 | C11: STOCK | F11: Flour | H11: Wsugar | J11: Bsugar | L11: Oil | N11: Eggs | P11: Ricoffy | R11: Wspoon | T11: IcingS | V11: Bpowder | X11: Bicarb | Z11: Cocoa | AB11: Milk | AD11: Carrots | AF11: Ccheese | AH11: Salt | AJ11: Vanilla | AL11: Lemon Juice | AN11: Choc Slabs | AP11: Van Slabs | AR11: Cinnamon | AT11: Red Cherries | AV11: Domes | AX11: Bases | AZ11: Vinegar | BB11: Pecan Nuts | BD11: Cremora
F12: 12.5kg | H12: 10kg | J12: 10kg | L12: 5LITRES | N12: 180 | P12: 750G | R12: 25kg | T12: 25kg | V12: 20kg | X12: 25kg | Z12: 25kg | AB12: 6 x 1litres | AD12: 5kg | AF12: 5kg | AH12: 1kg | AJ12: 3 LITRE | AL12: 2 L | AN12: 20 | AP12: 20 | AR12: 5kg | AT12: 6 KG | AV12: 100 | AX12: 100 | AZ12: 5litres | BB12: 10kg | BD12: 750G
C13: WEEKLY DATES | F13: QUANTITY | G13: TOTALS | H13: QUANTITY | I13: TOTALS | J13: QUANTITY | K13: TOTALS | L13: QUANTITY | M13: TOTALS | N13: QUANTITY | O13: TOTALS | P13: QUANTITY | Q13: TOTALS | R13: QUANTITY | S13: TOTALS | T13: QUANTITY | U13: TOTALS | V13: QUANTITY | W13: TOTALS | X13: QUANTITY | Y13: TOTALS | Z13: QUANTITY | AA13: TOTALS | AB13: QUANTITY | AC13: TOTALS | AD13: QUANTITY | AE13: TOTALS | AF13: QUANTITY | AG13: TOTALS | AH13: QUANTITY | AI13: TOTALS | AJ13: QUANTITY | AK13: TOTALS | AL13: QUANTITY | AM13: TOTALS | AN13: QUANTITY | AO13: TOTALS | AP13: QUANTITY | AQ13: TOTALS | AR13: QUANTITY | AS13: TOTALS | AT13: QUANTITY | AU13: TOTALS | AV13: QUANTITY | AW13: TOTALS | AX13: QUANTITY | AY13: TOTALS | AZ13: QUANTITY | BA13: TOTALS | BB13: QUANTITY | BC13: TOTALS | BD13: QUANTITY | BE13: TOTALS
C14: 27 JAN - 2 FEB 2025 | F14: 27 | G14: 3698.73 | H14: 10 | I14: 1541.9 | J14: 24 | K14: 4367.76 | L14: 34 | M14: 5307.78 | N14: 10 | O14: 6000 | P14: 2 | Q14: 269.98 | R14: 0 | S14: 0 | T14: 0 | U14: 0 | V14: 16 | W14: 687.84 | X14: 0 | Y14: 0 | Z14: 0 | AA14: 0 | AB14: 19 | AC14: 1880.81 | AD14: 20 | AE14: 729.8 | AF14: 0 | AG14: 0 | AH14: 0 | AI14: 0 | AJ14: 0 | AK14: 0 | AL14: 1 | AM14: 49.99 | AN14: 0 | AO14: 0 | AP14: 0 | AQ14: 0 | AR14: 0 | AS14: 0 | AT14: 0 | AU14: 0 | AV14: 15 | AW14: 3578.77 | AX14: 15 | AY14: 3578.77 | AZ14: 3 | BA14: 81.97 | BB14: 0 | BC14: 0 | BD14: 2 | BE14: 151.98 | BG14: ='DAILY WEEKLY EXPENSES STOCK'!#REF! -> #REF!
C15: 3 - 9 FEB 2025 | F15: 26 | G15: 3579.74 | H15: 11 | I15: 1876.89 | J15: 23 | K15: 4185.77 | L15: 34 | M15: 5557.66 | N15: 16 | O15: 8130 | P15: 2 | Q15: 269.98 | R15: 0 | S15: 0 | T15: 0 | U15: 0 | V15: 16 | W15: 687.84 | X15: 0 | Y15: 0 | Z15: 0 | AA15: 0 | AB15: 18 | AC15: 1781.82 | AD15: 27 | AE15: 944.73 | AF15: 0 | AG15: 0 | AH15: 4 | AI15: 23.96 | AJ15: 3 | AK15: 509.8 | AL15: 1 | AM15: 49.99 | AN15: 20 | AO15: 600 | AP15: 20 | AQ15: 600 | AR15: 0 | AS15: 0 | AT15: 0 | AU15: 0 | AV15: 15 | AW15: 3578.77 | AX15: 15 | AY15: 3578.77 | AZ15: 3 | BA15: 81.97 | BB15: 0 | BC15: 0 | BD15: 2 | BE15: 135.98
C16: 10 - 16 FEB 2025 | F16: 30 | G16: 4139.7 | H16: 10 | I16: 1699.9 | J16: 24 | K16: 4367.76 | L16: 33 | M16: 5510.67 | N16: 15 | O16: 5324.94 | P16: 3 | Q16: 404.97 | R16: 0 | S16: 0 | T16: 0 | U16: 0 | V16: 16 | W16: 687.84 | X16: 0 | Y16: 0 | Z16: 0 | AA16: 0 | AB16: 16 | AC16: 1583.84 | AD16: 24 | AE16: 819.76 | AF16: 1 | AG16: 575 | AH16: 0 | AI16: 0 | AJ16: 4 | AK16: 679.8 | AL16: 0 | AM16: 0 | AN16: 0 | AO16: 0 | AP16: 0 | AQ16: 0 | AR16: 0 | AS16: 0 | AT16: 0 | AU16: 0 | AV16: 15 | AW16: 3578.77 | AX16: 15 | AY16: 3578.77 | AZ16: 3 | BA16: 80.97 | BB16: 0 | BC16: 0 | BD16: 3 | BE16: 195.97
C17: 17 - 23 FEB 2025 | F17: 17 | G17: 2328.83 | H17: 4 | I17: 819.96 | J17: 14 | K17: 2547.86 | L17: 16 | M17: 2671.84 | N17: 9 | O17: 3184.95 | P17: 1 | Q17: 134.99 | R17: 6 | S17: 5451 | T17: 18 | U17: 9522 | V17: 8 | W17: 343.92 | X17: 1 | Y17: 772.8 | Z17: 2 | AA17: 8050 | AB17: 16 | AC17: 1285.84 | AD17: 18 | AE17: 629.82 | AF17: 0 | AG17: 0 | AH17: 0 | AI17: 0 | AJ17: 0 | AK17: 0 | AL17: 1 | AM17: 49.99 | AN17: 0 | AO17: 0 | AP17: 0 | AQ17: 0 | AR17: 0 | AS17: 0 | AT17: 2 | AU17: 824.33 | AV17: 10 | AW17: 2385.85 | AX17: 10 | AY17: 2385.85 | AZ17: 2 | BA17: 53.98 | BB17: 0 | BC17: 0 | BD17: 2 | BE17: 151.98
C18: GRAND TOTALS | F18: =SUM(F14:F17) -> 100 | G18: =SUM(G14:G17) -> 13747 | H18: =SUM(H14:H17) -> 35 | I18: =SUM(I14:I17) -> 5938.65 | J18: =SUM(J14:J17) -> 85 | K18: =SUM(K14:K17) -> 15469.15 | L18: =SUM(L14:L17) -> 117 | M18: =SUM(M14:M17) -> 19047.95 | ... BE18: =SUM(BE14:BE17) -> 635.91
A19: 45717 | C19: STOCK | F19: Flour | H19: Wsugar | J19: Bsugar | L19: Oil | N19: Eggs | P19: Ricoffy | R19: Wspoon | T19: IcingS | V19: Bpowder | X19: Bicarb | Z19: Cocoa | AB19: Milk | AD19: Carrots | AF19: Ccheese | AH19: Salt | AJ19: Vanilla | AL19: Lemon Juice | AN19: Choc Slabs | AP19: Van Slabs | AR19: Cinnamon | AT19: Red Cherries | AV19: Domes | AX19: Bases | AZ19: Vinegar | BB19: Pecan Nuts | BD19: Cremora
F20: 12.5kg | H20: 10kg | J20: 10kg | L20: 5LITRES | N20: 180 | P20: 750G | R20: 25kg | T20: 25kg | V20: 20kg | X20: 25kg | Z20: 25kg | AB20: 6 x 1litres | AD20: 5kg | AF20: 5kg | AH20: 1kg | AJ20: 3 LITRE | AL20: 2 L | AN20: 20 | AP20: 20 | AR20: 5kg | AT20: 6 KG | AV20: 100 | AX20: 100 | AZ20: 5litres | BB20: 10kg | BD20: 750G
C21: WEEKLY DATES | F21: QUANTITY | G21: TOTALS | H21: QUANTITY | I21: TOTALS | J21: QUANTITY | K21: TOTALS | L21: QUANTITY | M21: TOTALS | N21: QUANTITY | O21: TOTALS | P21: QUANTITY | Q21: TOTALS | R21: QUANTITY | S21: TOTALS | T21: QUANTITY | U21: TOTALS | V21: QUANTITY | W21: TOTALS | X21: QUANTITY | Y21: TOTALS | Z21: QUANTITY | AA21: TOTALS | AB21: QUANTITY | AC21: TOTALS | AD21: QUANTITY | AE21: TOTALS | AF21: QUANTITY | AG21: TOTALS | AH21: QUANTITY | AI21: TOTALS | AJ21: QUANTITY | AK21: TOTALS | AL21: QUANTITY | AM21: TOTALS | AN21: QUANTITY | AO21: TOTALS | AP21: QUANTITY | AQ21: TOTALS | AR21: QUANTITY | AS21: TOTALS | AT21: QUANTITY | AU21: TOTALS | AV21: QUANTITY | AW21: TOTALS | AX21: QUANTITY | AY21: TOTALS | AZ21: QUANTITY | BA21: TOTALS | BB21: QUANTITY | BC21: TOTALS | BD21: QUANTITY | BE21: TOTALS
C22: 24 FEB - 2 MAR 2025 | F22: 28 | G22: 3835.72 | H22: 8 | I22: 1639.92 | J22: 23 | K22: 4185.77 | L22: 32 | M22: 5379.8 | N22: 20 | O22: 6949.94 | P22: 1 | Q22: 134.99 | R22: 0 | S22: 0 | T22: 15 | U22: 7935 | V22: 14 | W22: 601.86 | X22: 0 | Y22: 0 | Z22: 0 | AA22: 0 | AB22: 19 | AC22: 1880.81 | AD22: 16 | AE22: 639.84 | AF22: 1 | AG22: 575 | AH22: 0 | AI22: 0 | AJ22: 5 | AK22: 849.75 | AL22: 0 | AM22: 0 | AN22: 20 | AO22: 600 | AP22: 20 | AQ22: 600 | AR22: 0 | AS22: 0 | AT22: 0 | AU22: 0 | AV22: 15 | AW22: 3578.77 | AX22: 15 | AY22: 3578.77 | AZ22: 3 | BA22: 80.97 | BB22: 0 | BC22: 0 | BD22: 3 | BE22: 227.97
C23: 3 - 9 MAR 2025 | F23: 32 | G23: 4419.68 | H23: 8 | I23: 1639.92 | J23: 27 | K23: 4913.73 | L23: 36 | M23: 6011.64 | N23: 17 | O23: 6074.96 | P23: 2 | Q23: 289.98 | R23: 12 | S23: 1886.9 | T23: 11 | U23: 6170.95 | V23: 14 | W23: 601.86 | X23: 0 | Y23: 0 | Z23: 0 | AA23: 0 | AB23: 20 | AC23: 1979.8 | AD23: 28 | AE23: 1123.72 | AF23: 0 | AG23: 0 | AH23: 0 | AI23: 0 | AJ23: 0 | AK23: 0 | AL23: 1 | AM23: 49.99 | AN23: 0 | AO23: 0 | AP23: 0 | AQ23: 0 | AR23: 0 | AS23: 0 | AT23: 0 | AU23: 0 | AV23: 0 | AW23: 0 | AX23: 0 | AY23: 0 | AZ23: 3 | BA23: 80.97 | BB23: 0 | BC23: 0 | BD23: 2 | BE23: 151.98
C24: 10 - 16 MAR 2025 | F24: 25 | G24: 3499.75 | H24: 6 | I24: 1229.94 | J24: 16 | K24: 2935.9 | L24: 28 | M24: 4711.84 | N24: 16 | O24: 5999.94 | P24: 2 | Q24: 289.99 | R24: 0 | S24: 0 | T24: 0 | U24: 0 | V24: 14 | W24: 601.86 | X24: 0 | Y24: 0 | Z24: 0 | AA24: 0 | AB24: 16 | AC24: 1627.84 | AD24: 21 | AE24: 944.79 | AF24: 0 | AG24: 0 | AH24: 2 | AI24: 11.98 | AJ24: 0 | AK24: 0 | AL24: 1 | AM24: 49.99 | AN24: 0 | AO24: 0 | AP24: 0 | AQ24: 0 | AR24: 0 | AS24: 0 | AT24: 0 | AU24: 0 | AV24: 10 | AW24: 2385.85 | AX24: 10 | AY24: 2385.85 | AZ24: 3 | BA24: 80.97 | BB24: 0 | BC24: 0 | BD24: 1 | BE24: 75.99
C25: 17 - 23 MAR 2025 | F25: 22 | G25: 3079.78 | H25: 6 | I25: 1229.94 | J25: 20 | K25: 3639.8 | L25: 26 | M25: 4401.74 | N25: 47 | O25: 5934.79 | P25: 2 | Q25: 289.98 | R25: 0 | S25: 0 | T25: 0 | U25: 0 | V25: 16 | W25: 729.84 | X25: 0 | Y25: 0 | Z25: 0 | AA25: 0 | AB25: 18 | AC25: 1781.82 | AD25: 16 | AE25: 719.84 | AF25: 0 | AG25: 0 | AH25: 0 | AI25: 0 | AJ25: 0 | AK25: 0 | AL25: 0 | AM25: 0 | AN25: 0 | AO25: 0 | AP25: 0 | AQ25: 0 | AR25: 0 | AS25: 0 | AT25: 0 | AU25: 0 | AV25: 15 | AW25: 3578.77 | AX25: 15 | AY25: 3578.77 | AZ25: 2 | BA25: 53.98 | BB25: 0 | BC25: 0 | BD25: 2 | BE25: 154.98
C26: GRAND TOTALS | F26: =SUM(F22:F25) -> 107 | G26: =SUM(G22:G25) -> 14834.93 | H26: =SUM(H22:H25) -> 28 | I26: =SUM(I22:I25) -> 5739.72 | J26: =SUM(J22:J25) -> 86 | K26: =SUM(K22:K25) -> 15675.2 | L26: =SUM(L22:L25) -> 122 | M26: =SUM(M22:M25) -> 20505.02 | ... BE26: =SUM(BE22:BE25) -> 610.92
A27: 45748 | C27: STOCK | F27: Flour | H27: Wsugar | J27: Bsugar | L27: Oil | N27: Eggs | P27: Ricoffy | R27: Wspoon | T27: IcingS | V27: Bpowder | X27: Bicarb | Z27: Cocoa | AB27: Milk | AD27: Carrots | AF27: Ccheese | AH27: Salt | AJ27: Vanilla | AL27: Lemon Juice | AN27: Choc Slabs | AP27: Van Slabs | AR27: Cinnamon | AT27: Red Cherries | AV27: Domes | AX27: Bases | AZ27: Vinegar | BB27: Pecan Nuts | BD27: Cremora
F28: 12.5kg | H28: 10kg | J28: 10kg | L28: 5LITRES | N28: 180 | P28: 750G | R28: 25kg | T28: 25kg | V28: 20kg | X28: 25kg | Z28: 25kg | AB28: 6 x 1litres | AD28: 5kg | AF28: 5kg | AH28: 1kg | AJ28: 3 LITRE | AL28: 2 L | AN28: 20 | AP28: 20 | AR28: 5kg | AT28: 6 KG | AV28: 100 | AX28: 100 | AZ28: 5litres | BB28: 10kg | BD28: 750G
C29: WEEKLY DATES | F29: QUANTITY | G29: TOTALS | H29: QUANTITY | I29: TOTALS | J29: QUANTITY | K29: TOTALS | L29: QUANTITY | M29: TOTALS | N29: QUANTITY | O29: TOTALS | P29: QUANTITY | Q29: TOTALS | R29: QUANTITY | S29: TOTALS | T29: QUANTITY | U29: TOTALS | V29: QUANTITY | W29: TOTALS | X29: QUANTITY | Y29: TOTALS | Z29: QUANTITY | AA29: TOTALS | AB29: QUANTITY | AC29: TOTALS | AD29: QUANTITY | AE29: TOTALS | AF29: QUANTITY | AG29: TOTALS | AH29: QUANTITY | AI29: TOTALS | AJ29: QUANTITY | AK29: TOTALS | AL29: QUANTITY | AM29: TOTALS | AN29: QUANTITY | AO29: TOTALS | AP29: QUANTITY | AQ29: TOTALS | AR29: QUANTITY | AS29: TOTALS | AT29: QUANTITY | AU29: TOTALS | AV29: QUANTITY | AW29: TOTALS | AX29: QUANTITY | AY29: TOTALS | AZ29: QUANTITY | BA29: TOTALS | BB29: QUANTITY | BC29: TOTALS | BD29: QUANTITY | BE29: TOTALS
C30: 24 - 30 MAR 2025 | F30: 30 | G30: 4136.7 | H30: 8 | I30: 1664.92 | J30: 24 | K30: 4367.76 | L30: 32 | M30: 5494.77 | N30: 44 | O30: 7539.82 | P30: 3 | Q30: 434.97 | R30: 0 | S30: 0 | T30: 0 | U30: 0 | V30: 14 | W30: 601.86 | X30: 0 | Y30: 0 | Z30: 1 | AA30: 4358 | AB30: 17 | AC30: 1682.83 | AD30: 28 | AE30: 1259.72 | AF30: 1 | AG30: 575 | AH30: 0 | AI30: 0 | AJ30: 5 | AK30: 849.75 | AL30: 1 | AM30: 43.99 | AN30: 20 | AO30: 300 | AP30: 20 | AQ30: 300 | AR30: 0 | AS30: 0 | AT30: 0 | AU30: 0 | AV30: 15 | AW30: 3578.77 | AX30: 15 | AY30: 3578.77 | AZ30: 4 | BA30: 107.96 | BB30: 0 | BC30: 0 | BD30: 1 | BE30: 75.99
C31: 31 MAR - 6 APR 2025 | F31: 12 | G31: 1655.88 | H31: 4 | I31: 819.96 | J31: 8 | K31: 1455.92 | L31: 12 | M31: 2075.88 | N31: 20 | O31: 3675 | P31: 0 | Q31: 0 | R31: 0 | S31: 0 | T31: 0 | U31: 0 | V31: 8 | W31: 343.92 | X31: 0 | Y31: 0 | Z31: 0 | AA31: 0 | AB31: 8 | AC31: 791.92 | AD31: 23 | AE31: 1149.77 | AF31: 0 | AG31: 0 | AH31: 0 | AI31: 0 | AJ31: 0 | AK31: 0 | AL31: 0 | AM31: 0 | AN31: 0 | AO31: 0 | AP31: 0 | AQ31: 0 | AR31: 0 | AS31: 0 | AT31: 0 | AU31: 0 | AV31: 15 | AW31: 3578.77 | AX31: 15 | AY31: 3578.77 | AZ31: 1 | BA31: 26.99 | BB31: 0 | BC31: 0 | BD31: 0 | BE31: 0
C32: 7 - 13 APR 2025 | F32: 23 | G32: 3150.77 | H32: 6 | I32: 1229.94 | J32: 21 | K32: 3821.79 | L32: 27 | M32: 4670.73 | N32: 45 | O32: 5849.55 | P32: 2 | Q32: 289.98 | R32: 22 | S32: 3763.12 | T32: 0 | U32: 0 | V32: 8 | W32: 413.94 | X32: 0 | Y32: 0 | Z32: 0 | AA32: 0 | AB32: 16 | AC32: 1583.84 | AD32: 22 | AE32: 784.78 | AF32: 1 | AG32: 548.32 | AH32: 0 | AI32: 0 | AJ32: 0 | AK32: 0 | AL32: 0 | AM32: 0 | AN32: 0 | AO32: 0 | AP32: 0 | AQ32: 0 | AR32: 0 | AS32: 0 | AT32: 0 | AU32: 0 | AV32: 15 | AW32: 3578.77 | AX32: 15 | AY32: 3578.77 | AZ32: 4 | BA32: 81.97 | BB32: 0 | BC32: 0 | BD32: 2 | BE32: 151.98
C33: 14 - 20 APR 2025 | F33: 40 | G33: 5479.6 | H33: 11 | I33: 2254.89 | J33: 34 | K33: 6187.66 | L33: 46 | M33: 7957.54 | N33: 40 | O33: 9854.79 | P33: 2 | Q33: 434.98 | R33: 0 | S33: 0 | T33: 0 | U33: 0 | V33: 24 | W33: 1783.76 | X33: 0 | Y33: 0 | Z33: 0 | AA33: 0 | AB33: 25 | AC33: 2474.75 | AD33: 38 | AE33: 1899.62 | AF33: 0 | AG33: 0 | AH33: 0 | AI33: 0 | AJ33: 0 | AK33: 0 | AL33: 1 | AM33: 49.99 | AN33: 0 | AO33: 0 | AP33: 0 | AQ33: 0 | AR33: 0 | AS33: 0 | AT33: 0 | AU33: 0 | AV33: 15 | AW33: 3578.77 | AX33: 15 | AY33: 3578.77 | AZ33: 5 | BA33: 139.95 | BB33: 0 | BC33: 0 | BD33: 1 | BE33: 75.99
C34: GRAND TOTALS | F34: =SUM(F30:F33) -> 105 | G34: =SUM(G30:G33) -> 14422.95 | H34: =SUM(H30:H33) -> 29 | I34: =SUM(I30:I33) -> 5969.71 | J34: =SUM(J30:J33) -> 87 | K34: =SUM(K30:K33) -> 15833.13 | L34: =SUM(L30:L33) -> 117 | M34: =SUM(M30:M33) -> 20198.92 | ... BE34: =SUM(BE30:BE33) -> 303.96
A35: 45778 | C35: STOCK | F35: Flour | H35: Wsugar | J35: Bsugar | L35: Oil | N35: Eggs | P35: Ricoffy | R35: Wspoon | T35: IcingS | V35: Bpowder | X35: Bicarb | Z35: Cocoa | AB35: Milk | AD35: Carrots | AF35: Ccheese | AH35: Salt | AJ35: Vanilla | AL35: Lemon Juice | AN35: Choc Slabs | AP35: Van Slabs | AR35: Cinnamon | AT35: Red Cherries | AV35: Domes | AX35: Bases | AZ35: Vinegar | BB35: Pecan Nuts | BD35: Cremora
F36: 12.5kg | H36: 10kg | J36: 10kg | L36: 5LITRES | N36: 180 | P36: 750G | R36: 25kg | T36: 25kg | V36: 20kg | X36: 25kg | Z36: 25kg | AB36: 6 x 1litres | AD36: 5kg | AF36: 5kg | AH36: 1kg | AJ36: 3 LITRE | AL36: 2 L | AN36: 20 | AP36: 20 | AR36: 5kg | AT36: 6 KG | AV36: 100 | AX36: 100 | AZ36: 5litres | BB36: 10kg | BD36: 750G
C37: WEEKLY DATES | F37: QUANTITY | G37: TOTALS | H37: QUANTITY | I37: TOTALS | J37: QUANTITY | K37: TOTALS | L37: QUANTITY | M37: TOTALS | N37: QUANTITY | O37: TOTALS | P37: QUANTITY | Q37: TOTALS | R37: QUANTITY | S37: TOTALS | T37: QUANTITY | U37: TOTALS | V37: QUANTITY | W37: TOTALS | X37: QUANTITY | Y37: TOTALS | Z37: QUANTITY | AA37: TOTALS | AB37: QUANTITY | AC37: TOTALS | AD37: QUANTITY | AE37: TOTALS | AF37: QUANTITY | AG37: TOTALS | AH37: QUANTITY | AI37: TOTALS | AJ37: QUANTITY | AK37: TOTALS | AL37: QUANTITY | AM37: TOTALS | AN37: QUANTITY | AO37: TOTALS | AP37: QUANTITY | AQ37: TOTALS | AR37: QUANTITY | AS37: TOTALS | AT37: QUANTITY | AU37: TOTALS | AV37: QUANTITY | AW37: TOTALS | AX37: QUANTITY | AY37: TOTALS | AZ37: QUANTITY | BA37: TOTALS | BB37: QUANTITY | BC37: TOTALS | BD37: QUANTITY | BE37: TOTALS
C38: 21 - 27 APR 2025 | F38: 26 | G38: 3615.74 | H38: 8 | I38: 1639.92 | J38: 20 | K38: 3639.8 | L38: 26 | M38: 4497.74 | N38: 48 | O38: 6143.67 | P38: 3 | Q38: 454.97 | R38: 0 | S38: 0 | T38: 12 | U38: 5155.08 | V38: 4 | W38: 171.96 | X38: 0 | Y38: 0 | Z38: 0 | AA38: 0 | AB38: 19 | AC38: 1880.81 | AD38: 24 | AE38: 1439.76 | AF38: 0 | AG38: 0 | AH38: 0 | AI38: 0 | AJ38: 4 | AK38: 759.8 | AL38: 1 | AM38: 43.99 | AN38: 0 | AO38: 0 | AP38: 0 | AQ38: 0 | AR38: 0 | AS38: 0 | AT38: 0 | AU38: 0 | AV38: 15 | AW38: 3578.77 | AX38: 15 | AY38: 3578.77 | AZ38: 7 | BA38: 155.93 | BB38: 0 | BC38: 0 | BD38: 2 | BE38: 139.98
C39: 28 APR - 4 MAY 2025 | F39: 34 | G39: 4711.66 | H39: 8 | I39: 1639.92 | J39: 27 | K39: 4949.73 | L39: 36 | M39: 6227.64 | N39: 69 | O39: 8843.7 | P39: 3 | Q39: 434.97 | R39: 0 | S39: 0 | T39: 0 | U39: 0 | V39: 18 | W39: 773.82 | X39: 0 | Y39: 0 | Z39: 0 | AA39: 0 | AB39: 24 | AC39: 2375.76 | AD39: 14 | AE39: 769.86 | AF39: 0 | AG39: 0 | AH39: 0 | AI39: 0 | AJ39: 0 | AK39: 0 | AL39: 0 | AM39: 0 | AN39: 0 | AO39: 0 | AP39: 0 | AQ39: 0 | AR39: 1 | AS39: 500 | AT39: 0 | AU39: 0 | AV39: 15 | AW39: 3578.77 | AX39: 15 | AY39: 3578.77 | AZ39: 3 | BA39: 83.97 | BB39: 0 | BC39: 0 | BD39: 2 | BE39: 159.98
C42: GRAND TOTALS | F42: =SUM(F38:F41) -> 60 | G42: =SUM(G38:G41) -> 8327.4 | H42: =SUM(H38:H41) -> 16 | I42: =SUM(I38:I41) -> 3279.84 | J42: =SUM(J38:J41) -> 47 | K42: =SUM(K38:K41) -> 8589.53 | L42: =SUM(L38:L41) -> 62 | M42: =SUM(M38:M41) -> 10725.38 | ... BE42: =SUM(BE38:BE41) -> 299.96
A43: 45809 | C43: STOCK | F43: Flour | H43: Wsugar | J43: Bsugar | L43: Oil | N43: Eggs | P43: Ricoffy | R43: Wspoon | T43: IcingS | V43: Bpowder | X43: Bicarb | Z43: Cocoa | AB43: Milk | AD43: Carrots | AF43: Ccheese | AH43: Salt | AJ43: Vanilla | AL43: Lemon Juice | AN43: Choc Slabs | AP43: Van Slabs | AR43: Cinnamon | AT43: Red Cherries | AV43: Domes | AX43: Bases | AZ43: Vinegar | BB43: Pecan Nuts | BD43: Cremora
F44: 12.5kg | H44: 10kg | J44: 10kg | L44: 5LITRES | N44: 180 | P44: 750G | R44: 25kg | T44: 25kg | V44: 20kg | X44: 25kg | Z44: 25kg | AB44: 6 x 1litres | AD44: 5kg | AF44: 5kg | AH44: 1kg | AJ44: 3 LITRE | AL44: 2 L | AN44: 20 | AP44: 20 | AR44: 5kg | AT44: 6 KG | AV44: 100 | AX44: 100 | AZ44: 5litres | BB44: 10kg | BD44: 750G
C45: WEEKLY DATES | F45: QUANTITY | G45: TOTALS | H45: QUANTITY | I45: TOTALS | J45: QUANTITY | K45: TOTALS | L45: QUANTITY | M45: TOTALS | N45: QUANTITY | O45: TOTALS | P45: QUANTITY | Q45: TOTALS | R45: QUANTITY | S45: TOTALS | T45: QUANTITY | U45: TOTALS | V45: QUANTITY | W45: TOTALS | X45: QUANTITY | Y45: TOTALS | Z45: QUANTITY | AA45: TOTALS | AB45: QUANTITY | AC45: TOTALS | AD45: QUANTITY | AE45: TOTALS | AF45: QUANTITY | AG45: TOTALS | AH45: QUANTITY | AI45: TOTALS | AJ45: QUANTITY | AK45: TOTALS | AL45: QUANTITY | AM45: TOTALS | AN45: QUANTITY | AO45: TOTALS | AP45: QUANTITY | AQ45: TOTALS | AR45: QUANTITY | AS45: TOTALS | AT45: QUANTITY | AU45: TOTALS | AV45: QUANTITY | AW45: TOTALS | AX45: QUANTITY | AY45: TOTALS | AZ45: QUANTITY | BA45: TOTALS | BB45: QUANTITY | BC45: TOTALS | BD45: QUANTITY | BE45: TOTALS
C50: GRAND TOTALS | F50: =SUM(F46:F49) -> 0 | G50: =SUM(G46:G49) -> 0 | H50: =SUM(H46:H49) -> 0 | I50: =SUM(I46:I49) -> 0 | J50: =SUM(J46:J49) -> 0 | K50: =SUM(K46:K49) -> 0 | L50: =SUM(L46:L49) -> 0 | M50: =SUM(M46:M49) -> 0 | ... BE50: =SUM(BE46:BE49) -> 0
A51: 45839 | C51: STOCK | F51: Flour | H51: Wsugar | J51: Bsugar | L51: Oil | N51: Eggs | P51: Ricoffy | R51: Wspoon | T51: IcingS | V51: Bpowder | X51: Bicarb | Z51: Cocoa | AB51: Milk | AD51: Carrots | AF51: Ccheese | AH51: Salt | AJ51: Vanilla | AL51: Lemon Juice | AN51: Choc Slabs | AP51: Van Slabs | AR51: Cinnamon | AT51: Red Cherries | AV51: Domes | AX51: Bases | AZ51: Vinegar | BB51: Pecan Nuts | BD51: Cremora
F52: 12.5kg | H52: 10kg | J52: 10kg | L52: 5LITRES | N52: 180 | P52: 750G | R52: 25kg | T52: 25kg | V52: 20kg | X52: 25kg | Z52: 25kg | AB52: 6 x 1litres | AD52: 5kg | AF52: 5kg | AH52: 1kg | AJ52: 3 LITRE | AL52: 2 L | AN52: 20 | AP52: 20 | AR52: 5kg | AT52: 6 KG | AV52: 100 | AX52: 100 | AZ52: 5litres | BB52: 10kg | BD52: 750G
C53: WEEKLY DATES | F53: QUANTITY | G53: TOTALS | H53: QUANTITY | I53: TOTALS | J53: QUANTITY | K53: TOTALS | L53: QUANTITY | M53: TOTALS | N53: QUANTITY | O53: TOTALS | P53: QUANTITY | Q53: TOTALS | R53: QUANTITY | S53: TOTALS | T53: QUANTITY | U53: TOTALS | V53: QUANTITY | W53: TOTALS | X53: QUANTITY | Y53: TOTALS | Z53: QUANTITY | AA53: TOTALS | AB53: QUANTITY | AC53: TOTALS | AD53: QUANTITY | AE53: TOTALS | AF53: QUANTITY | AG53: TOTALS | AH53: QUANTITY | AI53: TOTALS | AJ53: QUANTITY | AK53: TOTALS | AL53: QUANTITY | AM53: TOTALS | AN53: QUANTITY | AO53: TOTALS | AP53: QUANTITY | AQ53: TOTALS | AR53: QUANTITY | AS53: TOTALS | AT53: QUANTITY | AU53: TOTALS | AV53: QUANTITY | AW53: TOTALS | AX53: QUANTITY | AY53: TOTALS | AZ53: QUANTITY | BA53: TOTALS | BB53: QUANTITY | BC53: TOTALS | BD53: QUANTITY | BE53: TOTALS
C58: GRAND TOTALS | F58: =SUM(F54:F57) -> 0 | G58: =SUM(G54:G57) -> 0 | H58: =SUM(H54:H57) -> 0 | I58: =SUM(I54:I57) -> 0 | J58: =SUM(J54:J57) -> 0 | K58: =SUM(K54:K57) -> 0 | L58: =SUM(L54:L57) -> 0 | M58: =SUM(M54:M57) -> 0 | ... BE58: =SUM(BE54:BE57) -> 0
A59: 45870 | C59: STOCK | F59: Flour | H59: Wsugar | J59: Bsugar | L59: Oil | N59: Eggs | P59: Ricoffy | R59: Wspoon | T59: IcingS | V59: Bpowder | X59: Bicarb | Z59: Cocoa | AB59: Milk | AD59: Carrots | AF59: Ccheese | AH59: Salt | AJ59: Vanilla | AL59: Lemon Juice | AN59: Choc Slabs | AP59: Van Slabs | AR59: Cinnamon | AT59: Red Cherries | AV59: Domes | AX59: Bases | AZ59: Vinegar | BB59: Pecan Nuts | BD59: Cremora
F60: 12.5kg | H60: 10kg | J60: 10kg | L60: 5LITRES | N60: 180 | P60: 750G | R60: 25kg | T60: 25kg | V60: 20kg | X60: 25kg | Z60: 25kg | AB60: 6 x 1litres | AD60: 5kg | AF60: 5kg | AH60: 1kg | AJ60: 3 LITRE | AL60: 2 L | AN60: 20 | AP60: 20 | AR60: 5kg | AT60: 6 KG | AV60: 100 | AX60: 100 | AZ60: 5litres | BB60: 10kg | BD60: 750G
C61: WEEKLY DATES | F61: QUANTITY | G61: TOTALS | H61: QUANTITY | I61: TOTALS | J61: QUANTITY | K61: TOTALS | L61: QUANTITY | M61: TOTALS | N61: QUANTITY | O61: TOTALS | P61: QUANTITY | Q61: TOTALS | R61: QUANTITY | S61: TOTALS | T61: QUANTITY | U61: TOTALS | V61: QUANTITY | W61: TOTALS | X61: QUANTITY | Y61: TOTALS | Z61: QUANTITY | AA61: TOTALS | AB61: QUANTITY | AC61: TOTALS | AD61: QUANTITY | AE61: TOTALS | AF61: QUANTITY | AG61: TOTALS | AH61: QUANTITY | AI61: TOTALS | AJ61: QUANTITY | AK61: TOTALS | AL61: QUANTITY | AM61: TOTALS | AN61: QUANTITY | AO61: TOTALS | AP61: QUANTITY | AQ61: TOTALS | AR61: QUANTITY | AS61: TOTALS | AT61: QUANTITY | AU61: TOTALS | AV61: QUANTITY | AW61: TOTALS | AX61: QUANTITY | AY61: TOTALS | AZ61: QUANTITY | BA61: TOTALS | BB61: QUANTITY | BC61: TOTALS | BD61: QUANTITY | BE61: TOTALS
C66: GRAND TOTALS | F66: =SUM(F62:F65) -> 0 | G66: =SUM(G62:G65) -> 0 | H66: =SUM(H62:H65) -> 0 | I66: =SUM(I62:I65) -> 0 | J66: =SUM(J62:J65) -> 0 | K66: =SUM(K62:K65) -> 0 | L66: =SUM(L62:L65) -> 0 | M66: =SUM(M62:M65) -> 0 | ... BE66: =SUM(BE62:BE65) -> 0
A67: 45901 | C67: STOCK | F67: Flour | H67: Wsugar | J67: Bsugar | L67: Oil | N67: Eggs | P67: Ricoffy | R67: Wspoon | T67: IcingS | V67: Bpowder | X67: Bicarb | Z67: Cocoa | AB67: Milk | AD67: Carrots | AF67: Ccheese | AH67: Salt | AJ67: Vanilla | AL67: Lemon Juice | AN67: Choc Slabs | AP67: Van Slabs | AR67: Cinnamon | AT67: Red Cherries | AV67: Domes | AX67: Bases | AZ67: Vinegar | BB67: Pecan Nuts | BD67: Cremora
F68: 12.5kg | H68: 10kg | J68: 10kg | L68: 5LITRES | N68: 180 | P68: 750G | R68: 25kg | T68: 25kg | V68: 20kg | X68: 25kg | Z68: 25kg | AB68: 6 x 1litres | AD68: 5kg | AF68: 5kg | AH68: 1kg | AJ68: 3 LITRE | AL68: 2 L | AN68: 20 | AP68: 20 | AR68: 5kg | AT68: 6 KG | AV68: 100 | AX68: 100 | AZ68: 5litres | BB68: 10kg | BD68: 750G
C69: WEEKLY DATES | F69: QUANTITY | G69: TOTALS | H69: QUANTITY | I69: TOTALS | J69: QUANTITY | K69: TOTALS | L69: QUANTITY | M69: TOTALS | N69: QUANTITY | O69: TOTALS | P69: QUANTITY | Q69: TOTALS | R69: QUANTITY | S69: TOTALS | T69: QUANTITY | U69: TOTALS | V69: QUANTITY | W69: TOTALS | X69: QUANTITY | Y69: TOTALS | Z69: QUANTITY | AA69: TOTALS | AB69: QUANTITY | AC69: TOTALS | AD69: QUANTITY | AE69: TOTALS | AF69: QUANTITY | AG69: TOTALS | AH69: QUANTITY | AI69: TOTALS | AJ69: QUANTITY | AK69: TOTALS | AL69: QUANTITY | AM69: TOTALS | AN69: QUANTITY | AO69: TOTALS | AP69: QUANTITY | AQ69: TOTALS | AR69: QUANTITY | AS69: TOTALS | AT69: QUANTITY | AU69: TOTALS | AV69: QUANTITY | AW69: TOTALS | AX69: QUANTITY | AY69: TOTALS | AZ69: QUANTITY | BA69: TOTALS | BB69: QUANTITY | BC69: TOTALS | BD69: QUANTITY | BE69: TOTALS
C74: GRAND TOTALS | F74: =SUM(F70:F73) -> 0 | G74: =SUM(G70:G73) -> 0 | H74: =SUM(H70:H73) -> 0 | I74: =SUM(I70:I73) -> 0 | J74: =SUM(J70:J73) -> 0 | K74: =SUM(K70:K73) -> 0 | L74: =SUM(L70:L73) -> 0 | M74: =SUM(M70:M73) -> 0 | ... BE74: =SUM(BE70:BE73) -> 0
A75: 45931 | C75: STOCK | F75: Flour | H75: Wsugar | J75: Bsugar | L75: Oil | N75: Eggs | P75: Ricoffy | R75: Wspoon | T75: IcingS | V75: Bpowder | X75: Bicarb | Z75: Cocoa | AB75: Milk | AD75: Carrots | AF75: Ccheese | AH75: Salt | AJ75: Vanilla | AL75: Lemon Juice | AN75: Choc Slabs | AP75: Van Slabs | AR75: Cinnamon | AT75: Red Cherries | AV75: Domes | AX75: Bases | AZ75: Vinegar | BB75: Pecan Nuts | BD75: Cremora
F76: 12.5kg | H76: 10kg | J76: 10kg | L76: 5LITRES | N76: 180 | P76: 750G | R76: 25kg | T76: 25kg | V76: 20kg | X76: 25kg | Z76: 25kg | AB76: 6 x 1litres | AD76: 5kg | AF76: 5kg | AH76: 1kg | AJ76: 3 LITRE | AL76: 2 L | AN76: 20 | AP76: 20 | AR76: 5kg | AT76: 6 KG | AV76: 100 | AX76: 100 | AZ76: 5litres | BB76: 10kg | BD76: 750G
C77: WEEKLY DATES | F77: QUANTITY | G77: TOTALS | H77: QUANTITY | I77: TOTALS | J77: QUANTITY | K77: TOTALS | L77: QUANTITY | M77: TOTALS | N77: QUANTITY | O77: TOTALS | P77: QUANTITY | Q77: TOTALS | R77: QUANTITY | S77: TOTALS | T77: QUANTITY | U77: TOTALS | V77: QUANTITY | W77: TOTALS | X77: QUANTITY | Y77: TOTALS | Z77: QUANTITY | AA77: TOTALS | AB77: QUANTITY | AC77: TOTALS | AD77: QUANTITY | AE77: TOTALS | AF77: QUANTITY | AG77: TOTALS | AH77: QUANTITY | AI77: TOTALS | AJ77: QUANTITY | AK77: TOTALS | AL77: QUANTITY | AM77: TOTALS | AN77: QUANTITY | AO77: TOTALS | AP77: QUANTITY | AQ77: TOTALS | AR77: QUANTITY | AS77: TOTALS | AT77: QUANTITY | AU77: TOTALS | AV77: QUANTITY | AW77: TOTALS | AX77: QUANTITY | AY77: TOTALS | AZ77: QUANTITY | BA77: TOTALS | BB77: QUANTITY | BC77: TOTALS | BD77: QUANTITY | BE77: TOTALS
C82: GRAND TOTALS | F82: =SUM(F78:F81) -> 0 | G82: =SUM(G78:G81) -> 0 | H82: =SUM(H78:H81) -> 0 | I82: =SUM(I78:I81) -> 0 | J82: =SUM(J78:J81) -> 0 | K82: =SUM(K78:K81) -> 0 | L82: =SUM(L78:L81) -> 0 | M82: =SUM(M78:M81) -> 0 | ... BE82: =SUM(BE78:BE81) -> 0
A83: 45962 | C83: STOCK | F83: Flour | H83: Wsugar | J83: Bsugar | L83: Oil | N83: Eggs | P83: Ricoffy | R83: Wspoon | T83: IcingS | V83: Bpowder | X83: Bicarb | Z83: Cocoa | AB83: Milk | AD83: Carrots | AF83: Ccheese | AH83: Salt | AJ83: Vanilla | AL83: Lemon Juice | AN83: Choc Slabs | AP83: Van Slabs | AR83: Cinnamon | AT83: Red Cherries | AV83: Domes | AX83: Bases | AZ83: Vinegar | BB83: Pecan Nuts | BD83: Cremora
F84: 12.5kg | H84: 10kg | J84: 10kg | L84: 5LITRES | N84: 180 | P84: 750G | R84: 25kg | T84: 25kg | V84: 20kg | X84: 25kg | Z84: 25kg | AB84: 6 x 1litres | AD84: 5kg | AF84: 5kg | AH84: 1kg | AJ84: 3 LITRE | AL84: 2 L | AN84: 20 | AP84: 20 | AR84: 5kg | AT84: 6 KG | AV84: 100 | AX84: 100 | AZ84: 5litres | BB84: 10kg | BD84: 750G
C85: WEEKLY DATES | F85: QUANTITY | G85: TOTALS | H85: QUANTITY | I85: TOTALS | J85: QUANTITY | K85: TOTALS | L85: QUANTITY | M85: TOTALS | N85: QUANTITY | O85: TOTALS | P85: QUANTITY | Q85: TOTALS | R85: QUANTITY | S85: TOTALS | T85: QUANTITY | U85: TOTALS | V85: QUANTITY | W85: TOTALS | X85: QUANTITY | Y85: TOTALS | Z85: QUANTITY | AA85: TOTALS | AB85: QUANTITY | AC85: TOTALS | AD85: QUANTITY | AE85: TOTALS | AF85: QUANTITY | AG85: TOTALS | AH85: QUANTITY | AI85: TOTALS | AJ85: QUANTITY | AK85: TOTALS | AL85: QUANTITY | AM85: TOTALS | AN85: QUANTITY | AO85: TOTALS | AP85: QUANTITY | AQ85: TOTALS | AR85: QUANTITY | AS85: TOTALS | AT85: QUANTITY | AU85: TOTALS | AV85: QUANTITY | AW85: TOTALS | AX85: QUANTITY | AY85: TOTALS | AZ85: QUANTITY | BA85: TOTALS | BB85: QUANTITY | BC85: TOTALS | BD85: QUANTITY | BE85: TOTALS
C90: GRAND TOTALS | F90: =SUM(F86:F89) -> 0 | G90: =SUM(G86:G89) -> 0 | H90: =SUM(H86:H89) -> 0 | I90: =SUM(I86:I89) -> 0 | J90: =SUM(J86:J89) -> 0 | K90: =SUM(K86:K89) -> 0 | L90: =SUM(L86:L89) -> 0 | M90: =SUM(M86:M89) -> 0 | ... BE90: =SUM(BE86:BE89) -> 0
A91: 45992 | C91: STOCK | F91: Flour | H91: Wsugar | J91: Bsugar | L91: Oil | N91: Eggs | P91: Ricoffy | R91: Wspoon | T91: IcingS | V91: Bpowder | X91: Bicarb | Z91: Cocoa | AB91: Milk | AD91: Carrots | AF91: Ccheese | AH91: Salt | AJ91: Vanilla | AL91: Lemon Juice | AN91: Choc Slabs | AP91: Van Slabs | AR91: Cinnamon | AT91: Red Cherries | AV91: Domes | AX91: Bases | AZ91: Vinegar | BB91: Pecan Nuts | BD91: Cremora
F92: 12.5kg | H92: 10kg | J92: 10kg | L92: 5LITRES | N92: 180 | P92: 750G | R92: 25kg | T92: 25kg | V92: 20kg | X92: 25kg | Z92: 25kg | AB92: 6 x 1litres | AD92: 5kg | AF92: 5kg | AH92: 1kg | AJ92: 3 LITRE | AL92: 2 L | AN92: 20 | AP92: 20 | AR92: 5kg | AT92: 6 KG | AV92: 100 | AX92: 100 | AZ92: 5litres | BB92: 10kg | BD92: 750G
C93: WEEKLY DATES | F93: QUANTITY | G93: TOTALS | H93: QUANTITY | I93: TOTALS | J93: QUANTITY | K93: TOTALS | L93: QUANTITY | M93: TOTALS | N93: QUANTITY | O93: TOTALS | P93: QUANTITY | Q93: TOTALS | R93: QUANTITY | S93: TOTALS | T93: QUANTITY | U93: TOTALS | V93: QUANTITY | W93: TOTALS | X93: QUANTITY | Y93: TOTALS | Z93: QUANTITY | AA93: TOTALS | AB93: QUANTITY | AC93: TOTALS | AD93: QUANTITY | AE93: TOTALS | AF93: QUANTITY | AG93: TOTALS | AH93: QUANTITY | AI93: TOTALS | AJ93: QUANTITY | AK93: TOTALS | AL93: QUANTITY | AM93: TOTALS | AN93: QUANTITY | AO93: TOTALS | AP93: QUANTITY | AQ93: TOTALS | AR93: QUANTITY | AS93: TOTALS | AT93: QUANTITY | AU93: TOTALS | AV93: QUANTITY | AW93: TOTALS | AX93: QUANTITY | AY93: TOTALS | AZ93: QUANTITY | BA93: TOTALS | BB93: QUANTITY | BC93: TOTALS | BD93: QUANTITY | BE93: TOTALS
C98: GRAND TOTALS | F98: =SUM(F94:F97) -> 0 | G98: =SUM(G94:G97) -> 0 | H98: =SUM(H94:H97) -> 0 | I98: =SUM(I94:I97) -> 0 | J98: =SUM(J94:J97) -> 0 | K98: =SUM(K94:K97) -> 0 | L98: =SUM(L94:L97) -> 0 | M98: =SUM(M94:M97) -> 0 | ... BE98: =SUM(BE94:BE97) -> 0

Sheet EXPENSE DAILY
A1: EXPENSES
A2: DATE | B2: 45657
A3: SLIP NUMBER | B3: AMOUNT | C3: VAT | D3: Shop
A4: 1 | B4: 79 | C4: 10.3 | D4: TOLL GATE
A5: 2 | B5: 79 | C5: 10.3 | D5: TOLL GATE
A6: 3 | B6: 744.67 | D6: DIESEL
A7: 4 | B7: 1000 | D7: DIESEL
A8: 5 | B8: 3176 | C8: 414.26 | D8: BAKERSBIN
A9: 6 | B9: 252 | D9: BACK 2 BASICS
A10: 7 | B10: 5765.73 | C10: 413.37 | D10: WASI
A11: 8 | B11: 286.9 | C11: 2.32 | D11: SHOPRITE
A12: 9 | B12: 990.23 | C12: 129.16 | D12: PNP
A13: 10 | B13: 570 | D13: SOAP CENTRE
A14: 11 | B14: 90 | D14: TBANTU
A15: 12 | B15: 6000 | D15: HEIDEL EGGS
B16: =SUM(B4:B15) -> 19033.53 | C16: =SUM(C4:C15) -> 979.71
A18: EXPENSES
A19: DATE | B19: 45658
A20: SLIP NUMBER | B20: AMOUNT | C20: VAT | D20: Shop
A21: 1 | B21: 300 | D21: DIESEL
A22: 2 | B22: 800 | D22: DIESEL
B23: =SUM(B21:B22) -> 1100 | C23: =SUM(C21:C22) -> 0
A25: EXPENSES
A26: DATE | B26: 45659
A27: SLIP NUMBER | B27: AMOUNT | C27: VAT | D27: Shop
A28: 1 | B28: 300 | D28: DIESEL
A29: 2 | B29: 131.98 | C29: 17.21 | D29: PNP
A30: 3 | B30: 6147.5 | C30: 593.35 | D30: WASI
A31: 4 | B31: 7587.25 | C31: 989.64 | D31: WASI
B32: =SUM(B28:B31) -> 14166.73 | C32: =SUM(C28:C31) -> 1600.2
A34: EXPENSES
A35: DATE | B35: 45660
A36: SLIP NUMBER | B36: AMOUNT | C36: VAT | D36: Shop
A37: 1 | B37: 704.64 | D37: DIESEL
A38: 2 | B38: 469.89 | C38: 11.34 | D38: SHOPRITE
B39: =SUM(B37:B38) -> 1174.53 | C39: =SUM(C37:C38) -> 11.34
A41: EXPENSES
A42: DATE | B42: 45661
A43: SLIP NUMBER | B43: AMOUNT | C43: VAT | D43: Shop
A44: 1 | B44: 750 | D44: DIESEL
A45: 2 | B45: 1500 | D45: ELECTRICITY
A46: 3 | B46: 209.93 | D46: SHOPRITE
A47: 4 | B47: 5716.55 | C47: 507.41 | D47: WASI
A48: 5 | B48: 18010 | D48: WAGES
B49: =SUM(B44:B48) -> 26186.48 | C49: =SUM(C44:C48) -> 507.41
A51: EXPENSES
A52: DATE | B52: 45662
A53: SLIP NUMBER | B53: AMOUNT | C53: VAT | D53: Shop
A54: 1 | B54: 189.17 | D54: AE BARB CS
A55: 2 | B55: 178.98 | C55: 23.35 | D55: PNP
A56: 3 | B56: 40 | D56: WAS STORE
B57: =SUM(B54:B56) -> 408.15 | C57: =SUM(C54:C56) -> 23.35
A59: PP
A60: DATE | B60: 45663
A61: SLIP NUMBER | B61: AMOUNT | C61: VAT | D61: Shop
A62: 1 | B62: 575.18 | D62: DIESEL
A63: 2 | B63: 289 | C63: 37.7 | D63: FAMILY STORE
A64: 3 | B64: 575 | C64: 75 | D64: CAVALIERI
A65: 4 | B65: 299.9 | D65: SHOPRITE
A66: 5 | B66: 2472 | D66: HYPER SWEETS
A67: 6 | B67: 570 | D67: SOAP CENTRE
A68: 7 | B68: 6021.55 | C68: 582.86 | D68: WASI
A69: 8 | B69: 1733.8 | C69: 220.94 | D69: MAKRO
A70: 9 | B70: 12725 | D70: WAGES
B71: =SUM(B62:B70) -> 25261.43 | C71: =SUM(C62:C70) -> 916.5
A73: EXPENSES
A74: DATE | B74: 45664
A75: SLIP NUMBER | B75: AMOUNT | C75: VAT | D75: Shop
A76: 1 | B76: 804.52 | D76: DIESEL
A77: 2 | B77: 258.35 | D77: AE BARB CS
A78: 3 | B78: 51 | D78: AE CAROLINA
A79: 4 | B79: 1500 | D79: DIESL/PETROL
A80: 5 | B80: 79 | C80: 10.3 | D80: TOLL GATE
A81: 6 | B81: 79 | C81: 10.3 | D81: TOLL GATE
A82: 7 | B82: 114.99 | C82: 15 | D82: AE CAROLINA
A83: 8 | B83: 400 | D83: DIESEL
A84: 9 | B84: 86.96 | C84: 13.04 | D84: PROBUILD
A85: 10 | B85: 7522.57 | C85: 559.16 | D85: WASI
A86: 11 | B86: 6000 | D86: HEIDEL EGGS
A87: 12 | B87: 28014 | C87: 3654 | D87: CHIPKINS
B88: =SUM(B76:B87) -> 44910.39 | C88: =SUM(C76:C87) -> 4261.8
A90: EXPENSES
A91: DATE | B91: 45665
A92: SLIP NUMBER | B92: AMOUNT | C92: VAT | D92: Shop
A93: 1 | B93: 800 | D93: DIESEL
B94: =SUM(B93:B93) -> 800 | C94: =SUM(C93:C93) -> 0
A96: EXPENSES
A97: DATE | B97: 45666
A98: SLIP NUMBER | B98: AMOUNT | C98: VAT | D98: Shop
A99: 1 | B99: 999.22 | D99: DIESEL
A100: 2 | B100: 79 | C100: 10.3 | D100: TOLL GATE
A101: 3 | B101: 79 | C101: 10.3 | D101: TOLL GATE
A102: 4 | B102: 25 | D102: HOME & PARTY STORE
A103: 5 | B103: 27.99 | C103: 3.65 | D103: PNP
A104: 6 | B104: 94.99 | D104: PNP
A105: 7 | B105: 299.9 | D105: SHOPRITE
A106: 8 | B106: 6691.45 | C106: 623.95 | D106: WASI
A107: 9 | B107: 7587.25 | C107: 989.64 | D107: ACE
A108: 10 | B108: 4241 | C108: 553.17 | D108: POINT S
B109: =SUM(B99:B108) -> 20124.8 | C109: =SUM(C99:C108) -> 2191.01
...

Sheet DAILY INCOME EXPENSE
A1: MONTH
A2: 45658 | G2: 45689 | M2: 45717 | S2: 45748 | Y2: 45778 | AE2: 45809 | AK2: 45839 | AQ2: 45870 | AW2: 45901 | BC2: 45931 | BI2: 45962 | BO2: 45992
A3: DATE | B3: INCOME | C3: INCOME VAT | D3: EXPENSES | E3: EXPENSES VAT | G3: DATE | H3: INCOME | I3: INCOME VAT | J3: EXPENSES | K3: EXPENSES VAT | M3: DATE | N3: INCOME | O3: INCOME VAT | P3: EXPENSES | Q3: EXPENSES VAT | S3: DATE | T3: INCOME | U3: INCOME VAT | V3: EXPENSES | W3: EXPENSES VAT | Y3: DATE | Z3: INCOME | AA3: INCOME VAT | AB3: EXPENSES | AC3: EXPENSES VAT | AE3: DATE | AF3: INCOME | AG3: INCOME VAT | AH3: EXPENSES | AI3: EXPENSES VAT | AK3: DATE | AL3: INCOME | AM3: INCOME VAT | AN3: EXPENSES | AO3: EXPENSES VAT | AQ3: DATE | AR3: INCOME | AS3: INCOME VAT | AT3: EXPENSES | AU3: EXPENSES VAT | AW3: DATE | AX3: INCOME | AY3: INCOME VAT | AZ3: EXPENSES | BA3: EXPENSES VAT | BC3: DATE | BD3: INCOME | BE3: INCOME VAT | BF3: EXPENSES | BG3: EXPENSES VAT | BI3: DATE | BJ3: INCOME | BK3: INCOME VAT | BL3: EXPENSES | BM3: EXPENSES VAT | BO3: DATE | BP3: INCOME | BQ3: INCOME VAT | BR3: EXPENSES | BS3: EXPENSES VAT
A4: 1 | B4: 26962 | C4: =238.8+238.8+356.4+209.4+209.41+429.2 -> 1682.01 | D4: 1100 | G4: 1 | H4: 21137 | I4: 358.2+928.8 | J4: 14175.16 | K4: 565.91 | M4: 1 | N4: 0 | O4: 0 | P4: 10379.54 | Q4: 566.36 | S4: 1 | T4: 32648.5 | U4: =1128+773.4+773.4+773.4+773.4 -> 4221.6 | V4: =1713.5+8334.88 -> 10048.38 | W4: =223.5+516.7 -> 740.2 | Y4: 1 | Z4: 3429.3 | AA4: =477.3 -> 477.3 | AB4: 19634.23 | AC4: 1569.43 | AE4: 1 | AK4: 1 | AQ4: 1 | AW4: 1 | BC4: 1 | BI4: 1 | BO4: 1
A5: 2 | B5: 0 | C5: 0 | D5: 14166.73 | E5: 1600.2 | G5: 2 | M5: 2 | S5: 2 | T5: 28103.6 | U5: =536.4+356.4+297.6+1249.2 -> 2439.6 | V5: 800 | Y5: 2 | Z5: 36639.2 | AA5: =775.2+415.2+477.6+861.6+861.6 -> 3391.2 | AB5: 9294.47 | AC5: 421.77 | AE5: 2 | AK5: 2 | AQ5: 2 | AW5: 2 | BC5: 2 | BI5: 2 | BO5: 2
A6: 3 | B6: 34781.6 | C6: =238.8+238.8+297.6+418.8+1503.6 -> 2697.6 | D6: 1174.53 | E6: 11.34 | G6: 3 | H6: 28372.8 | I6: =536.4+356.4+477.6 -> 1370.4 | J6: 10025.85 | K6: 858.38 | M6: 3 | N6: 30372.8 | O6: =477.6+356.4+297.6+1069.2 -> 2200.8 | P6: 7862.62 | Q6: 519.82 | S6: 3 | T6: 3781.2 | U6: 508.8 | V6: =16537+9381.7 -> 25918.7 | W6: =2157+956.32 -> 3113.32 | Y6: 3 | Z6: 18564.2 | AA6: =878.1+878.1 -> 1756.2 | AB6: 26579.44 | AC6: 490.91 | AE6: 3 | AK6: 3 | AQ6: 3 | AW6: 3 | BC6: 3 | BI6: 3 | BO6: 3
A7: 4 | B7: 14519.9 | C7: =1025.1+868.8 -> 1893.9 | D7: 26186.48 | E7: 507.41 | G7: 4 | H7: 33362.6 | I7: =1190.4+1131.6+804.6+834+834+712.8 -> 5507.4 | J7: 8633.4 | K7: 678.36 | M7: 4 | N7: 32319.6 | O7: =995.7+789.9+834+834+744 -> 4197.6 | P7: 15362.72 | Q7: 1336.34 | S7: 4 | T7: 34996 | U7: =775.2+415.2+477.6+1488 -> 3156 | V7: 4660.56 | W7: 463.8 | Y7: 4 | Z7: 0 | AB7: 54.99 | AC7: 7.18 | AE7: 4 | AK7: 4 | AQ7: 4 | AW7: 4 | BC7: 4 | BI7: 4 | BO7: 4
A8: 5 | B8: 0 | C8: 0 | D8: 408.15 | E8: 23.35 | G8: 5 | H8: 29432.8 | I8: =536.4+356.4+418.8+1249.2 -> 2560.8 | J8: =24863+800 -> 25663 | K8: 3243 | M8: 5 | N8: 25572.8 | O8: =477.6+356.4+297.6+1069.2 -> 2200.8 | P8: 800 | S8: 5 | T8: 0 | U8: 0 | V8: 992.98 | Y8: 5 | Z8: 28898.2 | AB8: 13380.48 | AC8: 704.79 | AE8: 5 | AK8: 5 | AQ8: 5 | AW8: 5 | BC8: 5 | BI8: 5 | BO8: 5
A9: 6 | B9: 29475.2 | C9: =537.3+355.5+493.2+1295.1 -> 2681.1 | D9: 25261.43 | E9: 916.5 | G9: 6 | H9: 7510.8 | I9: 418.8 | J9: 17671.61 | K9: 1654.54 | M9: 6 | N9: 5910.8 | O9: 418.8 | P9: =4358.5+8885.69 -> 13244.19 | Q9: =568.5+514.16 -> 1082.66 | S9: 6 | T9: 13697.2 | U9: =1069.2 -> 1069.2 | V9: 6101.77 | W9: 204.58 | Y9: 6 | Z9: 44311.8 | AB9: 5470.97 | AC9: 205.93 | AE9: 6 | AK9: 6 | AQ9: 6 | AW9: 6 | BC9: 6 | BI9: 6 | BO9: 6
A10: 7 | B10: 28294.8 | C10: =1069.2+625.5+625.5+625.5 -> 2945.7 | D10: =28014+16896.39 -> 44910.39 | E10: =3654+607.8 -> 4261.8 | G10: 7 | H10: 30825.2 | I10: =595.2+356.4+477.6+1488 -> 2917.2 | J10: 6800 | M10: 7 | N10: 31485.2 | O10: =654+356.4+477.6+1249.2 -> 2737.2 | P10: 20437.03 | Q10: 68.95 | S10: 7 | T10: 23923.6 | U10: =238.8+238.8+178.2+178.2+148.8+148.8+564+564 -> 2259.6 | V10: 8823.39 | W10: 758.34 | Y10: 7 | Z10: 20038.6 | AB10: 800.08 | AE10: 7 | AK10: 7 | AQ10: 7 | AW10: 7 | BC10: 7 | BI10: 7 | BO10: 7
A11: WEEKLY TOTALS | B11: =SUM(B4:B10) -> 134033.5 | C11: =SUM(C4:C10) -> 11900.31 | D11: =SUM(D4:D10) -> 113207.71 | E11: =SUM(E4:E10) -> 7320.6 | G11: WEEKLY TOTALS | H11: =SUM(H4:H10) -> 150641.2 | I11: =SUM(I4:I10) -> 12774.6 | J11: =SUM(J4:J10) -> 82969.02 | K11: =SUM(K4:K10) -> 7000.19 | M11: WEEKLY TOTALS | N11: =SUM(N4:N10) -> 125661.2 | O11: =SUM(O4:O10) -> 11755.2 | P11: =SUM(P4:P10) -> 68086.1 | Q11: =SUM(Q4:Q10) -> 3574.13 | S11: WEEKLY TOTALS | T11: =SUM(T4:T10) -> 137150.1 | U11: =SUM(U4:U10) -> 13654.8 | V11: =SUM(V4:V10) -> 57345.78 | W11: =SUM(W4:W10) -> 5280.24 | Y11: WEEKLY TOTALS | Z11: =SUM(Z4:Z10) -> 151881.3 | AA11: =SUM(AA4:AA10) -> 5624.7 | AB11: =SUM(AB4:AB10) -> 75214.66 | AC11: =SUM(AC4:AC10) -> 3400.01 | AE11: WEEKLY TOTALS | AF11: =SUM(AF4:AF10) -> 0 | AG11: =SUM(AG4:AG10) -> 0 | AH11: =SUM(AH4:AH10) -> 0 | AI11: =SUM(AI4:AI10) -> 0 | AK11: WEEKLY TOTALS | AL11: =SUM(AL4:AL10) -> 0 | AM11: =SUM(AM4:AM10) -> 0 | AN11: =SUM(AN4:AN10) -> 0 | AO11: =SUM(AO4:AO10) -> 0 | AQ11: WEEKLY TOTALS | AR11: =SUM(AR4:AR10) -> 0 | AS11: =SUM(AS4:AS10) -> 0 | AT11: =SUM(AT4:AT10) -> 0 | AU11: =SUM(AU4:AU10) -> 0 | AW11: WEEKLY TOTALS | AX11: =SUM(AX4:AX10) -> 0 | AY11: =SUM(AY4:AY10) -> 0 | AZ11: =SUM(AZ4:AZ10) -> 0 | BA11: =SUM(BA4:BA10) -> 0 | BC11: WEEKLY TOTALS | BD11: =SUM(BD4:BD10) -> 0 | BE11: =SUM(BE4:BE10) -> 0 | BF11: =SUM(BF4:BF10) -> 0 | BG11: =SUM(BG4:BG10) -> 0 | BI11: WEEKLY TOTALS | BJ11: =SUM(BJ4:BJ10) -> 0 | BK11: =SUM(BK4:BK10) -> 0 | BL11: =SUM(BL4:BL10) -> 0 | BM11: =SUM(BM4:BM10) -> 0 | BO11: WEEKLY TOTALS | BP11: =SUM(BP4:BP10) -> 0 | BQ11: =SUM(BQ4:BQ10) -> 0 | BR11: =SUM(BR4:BR10) -> 0 | BS11: =SUM(BS4:BS10) -> 0
A12: 8 | B12: 24087 | C12: =537.3+355.5+449.1+1025.1 -> 2367 | D12: 800 | E12: 0 | G12: 8 | H12: 0 | I12: 0 | J12: 19627.7 | K12: 113.84 | M12: 8 | N12: 0 | O12: 0 | P12: 7434.59 | Q12: 667.61 | S12: 8 | T12: 26792.7 | U12: =626.4+949.8+655.8+655.8+670.5 -> 3558.3 | V12: =16547.13+9858.26 -> 26405.39 | W12: =2158.33+979.69 -> 3138.02 | Y12: 8 | Z12: 3661.6 | AB12: 8387.48 | AC12: 431.08 | AE12: 8 | AK12: 8 | AQ12: 8 | AW12: 8 | BC12: 8 | BI12: 8 | BO12: 8
A13: 9 | B13: 9075.4 | C13: =534.6+346.2 -> 880.8 | D13: 20124.8 | E13: 2191.01 | G13: 9 | H13: 0 | I13: 0 | J13: 8897.28 | K13: 638.79 | M13: 9 | N13: 8197.2 | O13: =1069.2 -> 1069.2 | P13: 10892.15 | Q13: 768.92 | S13: 9 | T13: 31422.8 | U13: =477.6+266.4+297.6+1069.2 -> 2110.8 | V13: 800 | Y13: 9 | AE13: 9 | AK13: 9 | AQ13: 9 | AW13: 9 | BC13: 9 | BI13: 9 | BO13: 9
A14: 10 | B14: 37083.9 | C14: =402.3+449.1+1430.1 -> 2281.5 | D14: 804.72 | E14: 0 | G14: 10 | H14: 33207.4 | I14: =253.5+253.5+178.2+178.2+238.8+238.8+1190.4+744 -> 3275.4 | J14: 10043.06 | K14: 637.24 | M14: 10 | N14: 35952.8 | O14: =536.4+356.4+297.6+1190.4 -> 2380.8 | P14: 11246.51 | Q14: 660.13 | S14: 10 | T14: 25519 | U14: 508.8 | V14: 20637.15 | W14: 1854.45 | Y14: 10 | AE14: 10 | AK14: 10 | AQ14: 10 | AW14: 10 | BC14: 10 | BI14: 10 | BO14: 10
A15: 11 | B15: 3300 | C15: =716.4 -> 716.4 | D15: 10078.14 | E15: 345.65 | G15: 11 | H15: 33136.1 | I15: =1131.6+804.6+834+834 -> 3604.2 | J15: 12317.61 | K15: 793.38 | M15: 11 | N15: 29573.4 | O15: =953.4+714.6+714.6+714.6+744 -> 3841.2 | P15: =19333.8+12400.5 -> 31734.3 | Q15: =2521.8+1077.46 -> 3599.26 | S15: 11 | T15: 25519 | U15: =597+356.4+477.6+1128 -> 2559 | V15: 15620 | Y15: 11 | AE15: 11 | AK15: 11 | AQ15: 11 | AW15: 11 | BC15: 11 | BI15: 11 | BO15: 11
A16: 12 | B16: 0 | C16: 0 | D16: 7158.41 | E16: 502.32 | G16: 12 | H16: 28480.4 | I16: =418.8+356.4+418.8+1190.4 -> 2384.4 | J16: 4590.61 | K16: 342.11 | M16: 12 | N16: 25052.8 | O16: =536.4+356.4+297.6+1190.4 -> 2380.8 | P16: 1400 | S16: 12 | T16: 0 | V16: 6942.5 | W16: 385.92 | Y16: 12 | AE16: 12 | AK16: 12 | AQ16: 12 | AW16: 12 | BC16: 12 | BI16: 12 | BO16: 12
A17: 13 | B17: 26805.8 | C17: =537.3+402.3+493.2+981 -> 2413.8 | D17: 8650.47 | E17: 493.46 | G17: 13 | H17: 2760 | I17: 360 | J17: 18137.31 | K17: 1822.17 | M17: 13 | N17: 0 | O17: 0 | P17: 6660.56 | Q17: 417.71 | S17: 13 | T17: 0 | V17: 260.5 | Y17: 13 | AE17: 13 | AK17: 13 | AQ17: 13 | AW17: 13 | BC17: 13 | BI17: 13 | BO17: 13
A18: 14 | B18: 28885.1 | C18: =936.9+625.5+625.5+534.6+625.5 -> 3348 | D18: 27762.42 | E18: 482.92 | G18: 14 | H18: 28683.69 | I18: =536.4+356.4+477.6+1249.2 -> 2619.6 | J18: 3178.19 | K18: 205.85 | M18: 14 | N18: 28856 | O18: =654+356.4+418.8+1186.8 -> 2616 | P18: 500 | S18: 14 | T18: 24967.4 | U18: =477.6+266.4+297.6+949.8 -> 1991.4 | V18: =33752.5+13047.39 -> 46799.89 | W18: =4402.5+810.59 -> 5213.09 | Y18: 14 | AE18: 14 | AK18: 14 | AQ18: 14 | AW18: 14 | BC18: 14 | BI18: 14 | BO18: 14
A19: WEEKLY TOTALS | B19: =SUM(B12:B18) -> 129237.2 | C19: =SUM(C12:C18) -> 12007.5 | D19: =SUM(D12:D18) -> 75378.96 | E19: =SUM(E12:E18) -> 4015.36 | G19: WEEKLY TOTALS | H19: =SUM(H12:H18) -> 126267.59 | I19: =SUM(I12:I18) -> 12243.6 | J19: =SUM(J12:J18) -> 76791.76 | K19: =SUM(K12:K18) -> 4553.38 | M19: WEEKLY TOTALS | N19: =SUM(N12:N18) -> 127632.2 | O19: =SUM(O12:O18) -> 12288 | P19: =SUM(P12:P18) -> 69868.11 | Q19: =SUM(Q12:Q18) -> 6113.63 | S19: WEEKLY TOTALS | T19: =SUM(T12:T18) -> 134220.9 | U19: =SUM(U12:U18) -> 10728.3 | V19: =SUM(V12:V18) -> 117465.43 | W19: =SUM(W12:W18) -> 10591.48 | Y19: WEEKLY TOTALS | Z19: =SUM(Z12:Z18) -> 3661.6 | AA19: =SUM(AA12:AA18) -> 0 | AB19: =SUM(AB12:AB18) -> 8387.48 | AC19: =SUM(AC12:AC18) -> 431.08 | AE19: WEEKLY TOTALS | AF19: =SUM(AF12:AF18) -> 0 | AG19: =SUM(AG12:AG18) -> 0 | AH19: =SUM(AH12:AH18) -> 0 | AI19: =SUM(AI12:AI18) -> 0 | AK19: WEEKLY TOTALS | AL19: =SUM(AL12:AL18) -> 0 | AM19: =SUM(AM12:AM18) -> 0 | AN19: =SUM(AN12:AN18) -> 0 | AO19: =SUM(AO12:AO18) -> 0 | AQ19: WEEKLY TOTALS | AR19: =SUM(AR12:AR18) -> 0 | AS19: =SUM(AS12:AS18) -> 0 | AT19: =SUM(AT12:AT18) -> 0 | AU19: =SUM(AU12:AU18) -> 0 | AW19: WEEKLY TOTALS | AX19: =SUM(AX12:AX18) -> 0 | AY19: =SUM(AY12:AY18) -> 0 | AZ19: =SUM(AZ12:AZ18) -> 0 | BA19: =SUM(BA12:BA18) -> 0 | BC19: WEEKLY TOTALS | BD19: =SUM(BD12:BD18) -> 0 | BE19: =SUM(BE12:BE18) -> 0 | BF19: =SUM(BF12:BF18) -> 0 | BG19: =SUM(BG12:BG18) -> 0 | BI19: WEEKLY TOTALS | BJ19: =SUM(BJ12:BJ18) -> 0 | BK19: =SUM(BK12:BK18) -> 0 | BL19: =SUM(BL12:BL18) -> 0 | BM19: =SUM(BM12:BM18) -> 0 | BO19: WEEKLY TOTALS | BP19: =SUM(BP12:BP18) -> 0 | BQ19: =SUM(BQ12:BQ18) -> 0 | BR19: =SUM(BR12:BR18) -> 0 | BS19: =SUM(BS12:BS18) -> 0
A20: 15 | B20: 23408.9 | C20: =981+537.3+355.5 -> 1873.8 | D20: =13146.8+850.16 -> 13996.96 | E20: 1714.8 | G20: 15 | H20: 12637.29 | I20: =1429.2 -> 1429.2 | J20: 9539.46 | K20: 501.76 | M20: 15 | N20: 0 | O20: 0 | P20: 27177.58 | Q20: 360.72 | S20: 15 | T20: 28094.5 | U20: =1008.6+626.4+655.8+655.8+670.5 -> 3617.1 | V20: 11092.04 | W20: 658.34 | Y20: 15 | AE20: 15 | AK20: 15 | AQ20: 15 | AW20: 15 | BC20: 15 | BI20: 15 | BO20: 15
A21: 16 | B21: 0 | C21: 0 | D21: =2529.08+6381.41 -> 8910.49 | E21: =329.88+549.81 -> 879.69 | G21: 16 | H21: 0 | I21: 0 | J21: 3016.32 | K21: 23.08 | M21: 16 | N21: 0 | O21: 0 | P21: 1310.98 | S21: 16 | T21: 35129.8 | U21: =597+415.2+477.6+744+744 -> 2977.8 | V21: 19836.08 | W21: 1332.32 | Y21: 16 | AE21: 16 | AK21: 16 | AQ21: 16 | AW21: 16 | BC21: 16 | BI21: 16 | BO21: 16
A22: 17 | B22: 31505.8 | C22: =449.1+355.5+449.1+1160.1 -> 2413.8 | D22: 800 | E22: 0 | G22: 17 | H22: 31482 | I22: =238.8+238.8+178.2+178.2+238.8+238.8+1190.4 -> 2502 | J22: 11740.13 | K22: 620.22 | M22: 17 | N22: 34043.6 | O22: =536.4+356.4+356.4+1190.4 -> 2439.6 | P22: =18571.13+15513.96 -> 34085.09 | Q22: =2422.33+1017.1 -> 3439.43 | S22: 17 | T22: 55558.8 | U22: =1341+1038+1038+4577+1128+477.6+536.4+536.4+536.4 -> 11208.8 | V22: 17204.31 | W22: 1413.57 | Y22: 17 | AE22: 17 | AK22: 17 | AQ22: 17 | AW22: 17 | BC22: 17 | BI22: 17 | BO22: 17
A23: 18 | B23: 0 | C23: 0 | D23: 8858.38 | E23: 710.66 | G23: 18 | H23: 0 | I23: 0 | J23: 205.96 | M23: 18 | N23: 29122.6 | O23: =891+714.6+714.6+714.6+744 -> 3778.8 | P23: 9766.31 | Q23: 620.59 | S23: 18 | T23: 25209.6 | U23: =955.2+534.6+655.8 -> 2145.6 | V23: 8664.51 | W23: 550.46 | Y23: 18 | AE23: 18 | AK23: 18 | AQ23: 18 | AW23: 18 | BC23: 18 | BI23: 18 | BO23: 18
A24: 19 | B24: =7859.1+4238.9 -> 12098 | C24: =1025.1+552.9 -> 1578 | D24: 0 | E24: 0 | G24: 19 | H24: 26222 | I24: =418.8+356.4+297.6+1069.2 -> 2142 | J24: 35049.91 | K24: 4093.5 | M24: 19 | N24: 21171.2 | O24: =477.6+356.4+297.6+563.5 -> 1695.1 | P24: 800 | S24: 19 | Y24: 19 | AE24: 19 | AK24: 19 | AQ24: 19 | AW24: 19 | BC24: 19 | BI24: 19 | BO24: 19
A25: 20 | B25: 25595.6 | C25: =449.1+355.5+449.1+936.9 -> 2190.6 | D25: 14014.66 | E25: 405.27 | G25: 20 | H25: 32333.4 | I25: =538.2+949.8+655.8+655.8+655.8+744 -> 4199.4 | J25: 8944.16 | K25: 845.75 | M25: 20 | N25: 3668.5 | O25: =209.4+269.1 -> 478.5 | P25: 12864.27 | Q25: 1246.31 | S25: 20 | Y25: 20 | AE25: 20 | AK25: 20 | AQ25: 20 | AW25: 20 | BC25: 20 | BI25: 20 | BO25: 20
A26: 21 | B26: 30026.7 | C26: =1116+684.3+684.3+534.6+684.3 -> 3703.5 | D26: =24276.5+5275.21 -> 29551.71 | E26: =3166.5+372.47 -> 3538.97 | G26: 21 | H26: 26628 | I26: =481.2+356.4+360+1131.6 -> 2329.2 | J26: 7884.99 | K26: 24.13 | M26: 21 | N26: 34646 | O26: =775.2+415.2+477.6+1488 -> 3156 | P26: 800 | S26: 21 | T26: 26612.8 | U26: =657.6+356.4+477.6+1249.2 -> 2740.8 | V26: 7384.62 | W26: 351.57 | Y26: 21 | AE26: 21 | AK26: 21 | AQ26: 21 | AW26: 21 | BC26: 21 | BI26: 21 | BO26: 21
A27: WEEKLY TOTALS | B27: =SUM(B20:B26) -> 122635 | C27: =SUM(C20:C26) -> 11759.7 | D27: =SUM(D20:D26) -> 76132.2 | E27: =SUM(E20:E26) -> 7249.39 | G27: WEEKLY TOTALS | H27: =SUM(H20:H26) -> 129302.69 | I27: =SUM(I20:I26) -> 12601.8 | J27: =SUM(J20:J26) -> 76380.93 | K27: =SUM(K20:K26) -> 6108.44 | M27: WEEKLY TOTALS | N27: =SUM(N20:N26) -> 122651.9 | O27: =SUM(O20:O26) -> 11548 | P27: =SUM(P20:P26) -> 86804.23 | Q27: =SUM(Q20:Q26) -> 5667.05 | S27: WEEKLY TOTALS | T27: =SUM(T20:T26) -> 170605.5 | U27: =SUM(U20:U26) -> 22690.1 | V27: =SUM(V20:V26) -> 64181.56 | W27: =SUM(W20:W26) -> 4306.26 | Y27: WEEKLY TOTALS | Z27: =SUM(Z20:Z26) -> 0 | AA27: =SUM(AA20:AA26) -> 0 | AB27: =SUM(AB20:AB26) -> 0 | AC27: =SUM(AC20:AC26) -> 0 | AE27: WEEKLY TOTALS | AF27: =SUM(AF20:AF26) -> 0 | AG27: =SUM(AG20:AG26) -> 0 | AH27: =SUM(AH20:AH26) -> 0 | AI27: =SUM(AI20:AI26) -> 0 | AK27: WEEKLY TOTALS | AL27: =SUM(AL20:AL26) -> 0 | AM27: =SUM(AM20:AM26) -> 0 | AN27: =SUM(AN20:AN26) -> 0 | AO27: =SUM(AO20:AO26) -> 0 | AQ27: WEEKLY TOTALS | AR27: =SUM(AR20:AR26) -> 0 | AS27: =SUM(AS20:AS26) -> 0 | AT27: =SUM(AT20:AT26) -> 0 | AU27: =SUM(AU20:AU26) -> 0 | AW27: WEEKLY TOTALS | AX27: =SUM(AX20:AX26) -> 0 | AY27: =SUM(AY20:AY26) -> 0 | AZ27: =SUM(AZ20:AZ26) -> 0 | BA27: =SUM(BA20:BA26) -> 0 | BC27: WEEKLY TOTALS | BD27: =SUM(BD20:BD26) -> 0 | BE27: =SUM(BE20:BE26) -> 0 | BF27: =SUM(BF20:BF26) -> 0 | BG27: =SUM(BG20:BG26) -> 0 | BI27: WEEKLY TOTALS | BJ27: =SUM(BJ20:BJ26) -> 0 | BK27: =SUM(BK20:BK26) -> 0 | BL27: =SUM(BL20:BL26) -> 0 | BM27: =SUM(BM20:BM26) -> 0 | BO27: WEEKLY TOTALS | BP27: =SUM(BP20:BP26) -> 0 | BQ27: =SUM(BQ20:BQ26) -> 0 | BR27: =SUM(BR20:BR26) -> 0 | BS27: =SUM(BS20:BS26) -> 0
A28: 22 | B28: 22870.8 | C28: =449.1+355.5+449.1+1025.1 -> 2278.8 | D28: 2430.05 | E28: 212.61 | G28: 22 | H28: 0 | I28: 0 | J28: 800 | M28: 22 | S28: 22 | T28: 29157.1 | U28: =1067.4+567.6+714.6+714.6+714.6 -> 3778.8 | V28: 38188.24 | W28: 1285.08 | Y28: 22 | AE28: 22 | AK28: 22 | AQ28: 22 | AW28: 22 | BC28: 22 | BI28: 22 | BO28: 22
A29: 23 | B29: 5783.1 | C29: =449.1 -> 449.1 | D29: 27410.05 | E29: 1825.19 | G29: 23 | H29: 0 | I29: 0 | J29: 9461.27 | K29: 514.75 | M29: 23 | N29: 0 | O29: 0 | P29: 10302.1 | Q29: 672.45 | S29: 23 | T29: 30668.2 | U29: =597+356.4+297.6+1069.2 -> 2320.2 | V29: 800 | Y29: 23 | AE29: 23 | AK29: 23 | AQ29: 23 | AW29: 23 | BC29: 23 | BI29: 23 | BO29: 23
A30: 24 | B30: 21896 | C30: =446.4+628.2+581.4+1638.6 -> 3294.6 | D30: 8141.75 | E30: 21.37 | G30: 24 | H30: 28151.2 | I30: =418.8+356.4+297.6+1190.4 -> 2263.2 | J30: 10224.41 | K30: 627.75 | M30: 24 | N30: 28924.8 | O30: =477.6+356.4+297.6+744+744 -> 2619.6 | P30: =16974+8444.48 -> 25418.48 | Q30: =2214+543.1 -> 2757.1 | S30: 24 | T30: 7462.4 | U30: 536.4 | V30: 16538.32 | W30: 1498.74 | Y30: 24 | AE30: 24 | AK30: 24 | AQ30: 24 | AW30: 24 | BC30: 24 | BI30: 24 | BO30: 24
A31: 25 | B31: 17602.6 | C31: =1638.6 -> 1638.6 | D31: 2638.8 | E31: 31.15 | G31: 25 | H31: 0 | I31: 0 | J31: 9053.1 | K31: 470.67 | M31: 25 | N31: 32945.2 | O31: =1128+773.4+773.4+773.4+817.5 -> 4265.7 | P31: 14171.65 | Q31: 940.64 | S31: 25 | T31: 29589.8 | U31: =655.8+356.4+297.6+1488 -> 2797.8 | V31: 806.95 | Y31: 25 | AE31: 25 | AK31: 25 | AQ31: 25 | AW31: 25 | BC31: 25 | BI31: 25 | BO31: 25
A32: 26 | B32: 0 | C32: =0 -> 0 | D32: 6221.48 | E32: 546.85 | G32: 26 | H32: 29312.8 | I32: =536.4+356.4+418.8+1249.2 -> 2560.8 | J32: 13475.56 | K32: 1553.5 | M32: 26 | N32: 27003.6 | O32: =536.4+356.4+297.6+1249.2 -> 2439.6 | P32: 800 | Q32: 0 | S32: 26 | T32: 0 | V32: 31109.61 | W32: 530.38 | Y32: 26 | AE32: 26 | AK32: 26 | AQ32: 26 | AW32: 26 | BC32: 26 | BI32: 26 | BO32: 26
A33: 27 | B33: 30755.1 | C33: =311.4+581.4+493.2+1295.1 -> 2681.1 | D33: 6563.58 | E33: 490.76 | G33: 27 | H33: 38527.2 | I33: =360+1131.6+773.4+773.4+773.4+744 -> 4555.8 | J33: 21920.92 | K33: 2001.47 | M33: 27 | O33: 405.9 | S33: 27 | Y33: 27 | AE33: 27 | AK33: 27 | AQ33: 27 | AW33: 27 | BC33: 27 | BI33: 27 | BO33: 27
A34: 28 | B34: 32665.6 | C34: =804.6+1116+804.6+804.6+712.8 -> 4242.6 | D34: =12186.33+9366.47 -> 21552.8 | E34: =1589.53+619.27 -> 2208.8 | G34: 28 | H34: 37496 | I34: =775.2+415.2+477.6+1488 -> 3156 | J34: 5597.69 | K34: 625.79 | M34: 28 | N34: 34576 | O34: =775.2+415.2+477.6+1488 -> 3156 | P34: 5518.5 | Q34: 615.46 | S34: 28 | T34: 28052.8 | U34: =477.6+356.4+297.6+1249.2 -> 2380.8 | V34: 10279.14 | W34: 638.83 | Y34: 28 | AE34: 28 | AK34: 28 | AQ34: 28 | AW34: 28 | BC34: 28 | BI34: 28 | BO34: 28
A35: WEEKLY TOTALS | B35: =SUM(B28:B34) -> 131573.2 | C35: =SUM(C28:C34) -> 14584.8 | D35: =SUM(D28:D34) -> 74958.51 | E35: =SUM(E28:E34) -> 5336.73 | G35: WEEKLY TOTALS | H35: =SUM(H28:H34) -> 133487.2 | I35: =SUM(I28:I34) -> 12535.8 | J35: =SUM(J28:J34) -> 70532.95 | K35: =SUM(K28:K34) -> 5793.93 | M35: WEEKLY TOTALS | N35: =SUM(N28:N34) -> 123449.6 | O35: =SUM(O28:O34) -> 12886.8 | P35: =SUM(P28:P34) -> 56210.73 | Q35: =SUM(Q28:Q34) -> 4985.65 | S35: WEEKLY TOTALS | T35: =SUM(T28:T34) -> 124930.3 | U35: =SUM(U28:U34) -> 11814 | V35: =SUM(V28:V34) -> 97722.26 | W35: =SUM(W28:W34) -> 3953.03 | Y35: WEEKLY TOTALS | Z35: =SUM(Z28:Z34) -> 0 | AA35: =SUM(AA28:AA34) -> 0 | AB35: =SUM(AB28:AB34) -> 0 | AC35: =SUM(AC28:AC34) -> 0 | AE35: WEEKLY TOTALS | AF35: =SUM(AF28:AF34) -> 0 | AG35: =SUM(AG28:AG34) -> 0 | AH35: =SUM(AH28:AH34) -> 0 | AI35: =SUM(AI28:AI34) -> 0 | AK35: WEEKLY TOTALS | AL35: =SUM(AL28:AL34) -> 0 | AM35: =SUM(AM28:AM34) -> 0 | AN35: =SUM(AN28:AN34) -> 0 | AO35: =SUM(AO28:AO34) -> 0 | AQ35: WEEKLY TOTALS | AR35: =SUM(AR28:AR34) -> 0 | AS35: =SUM(AS28:AS34) -> 0 | AT35: =SUM(AT28:AT34) -> 0 | AU35: =SUM(AU28:AU34) -> 0 | AW35: WEEKLY TOTALS | AX35: =SUM(AX28:AX34) -> 0 | AY35: =SUM(AY28:AY34) -> 0 | AZ35: =SUM(AZ28:AZ34) -> 0 | BA35: =SUM(BA28:BA34) -> 0 | BC35: WEEKLY TOTALS | BD35: =SUM(BD28:BD34) -> 0 | BE35: =SUM(BE28:BE34) -> 0 | BF35: =SUM(BF28:BF34) -> 0 | BG35: =SUM(BG28:BG34) -> 0 | BI35: WEEKLY TOTALS | BJ35: =SUM(BJ28:BJ34) -> 0 | BK35: =SUM(BK28:BK34) -> 0 | BL35: =SUM(BL28:BL34) -> 0 | BM35: =SUM(BM28:BM34) -> 0 | BO35: WEEKLY TOTALS | BP35: =SUM(BP28:BP34) -> 0 | BQ35: =SUM(BQ28:BQ34) -> 0 | BR35: =SUM(BR28:BR34) -> 0 | BS35: =SUM(BS28:BS34) -> 0
A36: 29 | B36: 24271.6 | C36: 2368.8 | D36: 800.16 | E36: 0 | G36: 29 | M36: 29 | N36: 0 | P36: 39664.42 | Q36: 718.44 | S36: 29 | T36: 28387.4 | U36: =1067.4+567.6+714.6+714.6+655.8 -> 3720 | V36: =20531.88+8865.37 -> 29397.25 | W36: =2678.08+543.85 -> 3221.93 | Y36: 29 | AE36: 29 | AK36: 29 | AQ36: 29 | AW36: 29 | BC36: 29 | BI36: 29 | BO36: 29
A37: 30 | B37: 6046.2 | D37: 15263.9 | E37: 1587.44 | G37: 30 | M37: 30 | N37: 11597.2 | O37: =1069.2 -> 1069.2 | P37: 184.98 | Q37: 27.75 | S37: 30 | T37: 28387.4 | U37: =477.6+327+297.6+1069.2 -> 2171.4 | V37: 800 | Y37: 30 | AE37: 30 | AK37: 30 | AQ37: 30 | AW37: 30 | BC37: 30 | BI37: 30 | BO37: 30
A38: 31 | B38: 36233.2 | D38: 8525.79 | E38: 32.87 | G38: 31 | M38: 31 | N38: 32943.6 | O38: =477.6+356.4+356.4+1249.2 -> 2439.6 | P38: 14858.66 | Q38: 1080.12 | S38: 31 | Y38: 31 | AE38: 31 | AK38: 31 | AQ38: 31 | AW38: 31 | BC38: 31 | BI38: 31 | BO38: 31
A39: WEEKLY TOTALS | B39: =SUM(B36:B38) -> 66551 | C39: =SUM(C36:C38) -> 2368.8 | D39: =SUM(D36:D38) -> 24589.85 | E39: =SUM(E36:E38) -> 1620.31 | G39: WEEKLY TOTALS | H39: =SUM(H36:H38) -> 0 | I39: =SUM(I36:I38) -> 0 | J39: =SUM(J36:J38) -> 0 | K39: =SUM(K36:K38) -> 0 | M39: WEEKLY TOTALS | N39: =SUM(N36:N38) -> 44540.8 | O39: =SUM(O36:O38) -> 3508.8 | P39: =SUM(P36:P38) -> 54708.06 | Q39: =SUM(Q36:Q38) -> 1826.31 | S39: WEEKLY TOTALS | T39: =SUM(T36:T38) -> 56774.8 | U39: =SUM(U36:U38) -> 5891.4 | V39: =SUM(V36:V38) -> 30197.25 | W39: =SUM(W36:W38) -> 3221.93 | Y39: WEEKLY TOTALS | Z39: =SUM(Z36:Z38) -> 0 | AA39: =SUM(AA36:AA38) -> 0 | AB39: =SUM(AB36:AB38) -> 0 | AC39: =SUM(AC36:AC38) -> 0 | AE39: WEEKLY TOTALS | AF39: =SUM(AF36:AF38) -> 0 | AG39: =SUM(AG36:AG38) -> 0 | AH39: =SUM(AH36:AH38) -> 0 | AI39: =SUM(AI36:AI38) -> 0 | AK39: WEEKLY TOTALS | AL39: =SUM(AL36:AL38) -> 0 | AM39: =SUM(AM36:AM38) -> 0 | AN39: =SUM(AN36:AN38) -> 0 | AO39: =SUM(AO36:AO38) -> 0 | AQ39: WEEKLY TOTALS | AR39: =SUM(AR36:AR38) -> 0 | AS39: =SUM(AS36:AS38) -> 0 | AT39: =SUM(AT36:AT38) -> 0 | AU39: =SUM(AU36:AU38) -> 0 | AW39: WEEKLY TOTALS | AX39: =SUM(AX36:AX38) -> 0 | AY39: =SUM(AY36:AY38) -> 0 | AZ39: =SUM(AZ36:AZ38) -> 0 | BA39: =SUM(BA36:BA38) -> 0 | BC39: WEEKLY TOTALS | BD39: =SUM(BD36:BD38) -> 0 | BE39: =SUM(BE36:BE38) -> 0 | BF39: =SUM(BF36:BF38) -> 0 | BG39: =SUM(BG36:BG38) -> 0 | BI39: WEEKLY TOTALS | BJ39: =SUM(BJ36:BJ38) -> 0 | BK39: =SUM(BK36:BK38) -> 0 | BL39: =SUM(BL36:BL38) -> 0 | BM39: =SUM(BM36:BM38) -> 0 | BO39: WEEKLY TOTALS | BP39: =SUM(BP36:BP38) -> 0 | BQ39: =SUM(BQ36:BQ38) -> 0 | BR39: =SUM(BR36:BR38) -> 0 | BS39: =SUM(BS36:BS38) -> 0
B40: =SUM(B39,B35,B27,B19,B11) -> 584029.9 | C40: =SUM(C39,C35,C27,C19,C11) -> 52621.11 | D40: =SUM(D39,D35,D27,D19,D11) -> 364267.23 | E40: =SUM(E39,E35,E27,E19,E11) -> 25542.39 | H40: =SUM(H39,H35,H27,H19,H11) -> 539698.68 | I40: =SUM(I39,I35,I27,I19,I11) -> 50155.8 | J40: =SUM(J39,J35,J27,J19,J11) -> 306674.66 | K40: =SUM(K39,K35,K27,K19,K11) -> 23455.94 | N40: =SUM(N39,N35,N27,N19,N11) -> 543935.7 | O40: =SUM(O39,O35,O27,O19,O11) -> 51986.8 | P40: =SUM(P39,P35,P27,P19,P11) -> 335677.23 | Q40: =SUM(Q39,Q35,Q27,Q19,Q11) -> 22166.77 | T40: =SUM(T39,T35,T27,T19,T11) -> 623681.6 | U40: =SUM(U39,U35,U27,U19,U11) -> 64778.6 | V40: =SUM(V39,V35,V27,V19,V11) -> 366912.28 | W40: =SUM(W39,W35,W27,W19,W11) -> 27352.94 | Z40: =SUM(Z39,Z35,Z27,Z19,Z11) -> 155542.9 | AA40: =SUM(AA39,AA35,AA27,AA19,AA11) -> 5624.7 | AB40: =SUM(AB39,AB35,AB27,AB19,AB11) -> 83602.14 | AC40: =SUM(AC39,AC35,AC27,AC19,AC11) -> 3831.09 | AF40: =SUM(AF39,AF35,AF27,AF19,AF11) -> 0 | AG40: =SUM(AG39,AG35,AG27,AG19,AG11) -> 0 | AH40: =SUM(AH39,AH35,AH27,AH19,AH11) -> 0 | AI40: =SUM(AI39,AI35,AI27,AI19,AI11) -> 0 | AL40: =SUM(AL39,AL35,AL27,AL19,AL11) -> 0 | AM40: =SUM(AM39,AM35,AM27,AM19,AM11) -> 0 | AN40: =SUM(AN39,AN35,AN27,AN19,AN11) -> 0 | AO40: =SUM(AO39,AO35,AO27,AO19,AO11) -> 0 | AR40: =SUM(AR39,AR35,AR27,AR19,AR11) -> 0 | AS40: =SUM(AS39,AS35,AS27,AS19,AS11) -> 0 | AT40: =SUM(AT39,AT35,AT27,AT19,AT11) -> 0 | AU40: =SUM(AU39,AU35,AU27,AU19,AU11) -> 0 | AX40: =SUM(AX39,AX35,AX27,AX19,AX11) -> 0 | AY40: =SUM(AY39,AY35,AY27,AY19,AY11) -> 0 | AZ40: =SUM(AZ39,AZ35,AZ27,AZ19,AZ11) -> 0 | BA40: =SUM(BA39,BA35,BA27,BA19,BA11) -> 0 | BD40: =SUM(BD39,BD35,BD27,BD19,BD11) -> 0 | BE40: =SUM(BE39,BE35,BE27,BE19,BE11) -> 0 | BF40: =SUM(BF39,BF35,BF27,BF19,BF11) -> 0 | BG40: =SUM(BG39,BG35,BG27,BG19,BG11) -> 0 | BJ40: =SUM(BJ39,BJ35,BJ27,BJ19,BJ11) -> 0 | BK40: =SUM(BK39,BK35,BK27,BK19,BK11) -> 0 | BL40: =SUM(BL39,BL35,BL27,BL19,BL11) -> 0 | BM40: =SUM(BM39,BM35,BM27,BM19,BM11) -> 0 | BP40: =SUM(BP39,BP35,BP27,BP19,BP11) -> 0 | BQ40: =SUM(BQ39,BQ35,BQ27,BQ19,BQ11) -> 0 | BR40: =SUM(BR39,BR35,BR27,BR19,BR11) -> 0 | BS40: =SUM(BS39,BS35,BS27,BS19,BS11) -> 0
A41: =B40-D40 -> 219762.67 | G41: =H40-J40 -> 233024.02 | M41: =N40-P40 -> 208258.47 | S41: =T40-V40 -> 256769.32 | Y41: =Z40-AB40 -> 71940.76 | AE41: =AF40-AH40 -> 0 | AK41: =AL40-AN40 -> 0 | AQ41: =AR40-AT40 -> 0 | AW41: =(AX40-AZ40) -> 0 | BC41: =(BD40-BF40) -> 0 | BI41: =(BJ40-BL40) -> 0 | BO41: =(BP40-BR40) -> 0
A42: INC - EXP | G42: INC - EXP | M42: INC - EXP | S42: INC - EXP | Y42: INC - EXP | AE42: INC - EXP | AK42: INC - EXP | AQ42: INC - EXP | AW42: INC - EXP | BC42: INC - EXP | BI42: INC - EXP | BO42: INC - EXP
U84: 45289 | V84: 5670 | X84: INDLOVU SUPERSPAR
U85: 45289 | V85: 118151.08 | X85: CHECKERS
U86: 45289 | V86: 5000 | X86: CAROLINA SPAR

Sheet WEEKLY DELIVEIES & RETURN
B1: 31 MAR - 6 APR 2025 | D1: CHOCOLATE | E1: VANILLA | F1: CARROT | G1: TOTALS
B2: RIVERSIDE MALL CHECKERS | C2: DELIVERED | D2: 40 | E2: 24 | F2: 12 | G2: =SUM(D2:F2) -> 76
C3: TOTAL BEFORE RETURNS | D3: =D2*112.7 -> 4508 | E3: =E2*112.7 -> 2704.8 | F3: =F2*119.6 -> 1435.2 | G3: =SUM(D3:F3) -> 8648
C4: RETURNS | D4: 6 | E4: 4 | F4: 1 | G4: =SUM(D4:F4) -> 11
C5: RETURN TOTAL | D5: =D4*112.7 -> 676.2 | E5: =E4*112.7 -> 450.8 | F5: =F4*119.6 -> 119.6 | G5: =SUM(D5:F5) -> 1246.6
C6: GRAND TOTAL AFTER RETURNS | D6: =(D2-D4)*112.7 -> 3831.8 | E6: =(E2-E4)*112.7 -> 2254 | F6: =(F2-F4)*119.6 -> 1315.6 | G6: =G3-G5 -> 7401.4
B8: =B1 -> 31 MAR - 6 APR 2025 | D8: CHOCOLATE | E8: VANILLA | F8: CARROT | G8: TOTALS
B9: HYPER CHECKERS ORCHADS | C9: DELIVERED | D9: =28+36 -> 64 | E9: 28 | F9: 28 | G9: =SUM(D9:F9) -> 120
C10: TOTAL BEFORE RETURNS | D10: =D9*112.7 -> 7212.8 | E10: =E9*112.7 -> 3155.6 | F10: =F9*119.6 -> 3348.8 | G10: =SUM(D10:F10) -> 13717.2
C11: RETURNS | G11: =SUM(D11:F11) -> 0
C12: RETURN TOTAL | D12: =D11*112.7 -> 0 | E12: =E11*112.7 -> 0 | F12: =F11*119.6 -> 0 | G12: =SUM(D12:F12) -> 0
C13: GRAND TOTAL AFTER RETURNS | D13: =(D9-D11)*112.7 -> 7212.8 | E13: =(E9-E11)*112.7 -> 3155.6 | F13: =(F9-F11)*119.6 -> 3348.8 | G13: =G10-G12 -> 13717.2
B15: =B8 -> 31 MAR - 6 APR 2025 | D15: CHOCOLATE | E15: VANILLA | F15: CARROT | G15: TOTALS
B16: WITRIVIER CHECKERS | C16: DELIVERED | D16: =16+28 -> 44 | E16: 16 | F16: 16 | G16: =SUM(D16:F16) -> 76
C17: TOTAL BEFORE RETURNS | D17: =D16*112.7 -> 4958.8 | E17: =E16*112.7 -> 1803.2 | F17: =F16*119.6 -> 1913.6 | G17: =SUM(D17:F17) -> 8675.6
C18: RETURNS | D18: 1 | E18: 5 | G18: =SUM(D18:F18) -> 6
C19: RETURN TOTAL | D19: =D18*112.7 -> 112.7 | E19: =E18*112.7 -> 563.5 | F19: =F18*119.6 -> 0 | G19: =SUM(D19:F19) -> 676.2
C20: GRAND TOTAL AFTER RETURNS | D20: =(D16-D18)*112.7 -> 4846.1 | E20: =(E16-E18)*112.7 -> 1239.7 | F20: =(F16-F18)*119.6 -> 1913.6 | G20: =G17-G19 -> 7999.4
B22: =B15 -> 31 MAR - 6 APR 2025 | D22: CHOCOLATE | E22: VANILLA | F22: CARROT | G22: TOTALS
B23: HAZYVIEW CHECKERS | C23: DELIVERED | D23: =48+108+52+52 -> 260 | E23: 76 | F23: 76 | G23: =SUM(D23:F23) -> 412
C24: TOTAL BEFORE RETURNS | D24: =D23*112.7 -> 29302 | E24: =E23*112.7 -> 8565.2 | F24: =F23*119.6 -> 9089.6 | G24: =SUM(D24:F24) -> 46956.8
C25: RETURNS | D25: 11 | E25: 2 | F25: 3 | G25: =SUM(D25:F25) -> 16
C26: RETURN TOTAL | D26: =D25*112.7 -> 1239.7 | E26: =E25*112.7 -> 225.4 | F26: =F25*119.6 -> 358.8 | G26: =SUM(D26:F26) -> 1823.9
C27: GRAND TOTAL AFTER RETURNS | D27: =(D23-D25)*112.7 -> 28062.3 | E27: =(E23-E25)*112.7 -> 8339.8 | F27: =(F23-F25)*119.6 -> 8730.8 | G27: =G24-G26 -> 45132.9
B29: =B22 -> 31 MAR - 6 APR 2025 | D29: CHOCOLATE | E29: VANILLA | F29: CARROT | G29: TOTALS
B30: LYDENBURG CHECKERS | C30: DELIVERED | D30: 16 | E30: 8 | F30: 10 | G30: =SUM(D30:F30) -> 34
C31: TOTAL BEFORE RETURNS | D31: =D30*112.7 -> 1803.2 | E31: =E30*112.7 -> 901.6 | F31: =F30*119.6 -> 1196 | G31: =SUM(D31:F31) -> 3900.8
C32: RETURNS | D32: 8 | E32: 2 | F32: 4 | G32: =SUM(D32:F32) -> 14
C33: RETURN TOTAL | D33: =D32*112.7 -> 901.6 | E33: =E32*112.7 -> 225.4 | F33: =F32*119.6 -> 478.4 | G33: =SUM(D33:F33) -> 1605.4
C34: GRAND TOTAL AFTER RETURNS | D34: =(D30-D32)*112.7 -> 901.6 | E34: =(E30-E32)*112.7 -> 676.2 | F34: =(F30-F32)*119.6 -> 717.6 | G34: =G31-G33 -> 2295.4
B36: =B29 -> 31 MAR - 6 APR 2025 | D36: CHOCOLATE | E36: VANILLA | F36: CARROT | G36: TOTALS
B37: MIDDELBRUG CHECKERS | C37: DELIVERED | D37: 32 | E37: 10 | F37: 10 | G37: =SUM(D37:F37) -> 52
C38: TOTAL BEFORE RETURNS | D38: =D37*112.7 -> 3606.4 | E38: =E37*112.7 -> 1127 | F38: =F37*119.6 -> 1196 | G38: =SUM(D38:F38) -> 5929.4
C39: RETURNS | D39: 1 | G39: =SUM(D39:F39) -> 1
C40: RETURN TOTAL | D40: =D39*112.7 -> 112.7 | E40: =E39*112.7 -> 0 | F40: =F39*119.6 -> 0 | G40: =SUM(D40:F40) -> 112.7
C41: GRAND TOTAL AFTER RETURNS | D41: =(D37-D39)*112.7 -> 3493.7 | E41: =(E37-E39)*112.7 -> 1127 | F41: =(F37-F39)*119.6 -> 1196 | G41: =G38-G40 -> 5816.7
B43: =B36 -> 31 MAR - 6 APR 2025 | D43: CHOCOLATE | E43: VANILLA | F43: CARROT | G43: TOTALS
B44: ERMELO CHECKERS | C44: DELIVERED | D44: 52 | E44: 12 | F44: 12 | G44: =SUM(D44:F44) -> 76
C45: TOTAL BEFORE RETURNS | D45: =D44*112.7 -> 5860.4 | E45: =E44*112.7 -> 1352.4 | F45: =F44*119.6 -> 1435.2 | G45: =SUM(D45:F45) -> 8648
C46: RETURNS | G46: =SUM(D46:F46) -> 0
C47: RETURN TOTAL | D47: =D46*112.7 -> 0 | E47: =E46*112.7 -> 0 | F47: =F46*119.6 -> 0 | G47: =SUM(D47:F47) -> 0
C48: GRAND TOTAL AFTER RETURNS | D48: =(D44-D46)*112.7 -> 5860.4 | E48: =(E44-E46)*112.7 -> 1352.4 | F48: =(F44-F46)*119.6 -> 1435.2 | G48: =G45-G47 -> 8648
B50: =B43 -> 31 MAR - 6 APR 2025 | D50: CHOCOLATE | E50: VANILLA | F50: CARROT | G50: TOTALS
B51: ERMELO MERINO MALL | C51: DELIVERED | D51: 32 | E51: 10 | F51: 10 | G51: =SUM(D51:F51) -> 52
C52: TOTAL BEFORE RETURNS | D52: =D51*112.7 -> 3606.4 | E52: =E51*112.7 -> 1127 | F52: =F51*119.6 -> 1196 | G52: =SUM(D52:F52) -> 5929.4
C53: RETURNS | D53: 7 | G53: =SUM(D53:F53) -> 7
C54: RETURN TOTAL | D54: =D53*112.7 -> 788.9 | E54: =E53*112.7 -> 0 | F54: =F53*119.6 -> 0 | G54: =SUM(D54:F54) -> 788.9
C55: GRAND TOTAL AFTER RETURNS | D55: =(D51-D53)*112.7 -> 2817.5 | E55: =(E51-E53)*112.7 -> 1127 | F55: =(F51-F53)*119.6 -> 1196 | G55: =G52-G54 -> 5140.5
B57: =B50 -> 31 MAR - 6 APR 2025 | D57: CHOCOLATE | E57: VANILLA | F57: CARROT | G57: TOTALS
B58: SAVEWAYS | C58: DELIVERED | D58: 32 | E58: 10 | F58: 10 | G58: =SUM(D58:F58) -> 52
C59: TOTAL BEFORE RETURNS | D59: =D58*112.7 -> 3606.4 | E59: =E58*112.7 -> 1127 | F59: =F58*119.6 -> 1196 | G59: =SUM(D59:F59) -> 5929.4
C60: RETURNS | G60: =SUM(D60:F60) -> 0
C61: RETURN TOTAL | D61: =D60*112.7 -> 0 | E61: =E60*112.7 -> 0 | F61: =F60*119.6 -> 0 | G61: =SUM(D61:F61) -> 0
C62: GRAND TOTAL AFTER RETURNS | D62: =(D58-D60)*112.7 -> 3606.4 | E62: =(E58-E60)*112.7 -> 1127 | F62: =(F58-F60)*119.6 -> 1196 | G62: =G59-G61 -> 5929.4
B64: =B57 -> 31 MAR - 6 APR 2025 | D64: CHOCOLATE | E64: VANILLA | F64: CARROT | G64: TOTALS
B65: KLIPFONTEIN | C65: DELIVERED | D65: 30 | E65: 12 | F65: 10 | G65: =SUM(D65:F65) -> 52
C66: TOTAL BEFORE RETURNS | D66: =D65*112.7 -> 3381 | E66: =E65*112.7 -> 1352.4 | F66: =F65*119.6 -> 1196 | G66: =SUM(D66:F66) -> 5929.4
C67: RETURNS | D67: 7 | F67: 6 | G67: =SUM(D67:F67) -> 13
C68: RETURN TOTAL | D68: =D67*112.7 -> 788.9 | E68: =E67*112.7 -> 0 | F68: =F67*119.6 -> 717.6 | G68: =SUM(D68:F68) -> 1506.5
C69: GRAND TOTAL AFTER RETURNS | D69: =(D65-D67)*112.7 -> 2592.1 | E69: =(E65-E67)*112.7 -> 1352.4 | F69: =(F65-F67)*119.6 -> 478.4 | G69: =G66-G68 -> 4422.9
B71: =B64 -> 31 MAR - 6 APR 2025 | D71: CHOCOLATE | E71: VANILLA | F71: COFFEE | G71: CARROT | H71: DARKM | I71: TOTALS
B72: BARBERTON PNP | C72: DELIVERED | D72: 44 | E72: 53 | F72: 18 | G72: 33 | H72: 63 | I72: =SUM(D72:H72) -> 211
C73: TOTAL BEFORE RETURNS | D73: =D72*100 -> 4400 | E73: =E72*100 -> 5300 | F73: =F72*100 -> 1800 | G73: =G72*100 -> 3300 | H73: =H72*100 -> 6300 | I73: =SUM(D73:H73) -> 21100
C74: RETURNS | D74: 1 | F74: 1 | I74: =SUM(D74:H74) -> 2
C75: RETURN TOTAL | D75: =D74*112.7 -> 112.7 | E75: =E74*112.7 -> 0 | F75: =F74*119.6 -> 119.6 | G75: =G74*112.7 -> 0 | H75: =H74*112.7 -> 0 | I75: =SUM(D75:H75) -> 232.3
C76: GRAND TOTAL AFTER RETURNS | D76: =(D72-D74)*112.7 -> 4846.1 | E76: =(E72-E74)*112.7 -> 5973.1 | F76: =(F72-F74)*119.6 -> 2033.2 | G76: =(G72-G74)*112.7 -> 3719.1 | H76: =(H72-H74)*112.7 -> 7100.1 | I76: =SUM(D76:H76) -> 23671.6
B78: =B71 -> 31 MAR - 6 APR 2025 | D78: CHOCOLATE | E78: VANILLA | F78: COFFEE | G78: CARROT | H78: DARKM | I78: TOTALS
B79: PLAZA SPAR | C79: DELIVERED | D79: 12 | E79: 4 | F79: 12 | H79: 12 | I79: =SUM(D79:H79) -> 40
C80: TOTAL BEFORE RETURNS | D80: =D79*120 -> 1440 | E80: =E79*120 -> 480 | F80: =F79*120 -> 1440 | G80: =G79*120 -> 0 | H80: =H79*120 -> 1440 | I80: =SUM(D80:H80) -> 4800
C81: RETURNS | I81: =SUM(D81:H81) -> 0
C82: RETURN TOTAL | D82: =D81*112.7 -> 0 | E82: =E81*112.7 -> 0 | F82: =F81*119.6 -> 0 | G82: =G81*112.7 -> 0 | H82: =H81*112.7 -> 0 | I82: =SUM(D82:H82) -> 0
C83: GRAND TOTAL AFTER RETURNS | D83: =(D79-D81)*112.7 -> 1352.4 | E83: =(E79-E81)*112.7 -> 450.8 | F83: =(F79-F81)*119.6 -> 1435.2 | G83: =(G79-G81)*112.7 -> 0 | H83: =(H79-H81)*112.7 -> 1352.4 | I83: =SUM(D83:H83) -> 4590.8
B85: =B78 -> 31 MAR - 6 APR 2025 | D85: CHOCOLATE | E85: VANILLA | F85: COFFEE | G85: CARROT | H85: DARKM | I85: TOTALS
B86: GROVE SPAR | C86: DELIVERED | I86: =SUM(D86:H86) -> 0
C87: TOTAL BEFORE RETURNS | D87: =D86*120 -> 0 | E87: =E86*120 -> 0 | F87: =F86*120 -> 0 | G87: =G86*120 -> 0 | H87: =H86*120 -> 0 | I87: =SUM(D87:H87) -> 0
C88: RETURNS | I88: =SUM(D88:H88) -> 0
C89: RETURN TOTAL | D89: =D88*112.7 -> 0 | E89: =E88*112.7 -> 0 | F89: =F88*119.6 -> 0 | G89: =G88*112.7 -> 0 | H89: =H88*112.7 -> 0 | I89: =SUM(D89:H89) -> 0
C90: GRAND TOTAL AFTER RETURNS | D90: =(D86-D88)*112.7 -> 0 | E90: =(E86-E88)*112.7 -> 0 | F90: =(F86-F88)*119.6 -> 0 | G90: =(G86-G88)*112.7 -> 0 | H90: =(H86-H88)*112.7 -> 0 | I90: =SUM(D90:H90) -> 0
B93: =B85 -> 31 MAR - 6 APR 2025 | D93: CHOCOLATE | E93: VANILLA | F93: COFFEE | G93: CARROT | H93: DARKM | I93: TOTALS
B94: HAZYVIEW SPAR | C94: DELIVERED | D94: 10 | E94: 5 | F94: 5 | G94: 5 | H94: 10 | I94: =SUM(D94:H94) -> 35
C95: TOTAL BEFORE RETURNS | D95: =D94*120 -> 1200 | E95: =E94*120 -> 600 | F95: =F94*120 -> 600 | G95: =G94*120 -> 600 | H95: =H94*120 -> 1200 | I95: =SUM(D95:H95) -> 4200
C96: RETURNS | G96: 2 | H96: 1 | I96: =SUM(D96:H96) -> 3
C97: RETURN TOTAL | D97: =D96*112.7 -> 0 | E97: =E96*112.7 -> 0 | F97: =F96*119.6 -> 0 | G97: =G96*112.7 -> 225.4 | H97: =H96*112.7 -> 112.7 | I97: =SUM(D97:H97) -> 338.1
C98: GRAND TOTAL AFTER RETURNS | D98: =(D94-D96)*112.7 -> 1127 | E98: =(E94-E96)*112.7 -> 563.5 | F98: =(F94-F96)*119.6 -> 598 | G98: =(G94-G96)*112.7 -> 338.1 | H98: =(H94-H96)*112.7 -> 1014.3 | I98: =SUM(D98:H98) -> 3640.9
B101: 7 - 13 APR 2025 | D101: CHOCOLATE | E101: VANILLA | F101: CARROT | G101: TOTALS
B102: RIVERSIDE MALL CHECKERS | C102: DELIVERED | D102: 34 | E102: 22 | F102: 10 | G102: =SUM(D102:F102) -> 66
C103: TOTAL BEFORE RETURNS | D103: =D102*112.7 -> 3831.8 | E103: =E102*112.7 -> 2479.4 | F103: =F102*119.6 -> 1196 | G103: =SUM(D103:F103) -> 7507.2
C104: RETURNS | D104: 1 | E104: 1 | G104: =SUM(D104:F104) -> 2
C105: RETURN TOTAL | D105: =D104*112.7 -> 112.7 | E105: =E104*112.7 -> 112.7 | F105: =F104*119.6 -> 0 | G105: =SUM(D105:F105) -> 225.4
C106: GRAND TOTAL AFTER RETURNS | D106: =(D102-D104)*112.7 -> 3719.1 | E106: =(E102-E104)*112.7 -> 2366.7 | F106: =(F102-F104)*119.6 -> 1196 | G106: =G103-G105 -> 7281.8
B108: =B101 -> 7 - 13 APR 2025 | D108: CHOCOLATE | E108: VANILLA | F108: CARROT | G108: TOTALS
B109: HYPER CHECKERS ORCHADS | C109: DELIVERED | D109: 52 | E109: 26 | F109: 26 | G109: =SUM(D109:F109) -> 104
C110: TOTAL BEFORE RETURNS | D110: =D109*112.7 -> 5860.4 | E110: =E109*112.7 -> 2930.2 | F110: =F109*119.6 -> 3109.6 | G110: =SUM(D110:F110) -> 11900.2
C111: RETURNS | G111: =SUM(D111:F111) -> 0
C112: RETURN TOTAL | D112: =D111*112.7 -> 0 | E112: =E111*112.7 -> 0 | F112: =F111*119.6 -> 0 | G112: =SUM(D112:F112) -> 0
C113: GRAND TOTAL AFTER RETURNS | D113: =(D109-D111)*112.7 -> 5860.4 | E113: =(E109-E111)*112.7 -> 2930.2 | F113: =(F109-F111)*119.6 -> 3109.6 | G113: =G110-G112 -> 11900.2
B115: =B108 -> 7 - 13 APR 2025 | D115: CHOCOLATE | E115: VANILLA | F115: CARROT | G115: TOTALS
B116: WITRIVIER CHECKERS | C116: DELIVERED | D116: 40 | E116: 16 | F116: 16 | G116: =SUM(D116:F116) -> 72
C117: TOTAL BEFORE RETURNS | D117: =D116*112.7 -> 4508 | E117: =E116*112.7 -> 1803.2 | F117: =F116*119.6 -> 1913.6 | G117: =SUM(D117:F117) -> 8224.8
C118: RETURNS | G118: =SUM(D118:F118) -> 0
...

Sheet DAILY PLANNING
D1: 45656 | F1: DAY | G1: MONDAY
F2: Units | G2: Units
F3: 6am | G3: 6pm | H3: Use
D5: Write down the electricity use
F6: CHOC 7 | G6: VAN 7 | H6: COFFEE7 | I6: CARROT 11 | J6: DM 9 | K6: TOTAL
D7: Batches | F7: 15 | G7: 9 | H7: 4 | I7: 5 | J7: 9 | K7: =SUM(F7:J7) -> 42
D8: Totals | F8: 105 | G8: 63 | H8: 28 | I8: 55 | J8: 81 | K8: =SUM(F8:J8) -> 332
D9: FLOPS | K9: =SUM(F9:J9) -> 0
D10: CASH SALES | F10: 1 | G10: 1 | J10: 2 | K10: =SUM(F10:J10) -> 4
D11: LEFT PREVIOUS DAY | F11: 52 | G11: 24 | H11: 21 | I11: 31 | J11: 42 | K11: =SUM(F11:J11) -> 170
D12: TOTAL | F12: =(F8+F11)-F10-F9 -> 156 | G12: =(G8+G11)-G10-G9 -> 86 | H12: =(H8+H11)-H10 -> 49 | I12: =(I8+I11)-I10-I9 -> 86 | J12: =(J8+J11)-J10-J9 -> 121 | K12: =(K8+K11)-K10-K9 -> 498
C14: Order no | D14: DELIVERIES | E14: TOTAL | F14: CHOC | G14: VAN | H14: COFFEE | I14: CARROT | J14: DM | K14: TOTAL | L14: CRATES
C15: INV 69 | D15: BARBERTON PNP | E15: =(F15+G15+H15+I15+J15)*100+(0*230) -> 8600 | F15: 25 | G15: 15 | H15: 9 | I15: 12 | J15: 25 | K15: =SUM(F15:J15) -> 86 | L15: =K15/4 -> 21.5
D16: Tuisbedryf | E16: =(F16+G16+H16+I16+J16)*120 -> 0 | K16: =SUM(F16:J16) -> 0 | L16: =K16/4 -> 0
D17: Grove Spar Riverside | E17: =(F17+G17+H17+I17+J17)*120 -> 0 | K17: =SUM(F17:J17) -> 0 | L17: =K17/4 -> 0
C18: INV 53 | D18: Plaza Spar Nelspruit | E18: =(F18+G18+H18+I18+J18)*120 -> 2400 | F18: 6 | G18: 2 | H18: 6 | J18: 6 | K18: =SUM(F18:J18) -> 20 | L18: =K18/4 -> 5
D19: STEILTES SPAR | E19: =(F19+G19+H19+I19+J19)*120 -> 0 | K19: =SUM(F19:J19) -> 0 | L19: =K19/4 -> 0
L20: =K20/4 -> 0
C21: 1167008473/1167621277 | D21: HYPER CHECKERS ORCHADS | E21: =(F21+G21+H21+J21)*112.7+(I21*119.6) -> 5041.6 | F21: 10 | G21: 12 | I21: 12 | J21: 10 | K21: =SUM(F21:J21) -> 44 | L21: =K21/4 -> 11
C22: 1167621273 | D22: RIVERSIDE CHECKERS | E22: =(F22+G22+H22+J22)*112.7+(I22*119.6) -> 2732.4 | F22: 6 | G22: 4 | H22: 4 | I22: 4 | J22: 6 | K22: =SUM(F22:J22) -> 24 | L22: =K22/4 -> 6
C23: 1167621276 | D23: WHITERIVER CHECKERS | E23: =(F23+G23+H23+J23)*112.7+(I23*119.6) -> 3661.6 | F23: 8 | G23: 8 | I23: 8 | J23: 8 | K23: =SUM(F23:J23) -> 32 | L23: =K23/4 -> 8
L24: =K24/4 -> 0
D25: HAZYVIEW SPAR NDLOVU | E25: =(F25+G25+H25+I25+J25)*120 -> 0 | K25: =SUM(F25:J25) -> 0 | L25: =K25/4 -> 0
C26: 1167008471 | D26: HAZYVIEW CHECKERS | E26: =(F26+G26+H26+J26)*112.7+(I26*119.6) -> 10957.2 | F26: 40 | G26: 16 | I26: 20 | J26: 20 | K26: =SUM(F26:J26) -> 96 | L26: =K26/4 -> 24
K27: =SUM(F27:J27) -> 0 | L27: =K27/4 -> 0
D28: LYDENBURG PNP | E28: =(F28+G28+H28+I28+J28)*120+(240*0)+(0*45) -> 0 | K28: =SUM(F28:J28) -> 0 | L28: =K28/4 -> 0
D29: LYDENBURG CHECKERS | E29: =(F29+G29+H29+J29)*112.7+(I29*119.6) -> 0 | K29: =SUM(F29:J29) -> 0 | L29: =K29/4 -> 0
L30: =K30/4 -> 0
D31: COUNTRY KING | E31: =(F31+G31+H31+I31+J31)*120 -> 0 | K31: =SUM(F31:J31) -> 0 | L31: =K31/4 -> 0
D32: CAROLINA SPAR | E32: =(F32+G32+H32+I32+J32)*120 -> 0 | K32: =SUM(F32:J32) -> 0 | L32: =K32/4 -> 0
D33: ERMELO CHECKERS | E33: =(F33+G33+H33+I33)*112.7+(J33*119.6) -> 0 | K33: =SUM(F33:J33) -> 0 | L33: =K33/4 -> 0
D34: ERMELO MERINO MALL | E34: =(F34+G34+H34+I34)*112.7+(J34*119.6) -> 0 | K34: =SUM(F34:J34) -> 0 | L34: =K34/4 -> 0
D35: MIDDELBURG MALL CHECKERS | E35: =(F35+G35+H35+I35)*112.7+(J35*119.6) -> 0 | K35: =SUM(F35:J35) -> 0 | L35: =K35/4 -> 0
D36: SAVEWAYS | E36: =(F36+G36+H36+I36)*112.7+(J36*119.6) -> 0 | K36: =SUM(F36:J36) -> 0 | L36: =K36/4 -> 0
D37: KLIPFONTEIN | E37: =(F37+G37+H37+I37)*112.7+(J37*119.6) -> 0 | K37: =SUM(F37:J37) -> 0 | L37: =K37/4 -> 0
D38: MARCO | K38: =SUM(F38:J38) -> 0
K39: =SUM(F39:J39) -> 0
D41: TOTALS | E41: =SUM(E15:E37) -> 33392.8 | F41: =SUM(F15:F40) -> 95 | G41: =SUM(G15:G40) -> 57 | H41: =SUM(H15:H40) -> 19 | I41: =SUM(I15:I40) -> 56 | J41: =SUM(J15:J40) -> 75 | K41: =SUM(F41:J41) -> 302 | L41: =SUM(L15:L40) -> 75.5
D42: TOTAL CAKES LEFT AFTER | F42: =F12-F41 -> 61 | G42: =G12-G41 -> 29 | H42: =H12-H41 -> 30 | I42: =I12-I41 -> 30 | J42: =J12-J41 -> 46 | K42: =SUM(F42:J42) -> 196
D43: DAMAGES | K43: =K41+K42 -> 498
D45: 45657 | F45: DAY | G45: TUESDAY
F46: Units | G46: Units
F47: 6am | G47: 6pm | H47: Use
D49: Write down the electricity use
F50: CHOC 7 | G50: VAN 7 | H50: COFFEE7 | I50: CARROT 11 | J50: DM 9 | K50: TOTAL
D51: Batches | F51: 9 | G51: 11 | I51: 6 | J51: 9 | K51: =SUM(F51:J51) -> 35
D52: Totals | F52: 61 | G52: 77 | I52: 66 | J52: 76 | K52: =SUM(F52:J52) -> 280
D53: FLOPS | K53: =SUM(F53:J53) -> 0
D54: CASH SALES | I54: 2 | J54: 1 | K54: =SUM(F54:J54) -> 3
D55: LEFT PREVIOUS DAY | F55: 62 | G55: 25 | I55: 22 | J55: 50 | K55: =SUM(F55:J55) -> 159
D56: TOTAL | F56: =(F52+F55)-F54-F53 -> 123 | G56: =(G52+G55)-G54-G53 -> 102 | H56: =(H52+H55)-H54 -> 0 | I56: =(I52+I55)-I54-I53 -> 86 | J56: =(J52+J55)-J54-J53 -> 125 | K56: =(K52+K55)-K54-K53 -> 436
C58: Order no | D58: DELIVERIES | E58: TOTAL | F58: CHOC | G58: VAN | H58: COFFEE | I58: CARROT | J58: DM | K58: TOTAL | L58: CRATES
D59: BARBERTON PNP | E59: =(F59+G59+H59+I59+J59)*100+(0*230) -> 0 | K59: =SUM(F59:J59) -> 0 | L59: =K59/4 -> 0
D60: Tuisbedryf | E60: =(F60+G60+H60+I60+J60)*120 -> 0 | K60: =SUM(F60:J60) -> 0 | L60: =K60/4 -> 0
D61: Grove Spar Riverside | E61: =(F61+G61+H61+I61+J61)*120 -> 0 | K61: =SUM(F61:J61) -> 0 | L61: =K61/4 -> 0
D62: Plaza Spar Nelspruit | E62: =(F62+G62+H62+I62+J62)*120 -> 0 | K62: =SUM(F62:J62) -> 0 | L62: =K62/4 -> 0
D63: STEILTES SPAR | E63: =(F63+G63+H63+I63+J63)*120 -> 0 | K63: =SUM(F63:J63) -> 0 | L63: =K63/4 -> 0
L64: =K64/4 -> 0
D65: HYPER CHECKERS ORCHADS | E65: =(F65+G65+H65+J65)*112.7+(I65*119.6) -> 0 | K65: =SUM(F65:J65) -> 0 | L65: =K65/4 -> 0
D66: RIVERSIDE CHECKERS | E66: =(F66+G66+H66+J66)*112.7+(I66*119.6) -> 0 | K66: =SUM(F66:J66) -> 0 | L66: =K66/4 -> 0
D67: WHITERIVER CHECKERS | E67: =(F67+G67+H67+J67)*112.7+(I67*119.6) -> 0 | K67: =SUM(F67:J67) -> 0 | L67: =K67/4 -> 0
L68: =K68/4 -> 0
D69: HAZYVIEW SPAR NDLOVU | E69: =(F69+G69+H69+I69+J69)*120 -> 0 | K69: =SUM(F69:J69) -> 0 | L69: =K69/4 -> 0
C70: 11665334513 | D70: HAZYVIEW CHECKERS | E70: =(F70+G70+H70+J70)*112.7+(I70*119.6) -> 8576.7 | F70: 28 | G70: 16 | I70: 18 | J70: 13 | K70: =SUM(F70:J70) -> 75 | L70: =K70/4 -> 18.75
K71: =SUM(F71:J71) -> 0 | L71: =K71/4 -> 0
D72: LYDENBURG PNP | E72: =(F72+G72+H72+I72+J72)*120+(240*0)+(0*45) -> 0 | K72: =SUM(F72:J72) -> 0 | L72: =K72/4 -> 0
D73: LYDENBURG CHECKERS | E73: =(F73+G73+H73+J73)*112.7+(I73*119.6) -> 0 | K73: =SUM(F73:J73) -> 0 | L73: =K73/4 -> 0
L74: =K74/4 -> 0
C75: INV 71 | D75: COUNTRY KING | E75: =(F75+G75+H75+I75+J75)*120 -> 2400 | F75: 7 | G75: 3 | I75: 3 | J75: 7 | K75: =SUM(F75:J75) -> 20 | L75: =K75/4 -> 5
D76: CAROLINA SPAR | E76: =(F76+G76+H76+I76+J76)*120 -> 0 | K76: =SUM(F76:J76) -> 0 | L76: =K76/4 -> 0
D77: ERMELO CHECKERS | E77: =(F77+G77+H77+I77)*112.7+(J77*119.6) -> 8280 | F77: 24 | G77: 12 | I77: 12 | J77: 24 | K77: =SUM(F77:J77) -> 72 | L77: =K77/4 -> 18
C78: 1168944385 | D78: ERMELO MERINO MALL | E78: =(F78+G78+H78+I78)*112.7+(J78*119.6) -> 6189.3 | F78: 15 | G78: 12 | I78: 12 | J78: 15 | K78: =SUM(F78:J78) -> 54 | L78: =K78/4 -> 13.5
C79: 1168944428 | D79: MIDDELBURG MALL CHECKERS | E79: =(F79+G79+H79+I79)*112.7+(J79*119.6) -> 6189.3 | F79: 15 | G79: 12 | I79: 12 | J79: 15 | K79: =SUM(F79:J79) -> 54 | L79: =K79/4 -> 13.5
C80: 1168944430 | D80: SAVEWAYS | E80: =(F80+G80+H80+I80)*112.7+(J80*119.6) -> 6189.3 | F80: 15 | G80: 12 | I80: 12 | J80: 15 | K80: =SUM(F80:J80) -> 54 | L80: =K80/4 -> 13.5
C81: 1168944427 | D81: KLIPFONTEIN | E81: =(F81+G81+H81+I81)*112.7+(J81*119.6) -> 7090.9 | F81: 15 | G81: 20 | I81: 12 | J81: 15 | K81: =SUM(F81:J81) -> 62 | L81: =K81/4 -> 15.5
D82: MARCO | K82: =SUM(F82:J82) -> 0
D83: REPLACEMENTS KLIPFONTEIN & ERMELO | F83: 3 | G83: 5 | I83: 2 | J83: 3 | K83: =SUM(F83:J83) -> 13
D85: TOTALS | E85: =SUM(E59:E81) -> 44915.5 | F85: =SUM(F59:F84) -> 122 | G85: =SUM(G59:G84) -> 92 | H85: =SUM(H59:H84) -> 0 | I85: =SUM(I59:I84) -> 83 | J85: =SUM(J59:J84) -> 107 | K85: =SUM(F85:J85) -> 404 | L85: =SUM(L59:L84) -> 97.75
D86: TOTAL CAKES LEFT AFTER | F86: =F56-F85 -> 1 | G86: =G56-G85 -> 10 | H86: =H56-H85 -> 0 | I86: =I56-I85 -> 3 | J86: =J56-J85 -> 18 | K86: =SUM(F86:J86) -> 32
D87: DAMAGES | K87: =K85+K86 -> 436
D89: 45658 | F89: DAY | G89: WEDNESDAY
F90: Units | G90: Units
F91: 6am | G91: 6pm | H91: Use
D93: Write down the electricity use
F94: CHOC 7 | G94: VAN 7 | H94: COFFEE7 | I94: CARROT 11 | J94: DM 9 | K94: TOTAL
D95: Batches | F95: 12 | G95: 7 | I95: 5 | J95: 7 | K95: =SUM(F95:J95) -> 31
D96: Totals | F96: 82 | G96: 49 | I96: 55 | J96: 63 | K96: =SUM(F96:J96) -> 249
D97: FLOPS | K97: =SUM(F97:J97) -> 0
D98: CASH SALES | F98: 8 | G98: 5 | J98: 3 | K98: =SUM(F98:J98) -> 16
D99: LEFT PREVIOUS DAY | H99: 17 | I99: 4 | K99: =SUM(F99:J99) -> 21
D100: TOTAL | F100: =(F96+F99)-F98-F97 -> 74 | G100: =(G96+G99)-G98-G97 -> 44 | H100: =(H96+H99)-H98 -> 17 | I100: =(I96+I99)-I98-I97 -> 59 | J100: =(J96+J99)-J98-J97 -> 60 | K100: =(K96+K99)-K98-K97 -> 254
C102: Order no | D102: DELIVERIES | E102: TOTAL | F102: CHOC | G102: VAN | H102: COFFEE | I102: CARROT | J102: DM | K102: TOTAL | L102: CRATES
C103: INV 19 | D103: BARBERTON PNP | E103: =(F103+G103+H103+I103+J103)*100+(0*230) -> 6400 | F103: 14 | G103: 12 | H103: 9 | I103: 9 | J103: 20 | K103: =SUM(F103:J103) -> 64 | L103: =K103/4 -> 16
D104: Tuisbedryf | E104: =(F104+G104+H104+I104+J104)*120 -> 0 | K104: =SUM(F104:J104) -> 0 | L104: =K104/4 -> 0
D105: Grove Spar Riverside | E105: =(F105+G105+H105+I105+J105)*120 -> 0 | K105: =SUM(F105:J105) -> 0 | L105: =K105/4 -> 0
D106: Plaza Spar Nelspruit | E106: =(F106+G106+H106+I106+J106)*120 -> 0 | K106: =SUM(F106:J106) -> 0 | L106: =K106/4 -> 0
D107: STEILTES SPAR | E107: =(F107+G107+H107+I107+J107)*120 -> 0 | K107: =SUM(F107:J107) -> 0 | L107: =K107/4 -> 0
L108: =K108/4 -> 0
C109: 1165334515/1167013338 | D109: HYPER CHECKERS ORCHADS | E109: =(F109+G109+H109+J109)*112.7+(I109*119.6) -> 3661.6 | F109: 8 | G109: 4 | H109: 4 | I109: 8 | J109: 8 | K109: =SUM(F109:J109) -> 32 | L109: =K109/4 -> 8
C110: 1165334511 | D110: RIVERSIDE CHECKERS | E110: =(F110+G110+H110+J110)*112.7+(I110*119.6) -> 2732.4 | F110: 6 | G110: 4 | H110: 4 | I110: 4 | J110: 6 | K110: =SUM(F110:J110) -> 24 | L110: =K110/4 -> 6
...

Sheet WEEKLY AMOUNTS
B3: DATE | C3: TYPE | D3: DAY | E3: TOTALS | F3: BTON PNP | G3: TUISBEDRYF | H3: HYPER NELS CHECK | I3: PLAZA SPAR | J3: GROVE SPAR | K3: R/MALL | L3: W/RIVER | M3: HAZYV SPAR | N3: HAZYV CHECK | O3: COUNTRY KING | P3: CAROLINA SPAR | Q3: ERMELO | R3: MERINO MALL | S3: MIDDELBURG | T3: SAVEWAYS | U3: KLIPFONTEIN | V3: STEILTES SPAR | W3: LYD CHECK | X3: LYD PNP | Y3: TOTALS | Z3: TYPE | AA3: DAY | AB3: DATE
B5: 45656 | C5: SALE | D5: MONDAY | E5: =SUM(F5:X5) -> 33392.8 | F5: 8600 | H5: 5041.6 | I5: 2400 | K5: 2732.4 | L5: 3661.6 | N5: 10957.2 | Y5: + | Z5: SALE | AA5: MONDAY | AB5: =B5 -> 45656
C6: RETURNS | E6: =SUM(F6:X6) -> 0 | Y6: =SUM(F6:X6) -> 0 | Z6: RETURNS
B7: 45657 | C7: SALE | D7: TUESDAY | E7: =SUM(F7:X7) -> 44915.5 | N7: 8576.7 | O7: 2400 | Q7: 8280 | R7: 6189.3 | S7: 6189.3 | T7: 6189.3 | U7: 7090.9 | Y7: =SUM(F7:X7) -> 44915.5 | Z7: SALE | AA7: TUESDAY | AB7: =B7 -> 45657
C8: RETURNS | E8: =SUM(F8:X8) -> 0 | Y8: =SUM(F8:X8) -> 0 | Z8: RETURNS
B9: 45658 | C9: SALE | D9: WEDNESDAY | E9: =SUM(F9:X9) -> 26962 | F9: 6400 | H9: 3661.6 | K9: 2732.4 | L9: 3210.8 | N9: 10957.2 | Y9: =SUM(F9:X9) -> 26962 | Z9: SALE | AA9: WEDNESDAY | AB9: =B9 -> 45658
C10: RETURNS | E10: =SUM(F10:X10) -> 0 | Y10: =SUM(F10:X10) -> 0 | Z10: RETURNS
B11: 45659 | C11: SALE | D11: THURSDAY | E11: =SUM(F11:X11) -> 0 | Y11: =SUM(F11:X11) -> 0 | Z11: SALE | AA11: THURSDAY | AB11: =B11 -> 45659
C12: RETURNS | E12: =SUM(F12:X12) -> 0 | Y12: =SUM(F12:X12) -> 0 | Z12: RETURNS
B13: 45660 | C13: SALE | D13: FRIDAY | E13: =SUM(F13:X13) -> 34781.6 | F13: 7500 | G13: 1200 | H13: 3661.6 | I13: 2400 | K13: 2281.6 | L13: 3210.8 | M13: 3000 | N13: 11527.6 | Y13: =SUM(F13:X13) -> 34781.6 | Z13: SALE | AA13: FRIDAY | AB13: =B13 -> 45660
C14: RETURNS | E14: =SUM(F14:X14) -> 0 | Y14: =SUM(F14:X14) -> 0 | Z14: RETURNS
B15: 45661 | C15: SALE | D15: SATURDAY | E15: =SUM(F15:X15) -> 14519.9 | N15: 14519.9 | Y15: =SUM(F15:X15) -> 14519.9 | Z15: SALE | AA15: SATURDAY | AB15: =B15 -> 45661
C16: RETURNS | E16: =SUM(F16:X16) -> 0 | Y16: =SUM(F16:X16) -> 0 | Z16: RETURNS
B17: 45662 | C17: SALE | D17: SUNDAY | E17: =SUM(F17:X17) -> 0 | Y17: =SUM(F17:X17) -> 0 | Z17: SALE | AA17: SUNDAY | AB17: =B17 -> 45662
C18: RETURNS | E18: =SUM(F18:X18) -> 0 | Y18: =SUM(F18:X18) -> 0 | Z18: RETURNS
B19: INV TOTALS | E19: =SUM(E11,E9,E7,E5,E13,E15,E17) -> 154571.8 | F19: =SUM(F5,F7,F9,F11,F13,F15,F17) -> 22500 | G19: =SUM(G5,G7,G9,G11,G13,G15,G17) -> 1200 | H19: =SUM(H5,H7,H9,H11,H13,H15,H17) -> 12364.8 | I19: =SUM(I5,I7,I9,I11,I13,I15,I17) -> 4800 | J19: =SUM(J5,J7,J9,J11,J13,J15,J17) -> 0 | K19: =SUM(K5,K7,K9,K11,K13,K15,K17) -> 7746.4 | L19: =SUM(L5,L7,L9,L11,L13,L15,L17) -> 10083.2 | M19: =SUM(M5,M7,M9,M11,M13,M15,M17) -> 3000 | ... Y19: =SUM(Y5,Y7,Y9,Y11,Y13,Y15,Y17) -> 121179 | AB19: INV TOTALS
B20: RETURNS TOTAL | E20: =SUM(E6,E8,E10,E12,E14,E16,E18) -> 0 | F20: =(F6+F8+F10+F12+F14+F16+F18) -> 0 | G20: =(G6+G8+G10+G12+G14+G16+G18) -> 0 | H20: =(H6+H8+H10+H12+H14+H16+H18) -> 0 | I20: =(I6+I8+I10+I12+I14+I16+I18) -> 0 | J20: =(J6+J8+J10+J12+J14+J16+J18) -> 0 | K20: =(K6+K8+K10+K12+K14+K16+K18) -> 0 | L20: =(L6+L8+L10+L12+L14+L16+L18) -> 0 | M20: =(M6+M8+M10+M12+M14+M16+M18) -> 0 | ... Y20: =(Y6+Y8+Y10+Y12+Y14+Y16+Y18) -> 0 | AB20: RETURNS TOTAL
B21: ACTUAL INCOME | E21: =E19-E20 -> 154571.8 | F21: =F19-F20 -> 22500 | G21: =G19-G20 -> 1200 | H21: =H19-H20 -> 12364.8 | I21: =I19-I20 -> 4800 | J21: =J19-J20 -> 0 | K21: =K19-K20 -> 7746.4 | L21: =L19-L20 -> 10083.2 | ... Y21: =Y19-Y20 -> 121179 | AB21: ACTUAL INCOME
B23: DATE | C23: TYPE | D23: DAY | E23: TOTALS | F23: BTON PNP | G23: TUISBEDRYF | H23: HYPER NELS CHECK | I23: PLAZA SPAR | J23: GROVE SPAR | K23: R/MALL | L23: W/RIVER | M23: HAZYV SPAR | N23: HAZYV CHECK | O23: COUNTRY KING | P23: CAROLINA SPAR | Q23: ERMELO | R23: MERINO MALL | S23: MIDDELBURG | T23: SAVEWAYS | U23: KLIPFONTEIN | V23: STEILTES SPAR | W23: LYD CHECK | X23: LYD PNP | Y23: TOTALS | Z23: TYPE | AA23: DAY | AB23: DATE
B25: 45663 | C25: SALE | D25: MONDAY | E25: =SUM(F25:X25) -> 29475.1 | F25: 6400 | H25: 4119.3 | I25: 2520 | K25: 2725.5 | L25: 3781.2 | N25: 9929.1 | Y25: + | Z25: SALE | AA25: MONDAY | AB25: =B25 -> 45663
C26: RETURNS | E26: =SUM(F26:X26) -> 0 | Y26: =SUM(F26:X26) -> 0 | Z26: RETURNS
B27: 45664 | C27: SALE | D27: TUESDAY | E27: =SUM(F27:X27) -> 28294.8 | O27: 1440 | Q27: 8280 | R27: 4816.2 | S27: 4816.2 | T27: 4816.2 | U27: 4126.2 | Y27: =SUM(F27:X27) -> 28294.8 | Z27: SALE | AA27: TUESDAY | AB27: =B27 -> 45664
C28: RETURNS | E28: =SUM(F28:X28) -> 0 | Y28: =SUM(F28:X28) -> 0 | Z28: RETURNS
B29: 45665 | C29: SALE | D29: WEDNESDAY | E29: =SUM(F29:X29) -> 24087 | F29: 4500 | G29: 1440 | H29: 4119.3 | K29: 2725.5 | L29: 3443.1 | N29: 7859.1 | Y29: =SUM(F29:X29) -> 24087 | Z29: SALE | AA29: WEDNESDAY | AB29: =B29 -> 45665
C30: RETURNS | E30: =SUM(F30:X30) -> 0 | Y30: =SUM(F30:X30) -> 0 | Z30: RETURNS
B31: 45666 | C31: SALE | D31: THURSDAY | E31: =SUM(F31:X31) -> 9075.4 | U31: 4126.2 | W31: 2654.2 | X31: 2295 | Y31: =SUM(F31:X31) -> 9075.4 | Z31: SALE | AA31: THURSDAY | AB31: =B31 -> 45666
C32: RETURNS | E32: =SUM(F32:X32) -> 0 | Y32: =SUM(F32:X32) -> 0 | Z32: RETURNS
B33: 45667 | C33: SALE | D33: FRIDAY | E33: =SUM(F33:X33) -> 37083.9 | F33: 5100 | H33: 5492.4 | J33: 4800 | K33: 3084.3 | L33: 3443.1 | M33: 4200 | N33: 10964.1 | Y33: =SUM(F33:X33) -> 37083.9 | Z33: SALE | AA33: FRIDAY | AB33: =B33 -> 45667
C34: RETURNS | E34: =SUM(F34:X34) -> 1200 | J34: =1200 -> 1200 | Y34: =SUM(F34:X34) -> 1200 | Z34: RETURNS
B35: 45668 | C35: SALE | D35: SATURDAY | E35: =SUM(F35:X35) -> 0 | Y35: =SUM(F35:X35) -> 0 | Z35: SALE | AA35: SATURDAY | AB35: =B35 -> 45668
C36: RETURNS | E36: =SUM(F36:X36) -> 0 | Y36: =SUM(F36:X36) -> 0 | Z36: RETURNS
B37: 45669 | C37: SALE | D37: SUNDAY | E37: =SUM(F37:X37) -> 0 | Y37: =SUM(F37:X37) -> 0 | Z37: SALE | AA37: SUNDAY | AB37: =B37 -> 45669
C38: RETURNS | E38: =SUM(F38:X38) -> 0 | Y38: =SUM(F38:X38) -> 0 | Z38: RETURNS
B39: INV TOTALS | E39: =SUM(E31,E29,E27,E25,E33,E35,E37) -> 128016.2 | F39: =SUM(F25,F27,F29,F31,F33,F35,F37) -> 16000 | G39: =SUM(G25,G27,G29,G31,G33,G35,G37) -> 1440 | H39: =SUM(H25,H27,H29,H31,H33,H35,H37) -> 13731 | I39: =SUM(I25,I27,I29,I31,I33,I35,I37) -> 2520 | J39: =SUM(J25,J27,J29,J31,J33,J35,J37) -> 4800 | K39: =SUM(K25,K27,K29,K31,K33,K35,K37) -> 8535.3 | L39: =SUM(L25,L27,L29,L31,L33,L35,L37) -> 10667.4 | M39: =SUM(M25,M27,M29,M31,M33,M35,M37) -> 4200 | ... Y39: =SUM(Y25,Y27,Y29,Y31,Y33,Y35,Y37) -> 98541.1 | AB39: INV TOTALS
B40: RETURNS TOTAL | E40: =SUM(E26,E28,E30,E32,E34,E36,E38) -> 1200 | F40: =(F26+F28+F30+F32+F34+F36+F38) -> 0 | G40: =(G26+G28+G30+G32+G34+G36+G38) -> 0 | H40: =(H26+H28+H30+H32+H34+H36+H38) -> 0 | I40: =(I26+I28+I30+I32+I34+I36+I38) -> 0 | J40: =(J26+J28+J30+J32+J34+J36+J38) -> 1200 | K40: =(K26+K28+K30+K32+K34+K36+K38) -> 0 | L40: =(L26+L28+L30+L32+L34+L36+L38) -> 0 | M40: =(M26+M28+M30+M32+M34+M36+M38) -> 0 | ... Y40: =(Y26+Y28+Y30+Y32+Y34+Y36+Y38) -> 1200 | AB40: RETURNS TOTAL
B41: ACTUAL INCOME | E41: =E39-E40 -> 126816.2 | F41: =F39-F40 -> 16000 | G41: =G39-G40 -> 1440 | H41: =H39-H40 -> 13731 | I41: =I39-I40 -> 2520 | J41: =J39-J40 -> 3600 | K41: =K39-K40 -> 8535.3 | L41: =L39-L40 -> 10667.4 | ... Y41: =Y39-Y40 -> 97341.1 | AB41: ACTUAL INCOME
B43: DATE | C43: TYPE | D43: DAY | E43: TOTALS | F43: BTON PNP | G43: TUISBEDRYF | H43: HYPER NELS CHECK | I43: PLAZA SPAR | J43: GROVE SPAR | K43: R/MALL | L43: W/RIVER | M43: HAZYV SPAR | N43: HAZYV CHECK | O43: COUNTRY KING | P43: CAROLINA SPAR | Q43: ERMELO | R43: MERINO MALL | S43: MIDDELBURG | T43: SAVEWAYS | U43: KLIPFONTEIN | V43: STEILTES SPAR | W43: LYD CHECK | X43: LYD PNP | Y43: TOTALS | Z43: TYPE | AA43: DAY | AB43: DATE
B45: 45670 | C45: SALE | D45: MONDAY | E45: =SUM(F45:X45) -> 26805.8 | F45: 4700 | G45: 1200 | H45: 4119.3 | I45: 2400 | K45: 3084.3 | L45: 3781.2 | N45: 7521 | Y45: + | Z45: SALE | AA45: MONDAY | AB45: =B45 -> 45670
C46: RETURNS | E46: =SUM(F46:X46) -> 0 | Y46: =SUM(F46:X46) -> 0 | Z46: RETURNS
B47: 45671 | C47: SALE | D47: TUESDAY | E47: =SUM(F47:X47) -> 27019.8 | O47: 1200 | Q47: 7245 | R47: 4816.2 | S47: 4816.2 | T47: 4816.2 | U47: 4126.2 | Y47: =SUM(F47:X47) -> 27019.8 | Z47: SALE | AA47: TUESDAY | AB47: =B47 -> 45671
C48: RETURNS | E48: =SUM(F48:X48) -> 0 | Y48: =SUM(F48:X48) -> 0 | Z48: RETURNS
B49: 45672 | C49: SALE | D49: WEDNESDAY | E49: =SUM(F49:X49) -> 23408.9 | F49: 5600 | H49: 4119.3 | K49: 2725.5 | L49: 3443.1 | N49: 7521 | Y49: =SUM(F49:X49) -> 23408.9 | Z49: SALE | AA49: WEDNESDAY | AB49: =B49 -> 45672
C50: RETURNS | E50: =SUM(F50:X50) -> 0 | Y50: =SUM(F50:X50) -> 0 | Z50: RETURNS
B51: 45673 | C51: SALE | D51: THURSDAY | E51: =SUM(F51:X51) -> 0 | Y51: =SUM(F51:X51) -> 0 | Z51: SALE | AA51: THURSDAY | AB51: =B51 -> 45673
C52: RETURNS | E52: =SUM(F52:X52) -> 0 | Y52: =SUM(F52:X52) -> 0 | Z52: RETURNS
B53: 45674 | C53: SALE | D53: FRIDAY | E53: =SUM(F53:X53) -> 31505.8 | F53: 5200 | G53: 1200 | H53: 3443.1 | J53: 2400 | K53: 2725.5 | L53: 3443.1 | M53: 4200 | N53: 8894.1 | Y53: =SUM(F53:X53) -> 31505.8 | Z53: SALE | AA53: FRIDAY | AB53: =B53 -> 45674
C54: RETURNS | E54: =SUM(F54:X54) -> 120 | J54: 120 | Y54: =SUM(F54:X54) -> 120 | Z54: RETURNS
B55: 45675 | C55: SALE | D55: SATURDAY | E55: =SUM(F55:X55) -> 0 | Y55: =SUM(F55:X55) -> 0 | Z55: SALE | AA55: SATURDAY | AB55: =B55 -> 45675
C56: RETURNS | E56: =SUM(F56:X56) -> 0 | Y56: =SUM(F56:X56) -> 0 | Z56: RETURNS
B57: 45676 | C57: SALE | D57: SUNDAY | E57: =SUM(F57:X57) -> 12098 | N57: 12098 | Y57: =SUM(F57:X57) -> 12098 | Z57: SALE | AA57: SUNDAY | AB57: =B57 -> 45676
C58: RETURNS | E58: =SUM(F58:X58) -> 0 | Y58: =SUM(F58:X58) -> 0 | Z58: RETURNS
B59: INV TOTALS | E59: =SUM(E51,E49,E47,E45,E53,E55,E57) -> 120838.3 | F59: =SUM(F45,F47,F49,F51,F53,F55,F57) -> 15500 | G59: =SUM(G45,G47,G49,G51,G53,G55,G57) -> 2400 | H59: =SUM(H45,H47,H49,H51,H53,H55,H57) -> 11681.7 | I59: =SUM(I45,I47,I49,I51,I53,I55,I57) -> 2400 | J59: =SUM(J45,J47,J49,J51,J53,J55,J57) -> 2400 | K59: =SUM(K45,K47,K49,K51,K53,K55,K57) -> 8535.3 | L59: =SUM(L45,L47,L49,L51,L53,L55,L57) -> 10667.4 | M59: =SUM(M45,M47,M49,M51,M53,M55,M57) -> 4200 | ... Y59: =SUM(Y45,Y47,Y49,Y51,Y53,Y55,Y57) -> 94032.5 | AB59: INV TOTALS
B60: RETURNS TOTAL | E60: =SUM(E46,E48,E50,E52,E54,E56,E58) -> 120 | F60: =(F46+F48+F50+F52+F54+F56+F58) -> 0 | G60: =(G46+G48+G50+G52+G54+G56+G58) -> 0 | H60: =(H46+H48+H50+H52+H54+H56+H58) -> 0 | I60: =(I46+I48+I50+I52+I54+I56+I58) -> 0 | J60: =(J46+J48+J50+J52+J54+J56+J58) -> 120 | K60: =(K46+K48+K50+K52+K54+K56+K58) -> 0 | L60: =(L46+L48+L50+L52+L54+L56+L58) -> 0 | M60: =(M46+M48+M50+M52+M54+M56+M58) -> 0 | ... Y60: =(Y46+Y48+Y50+Y52+Y54+Y56+Y58) -> 120 | AB60: RETURNS TOTAL
B61: ACTUAL INCOME | E61: =E59-E60 -> 120718.3 | F61: =F59-F60 -> 15500 | G61: =G59-G60 -> 2400 | H61: =H59-H60 -> 11681.7 | I61: =I59-I60 -> 2400 | J61: =J59-J60 -> 2280 | K61: =K59-K60 -> 8535.3 | L61: =L59-L60 -> 10667.4 | ... Y61: =Y59-Y60 -> 93912.5 | AB61: ACTUAL INCOME
B63: DATE | C63: TYPE | D63: DAY | E63: TOTALS | F63: BTON PNP | G63: TUISBEDRYF | H63: HYPER NELS CHECK | I63: PLAZA SPAR | J63: GROVE SPAR | K63: R/MALL | L63: W/RIVER | M63: HAZYV SPAR | N63: HAZYV CHECK | O63: COUNTRY KING | P63: CAROLINA SPAR | Q63: ERMELO | R63: MERINO MALL | S63: MIDDELBURG | T63: SAVEWAYS | U63: KLIPFONTEIN | V63: STEILTES SPAR | W63: LYD CHECK | X63: LYD PNP | Y63: TOTALS | Z63: TYPE | AA63: DAY | AB63: DATE
B65: 45677 | C65: SALE | D65: MONDAY | E65: =SUM(F65:X65) -> 25494.6 | F65: 5100 | G65: 1200 | H65: 3443.1 | I65: 2400 | K65: 2725.5 | L65: 3443.1 | N65: 7182.9 | Y65: + | Z65: SALE | AA65: MONDAY | AB65: =B65 -> 45677
C66: RETURNS | E66: =SUM(F66:X66) -> 240 | I66: 240 | Y66: =SUM(F66:X66) -> 240 | Z66: RETURNS
B67: 45678 | C67: SALE | D67: TUESDAY | E67: =SUM(F67:X67) -> 30026.7 | O67: 1440 | Q67: 8618.1 | R67: 5280.8 | S67: 5280.8 | T67: 5280.8 | U67: 4126.2 | Y67: =SUM(F67:X67) -> 30026.7 | Z67: SALE | AA67: TUESDAY | AB67: =B67 -> 45678
C68: RETURNS | E68: =SUM(F68:X68) -> 0 | Y68: =SUM(F68:X68) -> 0 | Z68: RETURNS
B69: 45679 | C69: SALE | D69: WEDNESDAY | E69: =SUM(F69:X69) -> 22870.8 | F69: 5400 | H69: 3443.1 | K69: 2725.5 | L69: 3443.1 | N69: 7859.1 | Y69: =SUM(F69:X69) -> 22870.8 | Z69: SALE | AA69: WEDNESDAY | AB69: =B69 -> 45679
C70: RETURNS | E70: =SUM(F70:X70) -> 0 | Y70: =SUM(F70:X70) -> 0 | Z70: RETURNS
B71: 45680 | C71: SALE | D71: THURSDAY | E71: =SUM(F71:X71) -> 5783.1 | W71: 3443.1 | X71: 2340 | Y71: =SUM(F71:X71) -> 5783.1 | Z71: SALE | AA71: THURSDAY | AB71: =B71 -> 45680
C72: RETURNS | E72: =SUM(F72:X72) -> 0 | Y72: =SUM(F72:X72) -> 0 | Z72: RETURNS
B73: 45681 | C73: SALE | D73: FRIDAY | E73: =SUM(F73:X73) -> 21896 | F73: 8000 | G73: 1200 | H73: 4816.2 | K73: 3422.4 | L73: 4457.4 | Y73: =SUM(F73:X73) -> 21896 | Z73: SALE | AA73: FRIDAY | AB73: =B73 -> 45681
C74: RETURNS | E74: =SUM(F74:X74) -> 0 | Y74: =SUM(F74:X74) -> 0 | Z74: RETURNS
B75: 45682 | C75: SALE | D75: SATURDAY | E75: =SUM(F75:X75) -> 17602.6 | M75: 5040 | N75: 12562.6 | Y75: =SUM(F75:X75) -> 17602.6 | Z75: SALE | AA75: SATURDAY | AB75: =B75 -> 45682
C76: RETURNS | E76: =SUM(F76:X76) -> 0 | Y76: =SUM(F76:X76) -> 0 | Z76: RETURNS
B77: 45683 | C77: SALE | D77: SUNDAY | E77: =SUM(F77:X77) -> 0 | Y77: =SUM(F77:X77) -> 0 | Z77: SALE | AA77: SUNDAY | AB77: =B77 -> 45683
C78: RETURNS | E78: =SUM(F78:X78) -> 0 | Y78: =SUM(F78:X78) -> 0 | Z78: RETURNS
B79: INV TOTALS | E79: =SUM(E71,E69,E67,E65,E73,E75,E77) -> 123673.8 | F79: =SUM(F65,F67,F69,F71,F73,F75,F77) -> 18500 | G79: =SUM(G65,G67,G69,G71,G73,G75,G77) -> 2400 | H79: =SUM(H65,H67,H69,H71,H73,H75,H77) -> 11702.4 | I79: =SUM(I65,I67,I69,I71,I73,I75,I77) -> 2400 | J79: =SUM(J65,J67,J69,J71,J73,J75,J77) -> 0 | K79: =SUM(K65,K67,K69,K71,K73,K75,K77) -> 8873.4 | L79: =SUM(L65,L67,L69,L71,L73,L75,L77) -> 11343.6 | M79: =SUM(M65,M67,M69,M71,M73,M75,M77) -> 5040 | ... Y79: =SUM(Y65,Y67,Y69,Y71,Y73,Y75,Y77) -> 98179.2 | AB79: INV TOTALS
B80: RETURNS TOTAL | E80: =SUM(E66,E68,E70,E72,E74,E76,E78) -> 240 | F80: =(F66+F68+F70+F72+F74+F76+F78) -> 0 | G80: =(G66+G68+G70+G72+G74+G76+G78) -> 0 | H80: =(H66+H68+H70+H72+H74+H76+H78) -> 0 | I80: =(I66+I68+I70+I72+I74+I76+I78) -> 240 | J80: =(J66+J68+J70+J72+J74+J76+J78) -> 0 | K80: =(K66+K68+K70+K72+K74+K76+K78) -> 0 | L80: =(L66+L68+L70+L72+L74+L76+L78) -> 0 | M80: =(M66+M68+M70+M72+M74+M76+M78) -> 0 | ... Y80: =(Y66+Y68+Y70+Y72+Y74+Y76+Y78) -> 240 | AB80: RETURNS TOTAL
B81: ACTUAL INCOME | E81: =E79-E80 -> 123433.8 | F81: =F79-F80 -> 18500 | G81: =G79-G80 -> 2400 | H81: =H79-H80 -> 11702.4 | I81: =I79-I80 -> 2160 | J81: =J79-J80 -> 0 | K81: =K79-K80 -> 8873.4 | L81: =L79-L80 -> 11343.6 | ... Y81: =Y79-Y80 -> 97939.2 | AB81: ACTUAL INCOME
B83: DATE | C83: TYPE | D83: DAY | E83: TOTALS | F83: BTON PNP | G83: TUISBEDRYF | H83: HYPER NELS CHECK | I83: PLAZA SPAR | J83: GROVE SPAR | K83: R/MALL | L83: W/RIVER | M83: HAZYV SPAR | N83: HAZYV CHECK | O83: COUNTRY KING | P83: CAROLINA SPAR | Q83: ERMELO | R83: MERINO MALL | S83: MIDDELBURG | T83: SAVEWAYS | U83: KLIPFONTEIN | V83: STEILTES SPAR | W83: LYD CHECK | X83: LYD PNP | Y83: TOTALS | Z83: TYPE | AA83: DAY | AB83: DATE
B85: 45684 | C85: SALE | D85: MONDAY | E85: =SUM(F85:X85) -> 30755.1 | F85: 4200 | H85: 4457.4 | I85: 2400 | J85: 3600 | K85: 2387.4 | L85: 3781.2 | N85: 9929.1 | Y85: + | Z85: SALE | AA85: MONDAY | AB85: =B85 -> 45684
C86: RETURNS | E86: =SUM(F86:X86) -> 840 | I86: 120 | J86: =6*120 -> 720 | Y86: =SUM(F86:X86) -> 840 | Z86: RETURNS
B87: 45685 | C87: SALE | D87: TUESDAY | E87: =SUM(F87:X87) -> 32664.6 | Q87: 8618.1 | R87: 6189.3 | S87: 6189.3 | T87: 6189.3 | U87: 5478.6 | Y87: =SUM(F87:X87) -> 32664.6 | Z87: SALE | AA87: TUESDAY | AB87: =B87 -> 45685
C88: RETURNS | E88: =SUM(F88:X88) -> 0 | Y88: =SUM(F88:X88) -> 0 | Z88: RETURNS
B89: 45686 | C89: SALE | D89: WEDNESDAY | E89: =SUM(F89:X89) -> 24271.6 | F89: 5600 | G89: 1440 | H89: 3210.8 | K89: 2387.4 | L89: 3210.8 | N89: 8422.6 | Y89: =SUM(F89:X89) -> 24271.6 | Z89: SALE | AA89: WEDNESDAY | AB89: =B89 -> 45686
C90: RETURNS | E90: =SUM(F90:X90) -> 0 | Y90: =SUM(F90:X90) -> 0 | Z90: RETURNS
B91: 45687 | C91: SALE | D91: THURSDAY | E91: =SUM(F91:X91) -> 6046.2 | W91: 2746.2 | X91: 3300 | Y91: =SUM(F91:X91) -> 6046.2 | Z91: SALE | AA91: THURSDAY | AB91: =B91 -> 45687
C92: RETURNS | E92: =SUM(F92:X92) -> 0 | Y92: =SUM(F92:X92) -> 0 | Z92: RETURNS
B93: 45688 | C93: SALE | D93: FRIDAY | E93: =SUM(F93:X93) -> 36233.2 | F93: 5800 | H93: 5041.6 | I93: 2400 | K93: 2612.8 | L93: 3661.6 | M93: 5760 | N93: 10957.2 | Y93: =SUM(F93:X93) -> 36233.2 | Z93: SALE | AA93: FRIDAY | AB93: =B93 -> 45688
C94: RETURNS | E94: =SUM(F94:X94) -> 720 | I94: =6*120 -> 720 | Y94: =SUM(F94:X94) -> 720 | Z94: RETURNS
B95: 45689 | C95: SALE | D95: SATURDAY | E95: =SUM(F95:X95) -> 21137 | F95: 5210 | N95: 9880.8 | W95: 2746.2 | X95: 3300 | Y95: =SUM(F95:X95) -> 21137 | Z95: SALE | AA95: SATURDAY | AB95: =B95 -> 45689
C96: RETURNS | E96: =SUM(F96:X96) -> 0 | Y96: =SUM(F96:X96) -> 0 | Z96: RETURNS
B97: 45690 | C97: SALE | D97: SUNDAY | E97: =SUM(F97:X97) -> 0 | Y97: =SUM(F97:X97) -> 0 | Z97: SALE | AA97: SUNDAY | AB97: =B97 -> 45690
C98: RETURNS | E98: =SUM(F98:X98) -> 0 | Y98: =SUM(F98:X98) -> 0 | Z98: RETURNS
B99: INV TOTALS | E99: =SUM(E91,E89,E87,E85,E93,E95,E97) -> 151107.7 | F99: =SUM(F85,F87,F89,F91,F93,F95,F97) -> 20810 | G99: =SUM(G85,G87,G89,G91,G93,G95,G97) -> 1440 | H99: =SUM(H85,H87,H89,H91,H93,H95,H97) -> 12709.8 | I99: =SUM(I85,I87,I89,I91,I93,I95,I97) -> 4800 | J99: =SUM(J85,J87,J89,J91,J93,J95,J97) -> 3600 | K99: =SUM(K85,K87,K89,K91,K93,K95,K97) -> 7387.6 | L99: =SUM(L85,L87,L89,L91,L93,L95,L97) -> 10653.6 | M99: =SUM(M85,M87,M89,M91,M93,M95,M97) -> 5760 | ... Y99: =SUM(Y85,Y87,Y89,Y91,Y93,Y95,Y97) -> 120352.6 | AB99: INV TOTALS
B100: RETURNS TOTAL | E100: =SUM(E86,E88,E90,E92,E94,E96,E98) -> 1560 | F100: =(F86+F88+F90+F92+F94+F96+F98) -> 0 | G100: =(G86+G88+G90+G92+G94+G96+G98) -> 0 | H100: =(H86+H88+H90+H92+H94+H96+H98) -> 0 | I100: =(I86+I88+I90+I92+I94+I96+I98) -> 840 | J100: =(J86+J88+J90+J92+J94+J96+J98) -> 720 | K100: =(K86+K88+K90+K92+K94+K96+K98) -> 0 | L100: =(L86+L88+L90+L92+L94+L96+L98) -> 0 | M100: =(M86+M88+M90+M92+M94+M96+M98) -> 0 | ... Y100: =(Y86+Y88+Y90+Y92+Y94+Y96+Y98) -> 1560 | AB100: RETURNS TOTAL
B101: ACTUAL INCOME | E101: =E99-E100 -> 149547.7 | F101: =F99-F100 -> 20810 | G101: =G99-G100 -> 1440 | H101: =H99-H100 -> 12709.8 | I101: =I99-I100 -> 3960 | J101: =J99-J100 -> 2880 | K101: =K99-K100 -> 7387.6 | L101: =L99-L100 -> 10653.6 | ... Y101: =Y99-Y100 -> 118792.6 | AB101: ACTUAL INCOME
B103: DATE | C103: TYPE | D103: DAY | E103: TOTALS | F103: BTON PNP | G103: TUISBEDRYF | H103: HYPER NELS CHECK | I103: PLAZA SPAR | J103: GROVE SPAR | K103: R/MALL | L103: W/RIVER | M103: HAZYV SPAR | N103: HAZYV CHECK | O103: COUNTRY KING | P103: CAROLINA SPAR | Q103: ERMELO | R103: MERINO MALL | S103: MIDDELBURG | T103: SAVEWAYS | U103: KLIPFONTEIN | V103: STEILTES SPAR | W103: LYD CHECK | X103: LYD PNP | Y103: TOTALS | Z103: TYPE | AA103: DAY | AB103: DATE
B105: 45691 | C105: SALE | D105: MONDAY | E105: =SUM(F105:X105) -> 28372.8 | F105: 4900 | G105: 1440 | H105: 4112.4 | I105: 2400 | K105: 2732.4 | L105: 3661.6 | N105: 9126.4 | Y105: + | Z105: SALE | AA105: MONDAY | AB105: =B105 -> 45691
C106: RETURNS | E106: =SUM(F106:X106) -> 2002.2 | F106: 700 | I106: 120 | K106: 345 | L106: 478.4 | N106: 358.8 | Y106: =SUM(F106:X106) -> 2002.2 | Z106: RETURNS
B107: 45692 | C107: SALE | D107: TUESDAY | E107: =SUM(F107:X107) -> 33262.6 | Q107: 8730.8 | R107: 6196.2 | S107: 6421.6 | T107: 6421.6 | U107: 5492.4 | Y107: =SUM(F107:X107) -> 33262.6 | Z107: SALE | AA107: TUESDAY | AB107: =B107 -> 45692
C108: RETURNS | E108: =SUM(F108:X108) -> 450.8 | U108: 450.8 | Y108: =SUM(F108:X108) -> 450.8 | Z108: RETURNS
B109: 45693 | C109: SALE | D109: WEDNESDAY | E109: =SUM(F109:X109) -> 29432.8 | F109: 6800 | H109: 4112.4 | J109: 3000 | K109: 2732.4 | L109: 3210.8 | N109: 9577.2 | Y109: =SUM(F109:X109) -> 29432.8 | Z109: SALE | AA109: WEDNESDAY | AB109: =B109 -> 45693
C110: RETURNS | E110: =SUM(F110:X110) -> 2771.6 | F110: 700 | J110: 480 | N110: 1591.6 | Y110: =SUM(F110:X110) -> 2771.6 | Z110: RETURNS
B111: 45694 | C111: SALE | D111: THURSDAY | E111: =SUM(F111:X111) -> 7510.8 | F111: 4300 | W111: 3210.8 | Y111: =SUM(F111:X111) -> 7510.8 | Z111: SALE | AA111: THURSDAY | AB111: =B111 -> 45694
C112: RETURNS | E112: =SUM(F112:X112) -> 0 | Y112: =SUM(F112:X112) -> 0 | Z112: RETURNS
B113: 45695 | C113: SALE | D113: FRIDAY | E113: =SUM(F113:X113) -> 30825.2 | F113: 5100 | G113: 1200 | H113: 4563.2 | I113: 2160 | K113: 2732.4 | L113: 3661.6 | N113: 11408 | Y113: =SUM(F113:X113) -> 30825.2 | Z113: SALE | AA113: FRIDAY | AB113: =B113 -> 45695
...

Sheet PRODUCTION BATCHES
D1: DAY | E1: SUNDAY | J1: DATE | K1: 45655
B2: DATE | C2: BATCHES | D2: TIME | F2: CHOCOLATE | G2: VANILLA | H2: COFFEE | I2: CARROT | J2: DM | K2: BOX | L2: CUPCAKES | M2: FLOPS | N2: BAKERS | O2: NOTES
B3: =K1 -> 45655 | D3: IN | E3: OUT | F3: 15 | G3: 9 | H3: 4 | I3: 5 | J3: 9
C4: 1 | D4: 0.33680556 | E4: 0.35763889 | G4: 28
C5: 2 | D5: 0.36458333 | E5: 0.38541667 | G5: 28
C6: 3 | D6: 0.38541667 | E6: 0.40625 | G6: 28
C7: 4 | D7: 0.40972222 | E7: 0.43055556 | G7: 14
C8: 5 | D8: 0.41319444 | E8: 0.43402778 | F8: 14
C9: 6 | D9: 0.47916667 | E9: 0.5 | G9: 28
C10: 7 | D10: 0.5 | E10: 0.52083333 | H10: 28
C11: 8 | D11: 0.53125 | E11: 0.55208333 | H11: 28
C12: 9 | D12: 0.55555556 | E12: 0.57638889 | F12: 28
C13: 10 | D13: 0.58680556 | E13: 0.60763889 | I13: 44
C14: 11 | D14: 0.62152778 | E14: 0.64236111 | F14: 28
C15: 12 | D15: 0.65277778 | E15: 0.67361111 | I15: 44
C16: 13 | D16: 0.6875 | E16: 0.70833333 | F16: 28
C17: 14 | D17: 0.71180556 | E17: 0.73263889 | J17: 36
C18: 15 | D18: 0.73958333 | E18: 0.76041667 | F18: 28
C19: 16 | D19: 0.77083333 | E19: 0.79166667 | J19: 36
C20: 17 | D20: 0.79861111 | E20: 0.81944444 | F20: 28
C21: 18 | D21: 0.81944444 | E21: 0.84027778 | J21: 36
C22: 19 | D22: 0.85069444 | E22: 0.87152778 | F22: 28
C23: 20 | D23: 0.87847222 | E23: 0.89930556 | J23: 36
C24: 21 | D24: 0.90625 | E24: 0.92708333 | F24: 28
C25: 22 | D25: 0.92013889 | E25: 0.94097222 | J25: 18
C26: 23 | D26: 0.94444444 | E26: 0.96527778 | I26: 22
C27: 24
C28: 25
C29: 26
C30: 27
C31: 28
C32: 29
C33: 30
C34: 31
C35: 32
C36: 33
C37: 34
C38: 35
... C40: 37
C41: TOTALS | F41: =(F4+F5+F6+F7+F8+F9+F25+F12+F13+F10+F11+F14+F15+F16+F17+F18+F19+F20+F21+F22+F23+F24+F26+F27+F29+F30+F31+F32+F33+F34+F35+F36+F37+F40)/2 -> 105 | G41: =(G4+G5+G6+G7+G8+G25+G9+G13+G12+G10+G11+G14+G15+G16+G17+G18+G19+G20+G21+G22+G23+G24+G26+G27+G29+G30+G31+G32+G33+G34+G35+G36)/2 -> 63 | H41: =(H4+H5+H6+H7+H8+H9+H25+H28+H12+H13+H10+H11+H14+H15+H16+H17+H18+H19+H20+H21+H22+H23+H24+H26+H27+H29+H30+H31+H32+H33+H34+H35+H36+H37+H40)/2 -> 28 | I41: =(I4+I5+I6+I7+I8+I38+I39+I9+I25+I12+I28+I13+I10+I11+I14+I15+I16+I17+I18+I19+I20+I21+I22+I23+I24+I26+I27+I29+I30+I31+I32+I33+I34+I35+I36+I37+I40)/2 -> 55 | J41: =(J4+J5+J6+J7+J8+J9+J13+J10+J12+J11+J28+J14+J15+J16+J17+J18+J19+J20+J21+J22+J23+J24+J25+J26+J27+J29+J30+J31+J32+J33+J34+J35+J36)/2 -> 81 | K41: =(K4+K5+K6+K7+K8+K9+K13+K10+K11+K14+K15+K16+K17+K18+K19+K20+K21+K22+K23+K24+K26+K27+K29+K30+K31+K32+K33+K34+K35+K36+K25) -> 0 | L41: =SUM(L4:L40) -> 0 | M41: =(M4+M5+M6+M7+M8+M9+M13+M12+M10+M11+M14+M15+M16+M17+M18+M19+M20+M21+M22+M23+M24+M26+M27+M29+M30+M31+M32+M33+M34+M35+M36)/2 -> 0
C42: GRAND TOTAL | E42: =SUM(F41:J41) -> 332
D44: DAY | E44: MONDAY | J44: DATE | K44: 45656
B45: DATE | C45: BATCHES | D45: TIME | F45: CHOCOLATE | G45: VANILLA | H45: COFFEE | I45: CARROT | J45: DM | K45: BOX | L45: CUPCAKES | M45: FLOPS | N45: BAKERS | O45: NOTES
B46: =K44 -> 45656 | D46: IN | E46: OUT | F46: 9 | G46: 11 | H46: 0 | I46: 6 | J46: 9
C47: 1 | D47: 0.43402778 | E47: 0.45486111 | G47: 14
C48: 2 | D48: 0.44444444 | E48: 0.46527778 | F48: 14
C49: 3 | D49: 0.46527778 | E49: 0.48611111 | J49: 18
C50: 4 | D50: 0.49652778 | E50: 0.51736111 | G50: 28
C51: 5 | D51: 0.52083333 | E51: 0.54166667 | G51: 28
C52: 6 | D52: 0.54513889 | E52: 0.56597222 | G52: 28
C53: 7 | D53: 0.56944444 | E53: 0.59027778 | G53: 28
C54: 8 | D54: 0.59722222 | E54: 0.61805556 | G54: 28
C55: 9 | D55: 0.62152778 | E55: 0.64236111 | I55: 44
C56: 10 | D56: 0.67708333 | E56: 0.69791667 | F56: 28
C57: 11 | D57: 0.70486111 | E57: 0.72569444 | I57: 44
C58: 12 | D58: 0.72916667 | E58: 0.75 | F58: 28
C59: 13 | D59: 0.76041667 | E59: 0.78125 | I59: 44
C60: 14 | D60: 0.78819444 | E60: 0.80902778 | F60: 28
C61: 15 | D61: 0.81944444 | E61: 0.84027778 | J61: 36 | M61: 2
C62: 16 | D62: 0.84722222 | E62: 0.86805556 | F62: 24 | K62: 1
C63: 17 | D63: 0.87152778 | E63: 0.89236111 | J63: 36
C64: 18 | D64: 0.90277778 | E64: 0.92361111 | J64: 36
C65: 19 | D65: 0.95486111 | E65: 0.97569444 | J65: 26
C66: 20
C67: 21
C68: 22
C69: 23
C70: 24
C71: 25
C72: 26
C73: 27
C74: 28
C75: 29
C76: 30
C77: 31
... C83: 37
C84: TOTALS | F84: =(F47+F48+F49+F50+F51+F52+F68+F55+F56+F53+F54+F57+F58+F59+F60+F61+F62+F63+F64+F65+F66+F67+F69+F70+F72+F73+F74+F75+F76+F77+F78+F79+F80+F83)/2 -> 61 | G84: =(G47+G48+G49+G50+G51+G68+G52+G56+G55+G53+G54+G57+G58+G59+G60+G61+G62+G63+G64+G65+G66+G67+G69+G70+G72+G73+G74+G75+G76+G77+G78+G79)/2 -> 77 | H84: =(H47+H48+H49+H50+H51+H52+H68+H71+H55+H56+H53+H54+H57+H58+H59+H60+H61+H62+H63+H64+H65+H66+H67+H69+H70+H72+H73+H74+H75+H76+H77+H78+H79+H80+H83)/2 -> 0 | I84: =(I47+I48+I49+I50+I51+I81+I82+I52+I68+I55+I71+I56+I53+I54+I57+I58+I59+I60+I61+I62+I63+I64+I65+I66+I67+I69+I70+I72+I73+I74+I75+I76+I77+I78+I79+I80+I83)/2 -> 66 | J84: =(J47+J48+J49+J50+J51+J52+J56+J53+J55+J54+J71+J57+J58+J59+J60+J61+J62+J63+J64+J65+J66+J67+J68+J69+J70+J72+J73+J74+J75+J76+J77+J78+J79)/2 -> 76 | K84: =(K47+K48+K49+K50+K51+K52+K56+K53+K54+K57+K58+K59+K60+K61+K62+K63+K64+K65+K66+K67+K69+K70+K72+K73+K74+K75+K76+K77+K78+K79+K68) -> 1 | L84: =SUM(L47:L83) -> 0 | M84: =(M47+M48+M49+M50+M51+M52+M56+M55+M53+M54+M57+M58+M59+M60+M61+M62+M63+M64+M65+M66+M67+M69+M70+M72+M73+M74+M75+M76+M77+M78+M79)/2 -> 1
C85: GRAND TOTAL | E85: =SUM(F84:J84) -> 280
D87: DAY | E87: TUESDAY | J87: DATE | K87: 45657
B88: DATE | C88: BATCHES | D88: TIME | F88: CHOCOLATE | G88: VANILLA | H88: COFFEE | I88: CARROT | J88: DM | K88: BOX | L88: CUPCAKES | M88: FLOPS | N88: BAKERS | O88: NOTES
B89: =K87 -> 45657 | D89: IN | E89: OUT | F89: 12 | G89: 7 | H89: 0 | I89: 5 | J89: 7
C90: 1 | D90: 0.31597222 | E90: 0.33680556 | G90: 28
C91: 2 | D91: 0.33680556 | E91: 0.35763889 | G91: 28
C92: 3 | D92: 0.36458333 | E92: 0.38541667 | G92: 28
C93: 4 | D93: 0.38888889 | E93: 0.40972222 | F93: 28
C94: 5 | D94: 0.40972222 | E94: 0.43055556 | G94: 14
C95: 6 | D95: 0.42013889 | E95: 0.44097222 | I95: 22
C96: 7 | D96: 0.44791667 | E96: 0.46875 | J96: 18
C97: 8 | D97: 0.46875 | E97: 0.48958333 | F97: 28
C98: 9 | D98: 0.5 | E98: 0.52083333 | I98: 44
C99: 10 | D99: 0.53819444 | E99: 0.55902778 | F99: 28
C100: 11 | D100: 0.56944444 | E100: 0.59027778 | I100: 44
C101: 12 | D101: 0.60069444 | E101: 0.62152778 | F101: 24
C102: 13 | D102: 0.62847222 | E102: 0.64930556 | J102: 36
C103: 14 | D103: 0.65625 | E103: 0.67708333 | F103: 28
C104: 15 | D104: 0.6875 | E104: 0.70833333 | J104: 36
C105: 16 | D105: 0.71527778 | E105: 0.73611111 | F105: 28
C106: 17 | D106: 0.73611111 | E106: 0.75694444 | J106: 36
C107: 18
C108: 19
...

Sheet PETTYCASH
B2: PAID TO: /RECEIVED FROM: | C2: AMOUNT IN | D2: AMOUNT OUT CASH | E2: NOTES | F2: PHYSICAL CASH BREAKDOWN
A3: 45658 | B3: BBF | C3: 5037.1 | E3: BBF | F3: PHYSICAL CASH BEGINNING OF DAY
B4: JABU | D4: 1100 | E4: DIESEL
F5: 200 | G5: 2800
F6: 100 | G6: 2100
F7: 50 | G7: 100
F8: R20 | G8: 0
F9: R10 | G9: 20
F10: COINS | G10: 17.1
F11: CARD
F12: =SUM(G5:G10) -> 5037.1
F15: PHYSICAL CASH END OF DAY
F17: 200 | G17: 1800
F18: 100 | G18: 2000
F19: 50 | G19: 100
F20: R20 | G20: 0
F21: R10 | G21: 20
F22: COINS | G22: 17.1
F23: CARD
F24: =SUM(G17:G22) -> 3937.1
A25: TOTALS | C25: =SUM(C3:C24) -> 5037.1 | D25: =SUM(D3:D24) -> 1100 | E25: =C25-D25 -> 3937.1
B27: PAID TO: /RECEIVED FROM: | C27: AMOUNT IN | D27: AMOUNT OUT CASH | E27: NOTES | F27: PHYSICAL CASH BREAKDOWN
A28: 45659 | B28: BBF | C28: =E25 -> 3937.1 | E28: BBF | F28: PHYSICAL CASH BEGINNING OF DAY
B29: JABU | D29: 300 | E29: DIESEL
B30: PNP | D30: 132 | E30: BAKING POWDER | F30: 200 | G30: 1800
B31: CAKE SALES | C31: 150 | E31: SALES | F31: 100 | G31: 2000
B32: STAFF | D32: =200+74 -> 274 | E32: TAXI MONEY | F32: 50 | G32: 100
F33: R20 | G33: 0
F34: R10 | G34: 20
F35: COINS | G35: 17.1
F36: CARD
F37: =SUM(G30:G35) -> 3937.1
F40: PHYSICAL CASH END OF DAY
F42: 200 | G42: 1800
F43: 100 | G43: 1400
F44: 50 | G44: 150
F45: R20 | G45: 0
F46: R10 | G46: 20
F47: COINS | G47: 11.1
F48: CARD
F49: =SUM(G42:G47) -> 3381.1
A50: TOTALS | C50: =SUM(C28:C49) -> 4087.1 | D50: =SUM(D28:D49) -> 706 | E50: =C50-D50 -> 3381.1
B52: PAID TO: /RECEIVED FROM: | C52: AMOUNT IN | D52: AMOUNT OUT CASH | E52: NOTES | F52: PHYSICAL CASH BREAKDOWN
A53: 45660 | B53: BBF | C53: =E50 -> 3381.1 | E53: BBF | F53: PHYSICAL CASH BEGINNING OF DAY
B54: TUISBEDRYF | C54: 1200 | E54: INV 73
F55: 200 | G55: 1800
F56: 100 | G56: 1400
F57: 50 | G57: 150
F58: R20 | G58: 0
F59: R10 | G59: 20
F60: COINS | G60: 11.1
F61: CARD
F62: =SUM(G55:G60) -> 3381.1
F65: PHYSICAL CASH END OF DAY
F67: 200 | G67: 3000
F68: 100 | G68: 1400
F69: 50 | G69: 150
F70: R20 | G70: 0
F71: R10 | G71: 20
F72: COINS | G72: 11.1
F73: CARD
F74: =SUM(G67:G72) -> 4581.1
A75: TOTALS | C75: =SUM(C53:C74) -> 4581.1 | D75: =SUM(D53:D74) -> 0 | E75: =C75-D75 -> 4581.1
B77: PAID TO: /RECEIVED FROM: | C77: AMOUNT IN | D77: AMOUNT OUT CASH | E77: NOTES | F77: PHYSICAL CASH BREAKDOWN
A78: 45661 | B78: BBF | C78: =E75 -> 4581.1 | E78: BBF | F78: PHYSICAL CASH BEGINNING OF DAY
F80: 200 | G80: 3000
F81: 100 | G81: 1400
F82: 50 | G82: 150
F83: R20 | G83: 0
F84: R10 | G84: 20
F85: COINS | G85: 11.1
F86: CARD
F87: =SUM(G80:G85) -> 4581.1
F90: PHYSICAL CASH END OF DAY
F92: 200 | G92: 3000
F93: 100 | G93: 1400
F94: 50 | G94: 150
F95: R20 | G95: 0
F96: R10 | G96: 20
F97: COINS | G97: 11.1
F98: CARD
F99: =SUM(G92:G97) -> 4581.1
A100: TOTALS | C100: =SUM(C78:C99) -> 4581.1 | D100: =SUM(D78:D99) -> 0 | E100: =C100-D100 -> 4581.1
B102: PAID TO: /RECEIVED FROM: | C102: AMOUNT IN | D102: AMOUNT OUT CASH | E102: NOTES | F102: PHYSICAL CASH BREAKDOWN
A103: 45662 | B103: BBF | C103: =E100 -> 4581.1 | E103: BBF | F103: PHYSICAL CASH BEGINNING OF DAY
B104: WAS STORE | D104: 40 | E104: REFUSE BAGS
B105: LINDIE | D105: 30 | E105: LOAN | F105: 200 | G105: 3000
B106: CAKE SALES | C106: 150 | E106: SALES | F106: 100 | G106: 1400
F107: 50 | G107: 150
F108: R20 | G108: 0
F109: R10 | G109: 20
F110: COINS | G110: 11.1
F111: CARD
F112: =SUM(G105:G110) -> 4581.1
F115: PHYSICAL CASH END OF DAY
F117: 200 | G117: 3000
F118: 100 | G118: 1500
F119: 50 | G119: 150
F120: R20 | G120: 0
F121: R10 | G121: 0
...

Sheet WAGES PAID
B1: DATE | C1: DEPARTMENT | D1: EMPLOYEE | E1: DATES OF DAYS WORKED | F1: HOURS WORKED | G1: SHIFTS WORKED | H1: EXTRA BATCHES | I1: EXTRA BATCHES | J1: OWE | K1: RATES | L1: LOAN | M1: EXTRA BATCHES | N1: TOTAL
B2: 45660 | C2: HEAD BAKER | D2: BOY | E2: SAT - MON (21 DEC-23) THU - FRI(26 - 2 7 DEC) THU (2 JAN) | F2: =12+12+12+10+16+8 -> 70 | G2: 7 | K2: R260 PER DAY R30 PER EXTRA BATCH | M2: 16 | N2: =(G2*260)+(M2*30) -> 2300 | O2: BOY
C3: BAKER | D3: ZANDILE | F3: 72 | G3: 7 | K3: R225 PER DAY R30 PER EXTRA BATCH | M3: 16 | N3: =(G3*225)+(M3*30)-130 -> 1925 | O3: ZANDILE
C4: HEAD ICER | D4: NKOSI | F4: 78 | G4: 7 | K4: R250 PER DAY R30 PER EXTRA BATCH | M4: 16 | N4: =(G4*250)+(M4*30) -> 2230 | O4: NKOSI
C5: CLEANER | D5: XOLILE | F5: 61 | G5: 6 | K5: R225 PER DAY R30 PER EXTRA BATCH | M5: 16 | N5: =(G5*225)+(M5*30)-130 -> 1700 | O5: XOLILE
C6: ICER | D6: NATHI | F6: 72 | G6: 7 | K6: R225 PER DAY R30 PER EXTRA BATCH | M6: 16 | N6: =(G6*225)+(M6*30)-200-130 -> 1725 | O6: NATHI
C7: EXTRA HELPER | D7: NHLELELO | F7: 60 | G7: 6 | K7: R225 PER DAY | M7: 16 | N7: =(G7*225)+(M7*30) -> 1830 | O7: NHLELELO
N8: =SUM(N2:N7) -> 11710
C10: DEPARTMENT | D10: EMPLOYEE | E10: DAYS WORKED | F10: SALARY | G10: RATES | H10: EXTRA SHIFT | K10: LOAN | M10: EXTRA | N10: TOTAL
B11: 45660 | C11: ADMIN | D11: LINDIE | E11: MON - FRI (30 DEC - 3 JAN) | F11: 2400 | G11: R400 PER DAY | N11: =F11-K11 -> 2400 | O11: LINDIE
C12: CO DRIVER | D12: DONELL | F12: 200 | G12: R200 PER DAY | N12: 200 | O12: DONELL
C13: DRIVER | D13: JABU | F13: 2200 | G13: R380 PER DAY | N13: 2200 | O13: JABU
C14: HOUSEKEEPER | D14: CLARAH | F14: 1500 | G14: R300 PER DAY | N14: 1500 | O14: CLARAH
N15: =SUM(N11:N14) -> 6300
B17: DATE | C17: DEPARTMENT | D17: EMPLOYEE | E17: DATES OF DAYS WORKED | F17: HOURS WORKED | G17: SHIFTS WORKED | H17: EXTRA BATCHES | I17: EXTRA BATCHES | J17: OWE | K17: RATES | M17: EXTRA BATCHES | N17: TOTAL
B18: 45663 | C18: HEAD BAKER | D18: PEPPY | E18: TUE(26 DEC) SUN-TUE(29 - 31 DEC) THU(2 JAN) SUN(5 JAN) | F18: =11.5+17.5+17.5+14+12+13.5 -> 86 | G18: 7 | K18: R300 PER DAY R30 PER EXTRA BATCH | M18: =7+10 -> 17 | N18: =(G18*300)+(0*150)+(M18*30)-1010 -> 1600 | O18: PEPPY
C19: BAKER | D19: WELCOME | F19: 86 | G19: 7 | K19: R225 PER DAY R30 PER EXTRA BATCH | M19: 17 | N19: =(G19*225)+(0*112.5)+(M19*30) -> 2085 | O19: WELCOME
C20: HEAD ICER | D20: THANDIWE | E20: TUE(26 DEC) SUN-TUE(29 - 31 DEC) THU - FRI(2-3 JAN) SUN(5 JAN) | F20: 95 | G20: 8 | K20: R250 PER DAY R30 PER EXTRA BATCH | M20: 20 | N20: =(G20*250)+(0*125)+(M20*30) -> 2600 | O20: THANDIWE
C21: ICER | D21: PRIMROSE | F21: 95 | G21: 8 | K21: R225 PER DAY R30 PER EXTRA BATCH | M21: 20 | N21: =(G21*225)+(0*112.5)+(M21*30) -> 2400 | O21: PRIMROSE
C22: CLEANER | D22: PORTIA | E22: TUE(26 DEC) SUN-TUE(29 - 31 DEC) THU(2 JAN) SUN(5 JAN) | F22: 81 | G22: 7 | K22: R225 PER DAY R30 PER EXTRA BATCH | M22: 17 | N22: =(G22*225)+(0*112.5)+(M22*30)-130 -> 1955 | O22: PORTIA
C23: EXTRA HELPER | D23: CEBSILE | F23: 83 | G23: 7 | K23: R225 PER DAY | M23: =7+10 -> 17 | N23: =(G23*225)+(0*112.5)+(M23*30) -> 2085 | O23: CEBSILE
N24: =SUM(N18:N23) -> 12725
C26: DEPARTMENT | D26: EMPLOYEE | E26: DAYS WORKED | F26: SALARY | G26: RATES | H26: EXTRA SHIFT | K26: LOAN | M26: EXTRA | N26: TOTAL
B27: 45667 | C27: ADMIN | D27: LINDIE | E27: MON - FRI(6 - 10 JAN 2025) | F27: 2000 | G27: R400 PER DAY | N27: =F27-K27 -> 2000 | O27: LINDIE
C28: CO DRIVER | D28: DONELL | F28: 1000 | G28: R200 PER DAY | N28: 1000 | O28: DONELL
C29: DRIVER | D29: JABU | F29: 2200 | G29: R380 PER DAY | N29: 2200 | O29: JABU
C30: HOUSEKEEPER | D30: CLARAH | F30: 1500 | G30: R300 PER DAY | N30: 1500 | O30: CLARAH
N31: =SUM(N27:N30) -> 6700
C33: DEPARTMENT | D33: EMPLOYEE | E33: DATES OF DAYS WORKED | F33: HOURS WORKED | G33: SHIFTS WORKED | H33: EXTRA BATCHES | I33: EXTRA BATCHES | J33: OWE | K33: RATES | L33: LOAN | M33: EXTRA BATCHES | N33: TOTAL
B34: 45670 | C34: HEAD BAKER | D34: BOY | E34: FRI(3 JAN) MON - TUE(6 - 7 JAN) THU(9 JAN) SUN - MON(12 - 13 JAN) | F34: =6.5+10.5+11+10+12+12 -> 62 | G34: 6 | K34: R260 PER DAY R30 PER EXTRA BATCH | M34: =3+11+3+8 -> 25 | N34: =(G34*260)+(M34*30)-150 -> 2160 | O34: BOY
C35: BAKER | D35: ZANDILE | F35: 64 | G35: 6 | K35: R225 PER DAY R30 PER EXTRA BATCH | M35: 25 | N35: =(G35*225)+(M35*30)-200 -> 1900 | O35: ZANDILE
C36: HEAD ICER | D36: NKOSI | E36: MON - TUE(6 - 7 JAN) THU(9 JAN) SUN - MON(12 - 13 JAN) | F36: 60 | G36: 5 | K36: R250 PER DAY R30 PER EXTRA BATCH | M36: =11+3+3+5 -> 22 | N36: =(G36*250)+(M36*30) -> 1910 | O36: NKOSI
C37: CLEANER | D37: XOLILE | F37: 61 | G37: 5 | K37: R225 PER DAY R30 PER EXTRA BATCH | M37: 22 | N37: =(G37*225)+(M37*30) -> 1785 | O37: XOLILE
C38: ICER | D38: NATHI | F38: 61 | G38: 5 | K38: R225 PER DAY R30 PER EXTRA BATCH | M38: 22 | N38: =(G38*225)+(M38*30) -> 1785 | O38: NATHI
C39: EXTRA HELPER | D39: NHLELELO | F39: 60 | G39: 5 | K39: R225 PER DAY | M39: 22 | N39: =(G39*225)+(M39*30) -> 1785 | O39: NHLELELO
N40: =SUM(N34:N39) -> 11325
C42: DEPARTMENT | D42: EMPLOYEE | E42: DAYS WORKED | F42: SALARY | G42: RATES | H42: EXTRA SHIFT | K42: LOAN | M42: EXTRA | N42: TOTAL
B43: 45674 | C43: ADMIN | D43: LINDIE | E43: MON - FRI(13 - 17 JAN) SUN(19 JAN) | F43: 2400 | G43: R400 PER DAY | K43: =150+150+100 -> 400 | N43: =F43-K43 -> 2000 | O43: LINDIE
C44: CO DRIVER | D44: DONELL | E44: MON - FRI(13 - 17 JAN) | F44: 1000 | G44: R200 PER DAY | N44: 1000 | O44: DONELL
C45: DRIVER | D45: JABU | F45: 1900 | G45: R380 PER DAY | N45: 1900 | O45: JABU
C46: HOUSEKEEPER | D46: CLARAH | F46: 1500 | G46: R300 PER DAY | N46: 1500 | O46: CLARAH
N47: =SUM(N43:N46) -> 6400
B49: DATE | C49: DEPARTMENT | D49: EMPLOYEE | E49: DATES OF DAYS WORKED | F49: HOURS WORKED | G49: SHIFTS WORKED | H49: EXTRA BATCHES | I49: EXTRA BATCHES | J49: OWE | K49: RATES | M49: EXTRA BATCHES | N49: TOTAL
B50: 45677 | C50: HEAD BAKER | D50: PEPPY | E50: THU ( 9 JAN) TUE (14 JAN) THU (16 JAN) SAT - MON ( 18 - 20 JAN) | F50: 70.5 | G50: 7 | K50: R300 PER DAY R30 PER EXTRA BATCH | M50: =5 -> 5 | N50: =(G50*300)+(0*150)+(M50*30) -> 2250 | O50: PEPPY
C51: BAKER | D51: WELCOME | F51: 70.5 | G51: 7 | K51: R225 PER DAY R30 PER EXTRA BATCH | M51: 5 | N51: =(G51*225)+(0*112.5)+(M51*30) -> 1725 | O51: WELCOME
C52: HEAD ICER | D52: THANDIWE | F52: 69 | G52: 7 | K52: R250 PER DAY R30 PER EXTRA BATCH | M52: 5 | N52: =(G52*250)+(0*125)+(M52*30) -> 1900 | O52: THANDIWE
C53: ICER | D53: PRIMROSE | F53: 68 | G53: 7 | K53: R225 PER DAY R30 PER EXTRA BATCH | M53: 5 | N53: =(G53*225)+(0*112.5)+(M53*30) -> 1725 | O53: PRIMROSE
C54: CLEANER | D54: PORTIA | E54: TUE (14 JAN) THU (16 JAN) SUN - MON ( 19 - 20 JAN) | F54: 69 | G54: 5 | K54: R225 PER DAY R30 PER EXTRA BATCH | M54: 2 | N54: =(G54*225)+(0*112.5)+(M54*30) -> 1185 | O54: PORTIA
C55: EXTRA HELPER | D55: CEBSILE | F55: 69 | G55: 5 | K55: R225 PER DAY | M55: 2 | N55: =(G55*225)+(0*112.5)+(M55*30) -> 1185 | O55: CEBSILE
N56: =SUM(N50:N55) -> 9970
C58: DEPARTMENT | D58: EMPLOYEE | E58: DAYS WORKED | F58: SALARY | G58: RATES | H58: EXTRA SHIFT | K58: LOAN | M58: EXTRA | N58: TOTAL
B59: 45681 | C59: ADMIN | D59: LINDIE | E59: MON - FRI (20 - 24 JAN 2025) | F59: 2000 | G59: R400 PER DAY | K59: 810 | N59: =F59-K59 -> 1190 | O59: LINDIE
C60: CO DRIVER | D60: DONELL | E60: MON - SAT(20 - 25 JAN 2025) | F60: 1200 | G60: R200 PER DAY | N60: 1200 | O60: DONELL
C61: DRIVER | D61: JABU | F61: 2200 | G61: R380 PER DAY | N61: 2200 | O61: JABU
C62: HOUSEKEEPER | D62: CLARAH | F62: 1500 | G62: R300 PER DAY | N62: 1500 | O62: CLARAH
N63: =SUM(N59:N62) -> 6090
C65: DEPARTMENT | D65: EMPLOYEE | E65: DATES OF DAYS WORKED | F65: HOURS WORKED | G65: SHIFTS WORKED | H65: EXTRA BATCHES | I65: EXTRA BATCHES | J65: OWE | K65: RATES | L65: LOAN | M65: EXTRA BATCHES | N65: TOTAL
B66: 45684 | C66: HEAD BAKER | D66: BOY | E66: THU(16 JAN) TUE(21 JAN) THU(23 JAN) SUN-MON(26-27 JAN) | F66: =6+8+18+13+15 -> 60 | G66: 6 | K66: R260 PER DAY R30 PER EXTRA BATCH | M66: 23 | N66: =(G66*260)+(M66*30)-660 -> 1590 | O66: BOY
C67: BAKER | D67: ZANDILE | F67: 64 | G67: 6 | K67: R225 PER DAY R30 PER EXTRA BATCH | M67: 23 | N67: =(G67*225)+(M67*30)-280 -> 1760 | O67: ZANDILE
C68: HEAD ICER | D68: NKOSI | F68: 60 | G68: 6 | K68: R250 PER DAY R30 PER EXTRA BATCH | M68: 23 | N68: =(G68*250)+(M68*30) -> 2190 | O68: NKOSI
C69: CLEANER | D69: XOLILE | E69: THU(16 JAN) TUE(21 JAN) THU(23 JAN) SUN-MON(26-27 JAN) | F69: 61 | G69: 6 | K69: R225 PER DAY R30 PER EXTRA BATCH | M69: 23 | N69: =(G69*225)+(M69*30)-120 -> 1920 | O69: XOLILE
C70: ICER | D70: NATHI | F70: 61 | G70: 5 | K70: R225 PER DAY R30 PER EXTRA BATCH | M70: 23 | N70: =(G70*225)+(M70*30) -> 1815 | O70: NATHI
C71: EXTRA HELPER | D71: NHLELELO | E71: THU(16 JAN) TUE(21 JAN) THU(23 JAN) SUN-MON(26-27 JAN) | F71: 60 | G71: 6 | K71: R225 PER DAY | M71: 23 | N71: =(G71*225)+(M71*30)-100 -> 1940 | O71: NHLELELO
N72: =SUM(N66:N71) -> 11215
C75: DEPARTMENT | D75: EMPLOYEE | E75: DAYS WORKED | F75: SALARY | G75: RATES | H75: EXTRA SHIFT | K75: LOAN | M75: EXTRA | N75: TOTAL
B76: 45688 | C76: ADMIN | D76: LINDIE | E76: MON - SUN (27 JAN - 2 FEB 2025) | F76: 2400 | G76: R400 PER DAY | K76: 400 | N76: =F76-K76 -> 2000 | O76: LINDIE
C77: CO DRIVER | D77: DONELL | E77: MON - FRI (27 JAN - 31 JAN) | F77: 1200 | G77: R200 PER DAY | N77: 1000 | O77: DONELL
C78: DRIVER | D78: JABU | F78: 2200 | G78: R380 PER DAY | N78: 2200 | O78: JABU
C79: HOUSEKEEPER | D79: CLARAH | F79: 1500 | G79: R300 PER DAY | N79: 1500 | O79: CLARAH
N80: =SUM(N76:N79) -> 6700
B82: DATE | C82: DEPARTMENT | D82: EMPLOYEE | E82: DATES OF DAYS WORKED | F82: HOURS WORKED | G82: SHIFTS WORKED | H82: EXTRA BATCHES | I82: EXTRA BATCHES | J82: OWE | K82: RATES | M82: EXTRA BATCHES | N82: TOTAL
B83: 45691 | C83: HEAD BAKER | D83: PEPPY | E83: TUE (28 JAN) THU - FRI(30 - 31 JAN) SUN - MON(2 - 3 FEB) | F83: =12.5+17+7+14+16 -> 66.5 | G83: 6 | K83: R300 PER DAY R30 PER EXTRA BATCH | M83: =1+5+6+11 -> 23 | N83: =(G83*300)+(0*150)+(M83*30) -> 2490 | O83: PEPPY
C84: BAKER | D84: WELCOME | F84: 66.5 | G84: 6 | K84: R225 PER DAY R30 PER EXTRA BATCH | M84: 23 | N84: =(G84*225)+(0*112.5)+(M84*30) -> 2040 | O84: WELCOME
C85: HEAD ICER | D85: THANDIWE | F85: 64.5 | G85: 6 | K85: R250 PER DAY R30 PER EXTRA BATCH | M85: 23 | N85: =(G85*250)+(0*125)+(M85*30) -> 2190 | O85: THANDIWE
C86: ICER | D86: PRIMROSE | F86: 64.5 | G86: 6 | K86: R225 PER DAY R30 PER EXTRA BATCH | M86: 23 | N86: =(G86*225)+(0*112.5)+(M86*30)-80 -> 1960 | O86: PRIMROSE
C87: CLEANER | D87: PORTIA | E87: TUE (28 JAN) THU (30 JAN) SUN - MON(2 - 3 FEB) | F87: 59.5 | G87: 6 | K87: R225 PER DAY R30 PER EXTRA BATCH | M87: 20 | N87: =(G87*225)+(0*112.5)+(M87*30) -> 1950 | O87: PORTIA
C88: EXTRA HELPER | D88: CEBSILE | F88: 59.5 | G88: 5 | K88: R225 PER DAY | M88: 20 | N88: =(G88*225)+(0*112.5)+(M88*30) -> 1725 | O88: CEBSILE
N89: =SUM(N83:N88) -> 12355
C91: DEPARTMENT | D91: EMPLOYEE | E91: DAYS WORKED | F91: SALARY | G91: RATES | H91: EXTRA SHIFT | K91: LOAN | M91: EXTRA | N91: TOTAL
B92: 45695 | C92: ADMIN | D92: LINDIE | E92: MON - FRI(3 - 7 FEB 2025) | F92: 2000 | G92: R400 PER DAY | N92: =F92-K92 -> 2000 | O92: LINDIE
C93: CO DRIVER | D93: DONELL | F93: 1000 | G93: R200 PER DAY | N93: 1000 | O93: DONELL
C94: DRIVER | D94: JABU | F94: 1900 | G94: R380 PER DAY | N94: 1900 | O94: JABU
C95: HOUSEKEEPER | D95: CLARAH | F95: 1500 | G95: R300 PER DAY | N95: 1500 | O95: CLARAH
N96: =SUM(N92:N95) -> 6400
C98: DEPARTMENT | D98: EMPLOYEE | E98: DATES OF DAYS WORKED | F98: HOURS WORKED | G98: SHIFTS WORKED | H98: EXTRA BATCHES | I98: EXTRA BATCHES | J98: OWE | K98: RATES | L98: LOAN | M98: EXTRA BATCHES | N98: TOTAL
B99: 45699 | C99: HEAD BAKER | D99: BOY | E99: TUE(4 FEB) THU(6 FEB) SUN-MON(9 - 10 FEB) | F99: =15+14+16+13 -> 58 | G99: 5 | K99: R260 PER DAY R30 PER EXTRA BATCH | M99: 32 | N99: =(G99*260)+(M99*30)-400 -> 1860 | O99: BOY
C100: BAKER | D100: ZANDILE | F100: 60 | G100: 5 | K100: R225 PER DAY R30 PER EXTRA BATCH | M100: 32 | N100: =(G100*225)+(M100*30)-200 -> 1885 | O100: ZANDILE
C101: HEAD ICER | D101: NKOSI | F101: 61 | G101: 5 | K101: R250 PER DAY R30 PER EXTRA BATCH | M101: 32 | N101: =(G101*250)+(M101*30)-60 -> 2150 | O101: NKOSI
C102: CLEANER | D102: XOLILE | F102: 58 | G102: 5 | K102: R225 PER DAY R30 PER EXTRA BATCH | M102: 32 | N102: =(G102*225)+(M102*30)-120 -> 1965 | O102: XOLILE
C103: ICER | D103: NATHI | F103: 60 | G103: 5 | K103: R225 PER DAY R30 PER EXTRA BATCH | M103: 32 | N103: =(G103*225)+(M103*30)-280 -> 1805 | O103: NATHI
C104: EXTRA HELPER | D104: NHLELELO | F104: 60 | G104: 5 | K104: R225 PER DAY | M104: 32 | N104: =(G104*225)+(M104*30)-80 -> 2005 | O104: NHLELELO
N105: =SUM(N99:N104) -> 11670
C107: DEPARTMENT | D107: EMPLOYEE | E107: DAYS WORKED | F107: SALARY | G107: RATES | H107: EXTRA SHIFT | K107: LOAN | M107: EXTRA | N107: TOTAL
B108: 45702 | C108: ADMIN | D108: LINDIE | E108: MON - SUN(9 - 16 FEB 2025) | F108: 2600 | G108: R400 PER DAY | K108: 200 | N108: =F108-K108 -> 2400 | O108: LINDIE
C109: CO DRIVER | D109: DONELL | F109: 1000 | G109: R200 PER DAY | N109: 1000 | O109: DONELL
C110: DRIVER | D110: JABU | F110: 1900 | G110: R380 PER DAY | N110: 1900 | O110: JABU
C111: HOUSEKEEPER | D111: CLARAH | F111: 1500 | G111: R300 PER DAY | N111: 1500 | O111: CLARAH
N112: =SUM(N108:N111) -> 6800
B114: DATE | C114: DEPARTMENT | D114: EMPLOYEE | E114: DATES OF DAYS WORKED | F114: HOURS WORKED | G114: SHIFTS WORKED | H114: EXTRA BATCHES | I114: EXTRA BATCHES | J114: OWE | K114: RATES | M114: EXTRA BATCHES | N114: TOTAL
B115: 45705 | C115: HEAD BAKER | D115: PEPPY | E115: TUE(11 FEB)THU-FRI(13 - 14 FEB) SUN-MON(16 - 17 FEB) | F115: =16+15.5+8.5+18.5+18 -> 76.5 | G115: 6 | K115: R300 PER DAY R30 PER EXTRA BATCH | M115: =11+9+8 -> 28 | N115: =(G115*300)+(0*150)+(M115*30) -> 2640 | O115: PEPPY
...

Sheet Template deliveries
A2: DATE | D2: DAY
D3: Units | E3: Units
D4: 6am | E4: 6pm | F4: Use
B6: Write down the electricity use
D7: CHOC 7 | E7: VAN 7 | F7: COFFEE7 | G7: CARROT 11 | H7: DM 9 | I7: TOTAL
B8: Batches
B9: Totals
B10: BAKED DAY SHIFT
B11: BAKED NIGHT SHIFT
B12: FLOPS
B13: CASH SALES
B14: LEFT PREVIOUS DAY
B15: TOTAL
A17: Order no | B17: DELIVERIES | C17: TOTAL | D17: CHOC | E17: VAN | F17: COFFEE | G17: CARROT | H17: DM | I17: TOTAL | J17: CRATES
B18: BARBERTON PNP
B19: Tuisbedryf
B20: Grove Spar Riverside
B21: Plaza Spar Nelspruit
B23: HYPER CHECKERS ORCHADS
B24: RIVERSIDE CHECKERS
B25: WHITERIVER CHECKERS
B27: HAZYVIEW SPAR NDLOVU
B28: HAZYVIEW CHECKERS
B30: LYDENBURG PNP
B31: LYDENBURG CHECKERS
B33: COUNTRY KING
... B40: KLIPFONTEIN
B42: MARCO | K42: =D42 -> 0 | U42: =K42 -> 0 | AE42: =U42 -> 0
K43: DAY | L43: DATE | M43: HAZYVIEW PICK AND PAY | U43: DAY | V43: DATE | W43: TUISBEDRYF | AE43: DAY | AF43: DATE | AG43: VILLAGE SPAR | AO43: TOTALS
B44: TOTALS | M44: CHOC | N44: VAN | O44: BF | P44: COF | Q44: DM | R44: CT | S44: SPES | T44: TOTALS | W44: CHOC | X44: VAN | Y44: BF | Z44: COF | AA44: DM | AB44: CT | AC44: SPES | AD44: TOTALS | AG44: CHOC | AH44: VAN | AI44: BF | AJ44: COF | AK44: DM | AL44: CT | AM44: SPES | AN44: TOTALS
K45: MON | L45: =B45 -> 0 | T45: =(M45+N45+O45+P45+Q45+R45)*100+(S45*160) -> 0 | U45: MON | V45: =L45 -> 0 | AD45: =(W45+X45+Y45+Z45+AA45+AB45)*100+(AC45*160) -> 0 | AE45: MON | AF45: =V45 -> 0 | AN45: =(AG45+AH45+AI45+AJ45+AK45+AL45)*100+(AM45*160) -> 0 | AO45: =SUM(AN45,AD45,T45,J45) -> 0
B46: TOTAL CAKES LEFT AFTER | L46: RET | T46: =(M46+N46+O46+P46+Q46+R46)*100+(S46*160) -> 0 | V46: RET | AD46: =(W46+X46+Y46+Z46+AA46+AB46)*100+(AC46*160) -> 0 | AF46: RET | AN46: =(AG46+AH46+AI46+AJ46+AK46+AL46)*100+(AM46*160) -> 0
B47: TOTAL | C47: =J45-J46 -> #VALUE! | L47: TOTAL | M47: =T45-T46 -> 0 | V47: TOTAL | W47: =AD45-AD46 -> 0 | AF47: TOTAL | AG47: =AN45-AN46 -> 0
A48: TUE | B48: 21 | J48: =(C48+D48+E48+F48+G48+H48)*100+(I48*160) -> 0 | K48: TUE | L48: =B48 -> 21 | T48: =(M48+N48+O48+P48+Q48+R48)*100+(S48*160) -> 0 | U48: TUE | V48: =L48 -> 21 | AD48: =(W48+X48+Y48+Z48+AA48+AB48)*100+(AC48*160) -> 0 | AE48: TUE | AF48: =V48 -> 21 | AN48: =(AG48+AH48+AI48+AJ48+AK48+AL48)*100+(AM48*160) -> 0 | AO48: =SUM(AN48,AD48,T48,J48) -> 0
B49: RET | J49: =(C49+D49+E49+F49+G49+H49)*100+(I49*160) -> 0 | L49: RET | T49: =(M49+N49+O49+P49+Q49+R49)*100+(S49*160) -> 0 | V49: RET | AD49: =(W49+X49+Y49+Z49+AA49+AB49)*100+(AC49*160) -> 0 | AF49: RET | AN49: =(AG49+AH49+AI49+AJ49+AK49+AL49)*100+(AM49*160) -> 0
B50: TOTAL | C50: =J48-J49 -> 0 | L50: TOTAL | M50: =T48-T49 -> 0 | V50: TOTAL | W50: =AD48-AD49 -> 0 | AF50: TOTAL | AG50: =AN48-AN49 -> 0
A51: WED | B51: 22 | J51: =(C51+D51+E51+F51+G51+H51)*100+(I51*160) -> 0 | K51: WED | L51: =B51 -> 22 | T51: =(M51+N51+O51+P51+Q51+R51)*100+(S51*160) -> 0 | U51: WED | V51: =L51 -> 22 | AD51: =(W51+X51+Y51+Z51+AA51+AB51)*100+(AC51*160) -> 0 | AE51: WED | AF51: =V51 -> 22 | AN51: =(AG51+AH51+AI51+AJ51+AK51+AL51)*100+(AM51*160) -> 0 | AO51: =SUM(AN51,AD51,T51,J51) -> 0
B52: RET | J52: =(C52+D52+E52+F52+G52+H52)*100+(I52*160) -> 0 | L52: RET | T52: =(M52+N52+O52+P52+Q52+R52)*100+(S52*160) -> 0 | V52: RET | AD52: =(W52+X52+Y52+Z52+AA52+AB52)*100+(AC52*160) -> 0 | AF52: RET | AN52: =(AG52+AH52+AI52+AJ52+AK52+AL52)*100+(AM52*160) -> 0
B53: TOTAL | C53: =J51-J52 -> 0 | L53: TOTAL | M53: =T51-T52 -> 0 | V53: TOTAL | W53: =AD51-AD52 -> 0 | AF53: TOTAL | AG53: =AN51-AN52 -> 0
A54: THU | B54: 23 | J54: =(C54+D54+E54+F54+G54+H54)*100+(I54*160) -> 0 | K54: THU | L54: =B54 -> 23 | T54: =(M54+N54+O54+P54+Q54+R54)*100+(S54*160) -> 0 | U54: THU | V54: =L54 -> 23 | AD54: =(W54+X54+Y54+Z54+AA54+AB54)*100+(AC54*160) -> 0 | AE54: THU | AF54: =V54 -> 23 | AN54: =(AG54+AH54+AI54+AJ54+AK54+AL54)*100+(AM54*160) -> 0 | AO54: =SUM(AN54,AD54,T54,J54) -> 0
B55: RET | J55: =(C55+D55+E55+F55+G55+H55)*100+(I55*160) -> 0 | L55: RET | T55: =(M55+N55+O55+P55+Q55+R55)*100+(S55*160) -> 0 | V55: RET | AD55: =(W55+X55+Y55+Z55+AA55+AB55)*100+(AC55*160) -> 0 | AF55: RET | AN55: =(AG55+AH55+AI55+AJ55+AK55+AL55)*100+(AM55*160) -> 0
B56: TOTAL | C56: =J54-J55 -> 0 | L56: TOTAL | M56: =T54-T55 -> 0 | V56: TOTAL | W56: =AD54-AD55 -> 0 | AF56: TOTAL | AG56: =AN54-AN55 -> 0
A57: FRI | B57: 24 | J57: =(C57+D57+E57+F57+G57+H57)*100+(I57*160) -> 0 | K57: FRI | L57: =B57 -> 24 | T57: =(M57+N57+O57+P57+Q57+R57)*100+(S57*160) -> 0 | U57: FRI | V57: =L57 -> 24 | AD57: =(W57+X57+Y57+Z57+AA57+AB57)*100+(AC57*160) -> 0 | AE57: FRI | AF57: =V57 -> 24 | AN57: =(AG57+AH57+AI57+AJ57+AK57+AL57)*100+(AM57*160) -> 0 | AO57: =SUM(AN57,AD57,T57,J57) -> 0
B58: RET | J58: =(C58+D58+E58+F58+G58+H58)*100+(I58*160) -> 0 | L58: RET | T58: =(M58+N58+O58+P58+Q58+R58)*100+(S58*160) -> 0 | V58: RET | AD58: =(W58+X58+Y58+Z58+AA58+AB58)*100+(AC58*160) -> 0 | AF58: RET | AN58: =(AG58+AH58+AI58+AJ58+AK58+AL58)*100+(AM58*160) -> 0
B59: TOTAL | C59: =J57-J58 -> 0 | L59: TOTAL | M59: =T57-T58 -> 0 | V59: TOTAL | W59: =AD57-AD58 -> 0 | AF59: TOTAL | AG59: =AN57-AN58 -> 0
A60: SAT | B60: 25 | J60: =(C60+D60+E60+F60+G60+H60)*100+(I60*160) -> 0 | K60: SAT | L60: =B60 -> 25 | T60: =(M60+N60+O60+P60+Q60+R60)*100+(S60*160) -> 0 | U60: SAT | V60: =L60 -> 25 | AD60: =(W60+X60+Y60+Z60+AA60+AB60)*100+(AC60*160) -> 0 | AE60: SAT | AF60: =V60 -> 25 | AN60: =(AG60+AH60+AI60+AJ60+AK60+AL60)*100+(AM60*160) -> 0 | AO60: =SUM(AN60,AD60,T60,J60) -> 0
B61: RET | J61: =(C61+D61+E61+F61+G61+H61)*100+(I61*160) -> 0 | L61: RET | T61: =(M61+N61+O61+P61+Q61+R61)*100+(S61*160) -> 0 | V61: RET | AD61: =(W61+X61+Y61+Z61+AA61+AB61)*100+(AC61*160) -> 0 | AF61: RET | AN61: =(AG61+AH61+AI61+AJ61+AK61+AL61)*100+(AM61*160) -> 0
B62: TOTAL | C62: =J60-J61 -> 0 | L62: TOTAL | M62: =T60-T61 -> 0 | V62: TOTAL | W62: =AD60-AD61 -> 0 | AF62: TOTAL | AG62: =AN60-AN61 -> 0
A63: SUN | B63: 26 | J63: =(C63+D63+E63+F63+G63+H63)*100+(I63*160) -> 0 | K63: SUN | L63: =B63 -> 26 | T63: =(M63+N63+O63+P63+Q63+R63)*100+(S63*160) -> 0 | U63: SUN | V63: =L63 -> 26 | AD63: =(W63+X63+Y63+Z63+AA63+AB63)*100+(AC63*160) -> 0 | AE63: SUN | AF63: =V63 -> 26 | AN63: =(AG63+AH63+AI63+AJ63+AK63+AL63)*100+(AM63*160) -> 0 | AO63: =SUM(AN63,AD63,T63,J63) -> 0
B64: RET | J64: =(C64+D64+E64+F64+G64+H64)*100+(I64*160) -> 0 | L64: RET | T64: =(M64+N64+O64+P64+Q64+R64)*100+(S64*160) -> 0 | V64: RET | AD64: =(W64+X64+Y64+Z64+AA64+AB64)*100+(AC64*160) -> 0 | AF64: RET | AN64: =(AG64+AH64+AI64+AJ64+AK64+AL64)*100+(AM64*160) -> 0
B65: TOTAL | C65: =J63-J64 -> 0 | L65: TOTAL | M65: =T63-T64 -> 0 | V65: TOTAL | W65: =AD63-AD64 -> 0 | AF65: TOTAL | AG65: =AN63-AN64 -> 0
A66: WEEK | B66: =SUM(J45,J48,J51,J54,J57,J60,J63) -> 0 | K66: WEEK | L66: =SUM(T45,T48,T51,T54,T57,T60,T63) -> 0 | U66: WEEK | V66: =SUM(AD45,AD48,AD51,AD54,AD57,AD60,AD63) -> 0 | AE66: WEEK | AF66: =SUM(AN45,AN48,AN51,AN54,AN57,AN60,AN63) -> 0 | AO66: =SUM(AO45,AO48,AO51,AO54,AO57,AO60,AO63) -> 0
A67: RETURNS | B67: =SUM(J46,J49,J52,J55,J58,J61,J64) -> 0 | K67: RETURNS | L67: =SUM(T46,T49,T52,T55,T58,T61,T64) -> 0 | U67: RETURNS | V67: =SUM(AD46,AD49,AD52,AD55,AD58,AD61,AD64) -> 0 | AE67: RETURNS | AF67: =SUM(AN46,AN49,AN52,AN55,AN58,AN61,AN64) -> 0 | AO67: =SUM(AF67,V67,L67,B67) -> 0
A68: BIG TOTAL | B68: =B66-B67 -> 0 | K68: BIG TOTAL | L68: =L66-L67 -> 0 | U68: BIG TOTAL | V68: =V66-V67 -> 0 | AE68: BIG TOTAL | AF68: =AF66-AF67 -> 0 | AO68: =SUM(AF68,V68,L68,B68) -> 0
A70: =D42 -> 0 | K70: =K42 -> 0 | U70: =K70 -> 0 | AE70: =U70 -> 0 | AO70: =AE70 -> 0 | AY70: =AO70 -> 0 | BI70: =AY70 -> 0 | BS70: =BI70 -> 0 | CC70: =BS70 -> 0
A71: DAY | B71: DATE | C71: RIVERSIDE MALL CHECKERS | K71: DAY | L71: DATE | M71: HYPER CHECKERS | U71: DAY | V71: DATE | W71: WHITERIVER CHECKERS | AE71: DAY | AF71: DATE | AG71: HAZYVIEWCHECKERS | AO71: DAY | AP71: DATE | AQ71: ERMELO CHECKERS | AY71: DAY | AZ71: DATE | BA71: MIDDELBURG CHECKERS | BI71: DAY | BJ71: DATE | BK71: SAVEWAYS CHECKERS | BS71: DAY | BT71: DATE | BU71: BEN FLEUR CHECKERS | CC71: DAY | CD71: DATE | CE71: COUNTRYKING | CM71: TOTALS
C72: CHOC | D72: VAN | E72: BF | F72: COF | G72: DM | H72: CT | I72: SPES | J72: TOTALS | M72: CHOC | N72: VAN | O72: BF | P72: COF | Q72: DM | R72: CT | S72: SPES | T72: TOTALS | W72: CHOC | X72: VAN | Y72: BF | Z72: COF | AA72: DM | AB72: CT | AC72: SPES | AD72: TOTALS | AG72: CHOC | AH72: VAN | AI72: BF | AJ72: COF | AK72: DM | AL72: CT | AM72: SPES | AN72: TOTALS | AQ72: CHOC | AR72: VAN | AS72: BF | AT72: COF | AU72: DM | AV72: CT | AW72: SPES | AX72: TOTALS | BA72: CHOC | BB72: VAN | BC72: BF | BD72: COF | BE72: DM | BF72: CT | BG72: SPES | BH72: TOTALS | BK72: CHOC | BL72: VAN | BM72: BF | BN72: COF | BO72: DM | BP72: CT | BQ72: SPES | BR72: TOTALS | BU72: CHOC | BV72: VAN | BW72: BF | BX72: COF | BY72: DM | BZ72: CT | CA72: SPES | CB72: TOTALS | CE72: CHOC | CF72: VAN | CG72: BF | CH72: COF | CI72: DM | CJ72: CT | CK72: SPES | CL72: TOTALS
A73: MON | B73: 20 | J73: =(C73+D73+E73+F73+G73+H73)*100+(I73*160) -> 0 | K73: MON | L73: =B73 -> 20 | T73: =(M73+N73+O73+P73+Q73+R73)*100+(S73*160) -> 0 | U73: MON | V73: =L73 -> 20 | AD73: =(W73+X73+Y73+Z73+AA73+AB73)*100+(AC73*160) -> 0 | AE73: MON | AF73: =V73 -> 20 | AN73: =(AG73+AH73+AI73+AJ73+AK73+AL73)*100+(AM73*160) -> 0 | AO73: MON | AP73: =AF73 -> 20 | AX73: =(AQ73+AR73+AS73+AT73+AU73+AV73)*100+(AW73*160) -> 0 | AY73: MON | AZ73: =AP73 -> 20 | BH73: =(BA73+BB73+BC73+BD73+BE73+BF73)*100+(BG73*160) -> 0 | BI73: MON | BJ73: =AZ73 -> 20 | BR73: =(BK73+BL73+BM73+BN73+BO73+BP73)*100+(BQ73*160) -> 0 | BS73: MON | BT73: =BJ73 -> 20 | CB73: =(BU73+BV73+BW73+BX73+BY73+BZ73)*100+(CA73*160) -> 0 | CC73: MON | CD73: =BT73 -> 20 | CL73: =(CE73+CF73+CG73+CH73+CI73+CJ73)*100+(CK73*160) -> 0 | CM73: =SUM(CL73,CB73,BR73,BH73) -> 0
B74: RET | J74: =(C74+D74+E74+F74+G74+H74)*100+(I74*160) -> 0 | L74: RET | T74: =(M74+N74+O74+P74+Q74+R74)*100+(S74*160) -> 0 | V74: RET | AD74: =(W74+X74+Y74+Z74+AA74+AB74)*100+(AC74*160) -> 0 | AF74: RET | AN74: =(AG74+AH74+AI74+AJ74+AK74+AL74)*100+(AM74*160) -> 0 | AP74: RET | AX74: =(AQ74+AR74+AS74+AT74+AU74+AV74)*100+(AW74*160) -> 0 | AZ74: RET | BH74: =(BA74+BB74+BC74+BD74+BE74+BF74)*100+(BG74*160) -> 0 | BJ74: RET | BR74: =(BK74+BL74+BM74+BN74+BO74+BP74)*100+(BQ74*160) -> 0 | BT74: RET | CB74: =(BU74+BV74+BW74+BX74+BY74+BZ74)*100+(CA74*160) -> 0 | CD74: RET | CL74: =(CE74+CF74+CG74+CH74+CI74+CJ74)*100+(CK74*160) -> 0
B75: TOTAL | C75: =J73-J74 -> 0 | L75: TOTAL | M75: =T73-T74 -> 0 | V75: TOTAL | W75: =AD73-AD74 -> 0 | AF75: TOTAL | AG75: =AN73-AN74 -> 0 | AP75: TOTAL | AQ75: =AX73-AX74 -> 0 | AZ75: TOTAL | BA75: =BH73-BH74 -> 0 | BJ75: TOTAL | BK75: =BR73-BR74 -> 0 | BT75: TOTAL | BU75: =CB73-CB74 -> 0 | CD75: TOTAL | CE75: =CL73-CL74 -> 0
A76: TUE | B76: 21 | J76: =(C76+D76+E76+F76+G76+H76)*100+(I76*160) -> 0 | K76: TUE | L76: =B76 -> 21 | T76: =(M76+N76+O76+P76+Q76+R76)*100+(S76*160) -> 0 | U76: TUE | V76: =L76 -> 21 | AD76: =(W76+X76+Y76+Z76+AA76+AB76)*100+(AC76*160) -> 0 | AE76: TUE | AF76: =V76 -> 21 | AN76: =(AG76+AH76+AI76+AJ76+AK76+AL76)*100+(AM76*160) -> 0 | AO76: TUE | AP76: =AF76 -> 21 | AX76: =(AQ76+AR76+AS76+AT76+AU76+AV76)*100+(AW76*160) -> 0 | AY76: TUE | AZ76: =AP76 -> 21 | BH76: =(BA76+BB76+BC76+BD76+BE76+BF76)*100+(BG76*160) -> 0 | BI76: TUE | BJ76: =AZ76 -> 21 | BR76: =(BK76+BL76+BM76+BN76+BO76+BP76)*100+(BQ76*160) -> 0 | BS76: TUE | BT76: =BJ76 -> 21 | CB76: =(BU76+BV76+BW76+BX76+BY76+BZ76)*100+(CA76*160) -> 0 | CC76: TUE | CD76: =BT76 -> 21 | CL76: =(CE76+CF76+CG76+CH76+CI76+CJ76)*100+(CK76*160) -> 0 | CM76: =SUM(CL76,CB76,BR76,BH76) -> 0
B77: RET | J77: =(C77+D77+E77+F77+G77+H77)*100+(I77*160) -> 0 | L77: RET | T77: =(M77+N77+O77+P77+Q77+R77)*100+(S77*160) -> 0 | V77: RET | AD77: =(W77+X77+Y77+Z77+AA77+AB77)*100+(AC77*160) -> 0 | AF77: RET | AN77: =(AG77+AH77+AI77+AJ77+AK77+AL77)*100+(AM77*160) -> 0 | AP77: RET | AX77: =(AQ77+AR77+AS77+AT77+AU77+AV77)*100+(AW77*160) -> 0 | AZ77: RET | BH77: =(BA77+BB77+BC77+BD77+BE77+BF77)*100+(BG77*160) -> 0 | BJ77: RET | BR77: =(BK77+BL77+BM77+BN77+BO77+BP77)*100+(BQ77*160) -> 0 | BT77: RET | CB77: =(BU77+BV77+BW77+BX77+BY77+BZ77)*100+(CA77*160) -> 0 | CD77: RET | CL77: =(CE77+CF77+CG77+CH77+CI77+CJ77)*100+(CK77*160) -> 0
B78: TOTAL | C78: =J76-J77 -> 0 | L78: TOTAL | M78: =T76-T77 -> 0 | V78: TOTAL | W78: =AD76-AD77 -> 0 | AF78: TOTAL | AG78: =AN76-AN77 -> 0 | AP78: TOTAL | AQ78: =AX76-AX77 -> 0 | AZ78: TOTAL | BA78: =BH76-BH77 -> 0 | BJ78: TOTAL | BK78: =BR76-BR77 -> 0 | BT78: TOTAL | BU78: =CB76-CB77 -> 0 | CD78: TOTAL | CE78: =CL76-CL77 -> 0
A79: WED | B79: 22 | J79: =(C79+D79+E79+F79+G79+H79)*100+(I79*160) -> 0 | K79: WED | L79: =B79 -> 22 | T79: =(M79+N79+O79+P79+Q79+R79)*100+(S79*160) -> 0 | U79: WED | V79: =L79 -> 22 | AD79: =(W79+X79+Y79+Z79+AA79+AB79)*100+(AC79*160) -> 0 | AE79: WED | AF79: =V79 -> 22 | AN79: =(AG79+AH79+AI79+AJ79+AK79+AL79)*100+(AM79*160) -> 0 | AO79: WED | AP79: =AF79 -> 22 | AX79: =(AQ79+AR79+AS79+AT79+AU79+AV79)*100+(AW79*160) -> 0 | AY79: WED | AZ79: =AP79 -> 22 | BH79: =(BA79+BB79+BC79+BD79+BE79+BF79)*100+(BG79*160) -> 0 | BI79: WED | BJ79: =AZ79 -> 22 | BR79: =(BK79+BL79+BM79+BN79+BO79+BP79)*100+(BQ79*160) -> 0 | BS79: WED | BT79: =BJ79 -> 22 | CB79: =(BU79+BV79+BW79+BX79+BY79+BZ79)*100+(CA79*160) -> 0 | CC79: WED | CD79: =BT79 -> 22 | CL79: =(CE79+CF79+CG79+CH79+CI79+CJ79)*100+(CK79*160) -> 0 | CM79: =SUM(CL79,CB79,BR79,BH79) -> 0
B80: RET | J80: =(C80+D80+E80+F80+G80+H80)*100+(I80*160) -> 0 | L80: RET | T80: =(M80+N80+O80+P80+Q80+R80)*100+(S80*160) -> 0 | V80: RET | AD80: =(W80+X80+Y80+Z80+AA80+AB80)*100+(AC80*160) -> 0 | AF80: RET | AN80: =(AG80+AH80+AI80+AJ80+AK80+AL80)*100+(AM80*160) -> 0 | AP80: RET | AX80: =(AQ80+AR80+AS80+AT80+AU80+AV80)*100+(AW80*160) -> 0 | AZ80: RET | BH80: =(BA80+BB80+BC80+BD80+BE80+BF80)*100+(BG80*160) -> 0 | BJ80: RET | BR80: =(BK80+BL80+BM80+BN80+BO80+BP80)*100+(BQ80*160) -> 0 | BT80: RET | CB80: =(BU80+BV80+BW80+BX80+BY80+BZ80)*100+(CA80*160) -> 0 | CD80: RET | CL80: =(CE80+CF80+CG80+CH80+CI80+CJ80)*100+(CK80*160) -> 0
B81: TOTAL | C81: =J79-J80 -> 0 | L81: TOTAL | M81: =T79-T80 -> 0 | V81: TOTAL | W81: =AD79-AD80 -> 0 | AF81: TOTAL | AG81: =AN79-AN80 -> 0 | AP81: TOTAL | AQ81: =AX79-AX80 -> 0 | AZ81: TOTAL | BA81: =BH79-BH80 -> 0 | BJ81: TOTAL | BK81: =BR79-BR80 -> 0 | BT81: TOTAL | BU81: =CB79-CB80 -> 0 | CD81: TOTAL | CE81: =CL79-CL80 -> 0
A82: THU | B82: 23 | J82: =(C82+D82+E82+F82+G82+H82)*100+(I82*160) -> 0 | K82: THU | L82: =B82 -> 23 | T82: =(M82+N82+O82+P82+Q82+R82)*100+(S82*160) -> 0 | U82: THU | V82: =L82 -> 23 | AD82: =(W82+X82+Y82+Z82+AA82+AB82)*100+(AC82*160) -> 0 | AE82: THU | AF82: =V82 -> 23 | AN82: =(AG82+AH82+AI82+AJ82+AK82+AL82)*100+(AM82*160) -> 0 | AO82: THU | AP82: =AF82 -> 23 | AX82: =(AQ82+AR82+AS82+AT82+AU82+AV82)*100+(AW82*160) -> 0 | AY82: THU | AZ82: =AP82 -> 23 | BH82: =(BA82+BB82+BC82+BD82+BE82+BF82)*100+(BG82*160) -> 0 | BI82: THU | BJ82: =AZ82 -> 23 | BR82: =(BK82+BL82+BM82+BN82+BO82+BP82)*100+(BQ82*160) -> 0 | BS82: THU | BT82: =BJ82 -> 23 | CB82: =(BU82+BV82+BW82+BX82+BY82+BZ82)*100+(CA82*160) -> 0 | CC82: THU | CD82: =BT82 -> 23 | CL82: =(CE82+CF82+CG82+CH82+CI82+CJ82)*100+(CK82*160) -> 0 | CM82: =SUM(CL82,CB82,BR82,BH82) -> 0
B83: RET | J83: =(C83+D83+E83+F83+G83+H83)*100+(I83*160) -> 0 | L83: RET | T83: =(M83+N83+O83+P83+Q83+R83)*100+(S83*160) -> 0 | V83: RET | AD83: =(W83+X83+Y83+Z83+AA83+AB83)*100+(AC83*160) -> 0 | AF83: RET | AN83: =(AG83+AH83+AI83+AJ83+AK83+AL83)*100+(AM83*160) -> 0 | AP83: RET | AX83: =(AQ83+AR83+AS83+AT83+AU83+AV83)*100+(AW83*160) -> 0 | AZ83: RET | BH83: =(BA83+BB83+BC83+BD83+BE83+BF83)*100+(BG83*160) -> 0 | BJ83: RET | BR83: =(BK83+BL83+BM83+BN83+BO83+BP83)*100+(BQ83*160) -> 0 | BT83: RET | CB83: =(BU83+BV83+BW83+BX83+BY83+BZ83)*100+(CA83*160) -> 0 | CD83: RET | CL83: =(CE83+CF83+CG83+CH83+CI83+CJ83)*100+(CK83*160) -> 0
B84: TOTAL | C84: =J82-J83 -> 0 | L84: TOTAL | M84: =T82-T83 -> 0 | V84: TOTAL | W84: =AD82-AD83 -> 0 | AF84: TOTAL | AG84: =AN82-AN83 -> 0 | AP84: TOTAL | AQ84: =AX82-AX83 -> 0 | AZ84: TOTAL | BA84: =BH82-BH83 -> 0 | BJ84: TOTAL | BK84: =BR82-BR83 -> 0 | BT84: TOTAL | BU84: =CB82-CB83 -> 0 | CD84: TOTAL | CE84: =CL82-CL83 -> 0
A85: FRI | B85: 24 | J85: =(C85+D85+E85+F85+G85+H85)*100+(I85*160) -> 0 | K85: FRI | L85: =B85 -> 24 | T85: =(M85+N85+O85+P85+Q85+R85)*100+(S85*160) -> 0 | U85: FRI | V85: =L85 -> 24 | AD85: =(W85+X85+Y85+Z85+AA85+AB85)*100+(AC85*160) -> 0 | AE85: FRI | AF85: =V85 -> 24 | AN85: =(AG85+AH85+AI85+AJ85+AK85+AL85)*100+(AM85*160) -> 0 | AO85: FRI | AP85: =AF85 -> 24 | AX85: =(AQ85+AR85+AS85+AT85+AU85+AV85)*100+(AW85*160) -> 0 | AY85: FRI | AZ85: =AP85 -> 24 | BH85: =(BA85+BB85+BC85+BD85+BE85+BF85)*100+(BG85*160) -> 0 | BI85: FRI | BJ85: =AZ85 -> 24 | BR85: =(BK85+BL85+BM85+BN85+BO85+BP85)*100+(BQ85*160) -> 0 | BS85: FRI | BT85: =BJ85 -> 24 | CB85: =(BU85+BV85+BW85+BX85+BY85+BZ85)*100+(CA85*160) -> 0 | CC85: FRI | CD85: =BT85 -> 24 | CL85: =(CE85+CF85+CG85+CH85+CI85+CJ85)*100+(CK85*160) -> 0 | CM85: =SUM(CL85,CB85,BR85,BH85) -> 0
B86: RET | J86: =(C86+D86+E86+F86+G86+H86)*100+(I86*160) -> 0 | L86: RET | T86: =(M86+N86+O86+P86+Q86+R86)*100+(S86*160) -> 0 | V86: RET | AD86: =(W86+X86+Y86+Z86+AA86+AB86)*100+(AC86*160) -> 0 | AF86: RET | AN86: =(AG86+AH86+AI86+AJ86+AK86+AL86)*100+(AM86*160) -> 0 | AP86: RET | AX86: =(AQ86+AR86+AS86+AT86+AU86+AV86)*100+(AW86*160) -> 0 | AZ86: RET | BH86: =(BA86+BB86+BC86+BD86+BE86+BF86)*100+(BG86*160) -> 0 | BJ86: RET | BR86: =(BK86+BL86+BM86+BN86+BO86+BP86)*100+(BQ86*160) -> 0 | BT86: RET | CB86: =(BU86+BV86+BW86+BX86+BY86+BZ86)*100+(CA86*160) -> 0 | CD86: RET | CL86: =(CE86+CF86+CG86+CH86+CI86+CJ86)*100+(CK86*160) -> 0
B87: TOTAL | C87: =J85-J86 -> 0 | L87: TOTAL | M87: =T85-T86 -> 0 | V87: TOTAL | W87: =AD85-AD86 -> 0 | AF87: TOTAL | AG87: =AN85-AN86 -> 0 | AP87: TOTAL | AQ87: =AX85-AX86 -> 0 | AZ87: TOTAL | BA87: =BH85-BH86 -> 0 | BJ87: TOTAL | BK87: =BR85-BR86 -> 0 | BT87: TOTAL | BU87: =CB85-CB86 -> 0 | CD87: TOTAL | CE87: =CL85-CL86 -> 0
A88: SAT | B88: 25 | J88: =(C88+D88+E88+F88+G88+H88)*100+(I88*160) -> 0 | K88: SAT | L88: =B88 -> 25 | T88: =(M88+N88+O88+P88+Q88+R88)*100+(S88*160) -> 0 | U88: SAT | V88: =L88 -> 25 | AD88: =(W88+X88+Y88+Z88+AA88+AB88)*100+(AC88*160) -> 0 | AE88: SAT | AF88: =V88 -> 25 | AN88: =(AG88+AH88+AI88+AJ88+AK88+AL88)*100+(AM88*160) -> 0 | AO88: SAT | AP88: =AF88 -> 25 | AX88: =(AQ88+AR88+AS88+AT88+AU88+AV88)*100+(AW88*160) -> 0 | AY88: SAT | AZ88: =AP88 -> 25 | BH88: =(BA88+BB88+BC88+BD88+BE88+BF88)*100+(BG88*160) -> 0 | BI88: SAT | BJ88: =AZ88 -> 25 | BR88: =(BK88+BL88+BM88+BN88+BO88+BP88)*100+(BQ88*160) -> 0 | BS88: SAT | BT88: =BJ88 -> 25 | CB88: =(BU88+BV88+BW88+BX88+BY88+BZ88)*100+(CA88*160) -> 0 | CC88: SAT | CD88: =BT88 -> 25 | CL88: =(CE88+CF88+CG88+CH88+CI88+CJ88)*100+(CK88*160) -> 0 | CM88: =SUM(CL88,CB88,BR88,BH88) -> 0
B89: RET | J89: =(C89+D89+E89+F89+G89+H89)*100+(I89*160) -> 0 | L89: RET | T89: =(M89+N89+O89+P89+Q89+R89)*100+(S89*160) -> 0 | V89: RET | AD89: =(W89+X89+Y89+Z89+AA89+AB89)*100+(AC89*160) -> 0 | AF89: RET | AN89: =(AG89+AH89+AI89+AJ89+AK89+AL89)*100+(AM89*160) -> 0 | AP89: RET | AX89: =(AQ89+AR89+AS89+AT89+AU89+AV89)*100+(AW89*160) -> 0 | AZ89: RET | BH89: =(BA89+BB89+BC89+BD89+BE89+BF89)*100+(BG89*160) -> 0 | BJ89: RET | BR89: =(BK89+BL89+BM89+BN89+BO89+BP89)*100+(BQ89*160) -> 0 | BT89: RET | CB89: =(BU89+BV89+BW89+BX89+BY89+BZ89)*100+(CA89*160) -> 0 | CD89: RET | CL89: =(CE89+CF89+CG89+CH89+CI89+CJ89)*100+(CK89*160) -> 0
B90: TOTAL | C90: =J88-J89 -> 0 | L90: TOTAL | M90: =T88-T89 -> 0 | V90: TOTAL | W90: =AD88-AD89 -> 0 | AF90: TOTAL | AG90: =AN88-AN89 -> 0 | AP90: TOTAL | AQ90: =AX88-AX89 -> 0 | AZ90: TOTAL | BA90: =BH88-BH89 -> 0 | BJ90: TOTAL | BK90: =BR88-BR89 -> 0 | BT90: TOTAL | BU90: =CB88-CB89 -> 0 | CD90: TOTAL | CE90: =CL88-CL89 -> 0
A91: SUN | B91: 26 | J91: =(C91+D91+E91+F91+G91+H91)*100+(I91*160) -> 0 | K91: SUN | L91: =B91 -> 26 | T91: =(M91+N91+O91+P91+Q91+R91)*100+(S91*160) -> 0 | U91: SUN | V91: =L91 -> 26 | AD91: =(W91+X91+Y91+Z91+AA91+AB91)*100+(AC91*160) -> 0 | AE91: SUN | AF91: =V91 -> 26 | AN91: =(AG91+AH91+AI91+AJ91+AK91+AL91)*100+(AM91*160) -> 0 | AO91: SUN | AP91: =AF91 -> 26 | AX91: =(AQ91+AR91+AS91+AT91+AU91+AV91)*100+(AW91*160) -> 0 | AY91: SUN | AZ91: =AP91 -> 26 | BH91: =(BA91+BB91+BC91+BD91+BE91+BF91)*100+(BG91*160) -> 0 | BI91: SUN | BJ91: =AZ91 -> 26 | BR91: =(BK91+BL91+BM91+BN91+BO91+BP91)*100+(BQ91*160) -> 0 | BS91: SUN | BT91: =BJ91 -> 26 | CB91: =(BU91+BV91+BW91+BX91+BY91+BZ91)*100+(CA91*160) -> 0 | CC91: SUN | CD91: =BT91 -> 26 | CL91: =(CE91+CF91+CG91+CH91+CI91+CJ91)*100+(CK91*160) -> 0 | CM91: =SUM(CL91,CB91,BR91,BH91) -> 0
B92: RET | J92: =(C92+D92+E92+F92+G92+H92)*100+(I92*160) -> 0 | L92: RET | T92: =(M92+N92+O92+P92+Q92+R92)*100+(S92*160) -> 0 | V92: RET | AD92: =(W92+X92+Y92+Z92+AA92+AB92)*100+(AC92*160) -> 0 | AF92: RET | AN92: =(AG92+AH92+AI92+AJ92+AK92+AL92)*100+(AM92*160) -> 0 | AP92: RET | AX92: =(AQ92+AR92+AS92+AT92+AU92+AV92)*100+(AW92*160) -> 0 | AZ92: RET | BH92: =(BA92+BB92+BC92+BD92+BE92+BF92)*100+(BG92*160) -> 0 | BJ92: RET | BR92: =(BK92+BL92+BM92+BN92+BO92+BP92)*100+(BQ92*160) -> 0 | BT92: RET | CB92: =(BU92+BV92+BW92+BX92+BY92+BZ92)*100+(CA92*160) -> 0 | CD92: RET | CL92: =(CE92+CF92+CG92+CH92+CI92+CJ92)*100+(CK92*160) -> 0
B93: TOTAL | C93: =J91-J92 -> 0 | L93: TOTAL | M93: =T91-T92 -> 0 | V93: TOTAL | W93: =AD91-AD92 -> 0 | AF93: TOTAL | AG93: =AN91-AN92 -> 0 | AP93: TOTAL | AQ93: =AX91-AX92 -> 0 | AZ93: TOTAL | BA93: =BH91-BH92 -> 0 | BJ93: TOTAL | BK93: =BR91-BR92 -> 0 | BT93: TOTAL | BU93: =CB91-CB92 -> 0 | CD93: TOTAL | CE93: =CL91-CL92 -> 0
A94: WEEK | B94: =SUM(J73,J76,J79,J82,J85,J88,J91) -> 0 | K94: WEEK | L94: =SUM(T73,T76,T79,T82,T85,T88,T91) -> 0 | U94: WEEK | V94: =SUM(AD73,AD76,AD79,AD82,AD85,AD88,AD91) -> 0 | AE94: WEEK | AF94: =SUM(AN73,AN76,AN79,AN82,AN85,AN88,AN91) -> 0 | AO94: WEEK | AP94: =SUM(AX73,AX76,AX79,AX82,AX85,AX88,AX91) -> 0 | AY94: WEEK | AZ94: =SUM(BH73,BH76,BH79,BH82,BH85,BH88,BH91) -> 0 | BI94: WEEK | BJ94: =SUM(BR73,BR76,BR79,BR82,BR85,BR88,BR91) -> 0 | BS94: WEEK | BT94: =SUM(CB73,CB76,CB79,CB82,CB85,CB88,CB91) -> 0 | CC94: WEEK | CD94: =SUM(CL73,CL76,CL79,CL82,CL85,CL88,CL91) -> 0 | CM94: =SUM(CM91,CM88,CM85,CM82,CM79,CM76,CM73) -> 0
A95: RETURNS | B95: =SUM(J74,J77,J80,J83,J86,J89,J92) -> 0 | K95: RETURNS | L95: =SUM(T74,T77,T80,T83,T86,T89,T92) -> 0 | U95: RETURNS | V95: =SUM(AD74,AD77,AD80,AD83,AD86,AD89,AD92) -> 0 | AE95: RETURNS | AF95: =SUM(AN74,AN77,AN80,AN83,AN86,AN89,AN92) -> 0 | AO95: RETURNS | AP95: =SUM(AX74,AX77,AX80,AX83,AX86,AX89,AX92) -> 0 | AY95: RETURNS | AZ95: =SUM(BH74,BH77,BH80,BH83,BH86,BH89,BH92) -> 0 | BI95: RETURNS | BJ95: =SUM(BR74,BR77,BR80,BR83,BR86,BR89,BR92) -> 0 | BS95: RETURNS | BT95: =SUM(CB74,CB77,CB80,CB83,CB86,CB89,CB92) -> 0 | CC95: RETURNS | CD95: =SUM(CL74,CL77,CL80,CL83,CL86,CL89,CL92) -> 0 | CM95: =SUM(CD95,BT95,BJ95,AZ95,AP95,AF95,V95,L95,B95) -> 0
A96: BIG TOTAL | B96: =B94-B95 -> 0 | K96: BIG TOTAL | L96: =L94-L95 -> 0 | U96: BIG TOTAL | V96: =V94-V95 -> 0 | AE96: BIG TOTAL | AF96: =AF94-AF95 -> 0 | AO96: BIG TOTAL | AP96: =AP94-AP95 -> 0 | AY96: BIG TOTAL | AZ96: =AZ94-AZ95 -> 0 | BI96: BIG TOTAL | BJ96: =BJ94-BJ95 -> 0 | BS96: BIG TOTAL | BT96: =BT94-BT95 -> 0 | CC96: BIG TOTAL | CD96: =CD94-CD95 -> 0 | CM96: =SUM(B96,L96,V96,AF96,AP96,AZ96,BJ96,BT96,CD96) -> 0
D98: DAY | J98: DATE
D99: TIME | E99: TIME | F99: CHOCOLATE | G99: VANILLA | H99: COFFEE | I99: CARROT | J99: DM | K99: BOX | L99: CUPCAKES | M99: FLOPS | N99: BAKERS | O99: NOTES
C100: BATCHES | D100: IN | E100: OUT
C101: 1
C102: 2
C103: 3
C104: 4
C105: 5
C106: 6
C107: 7
C108: 8
C109: 9
C110: 10
C111: 11
C112: 12
... C130: 30
C131: TOTALS
C132: GRAND TOTAL

Sheet PLANNING
AD1: QUANTITY | AE1: TOTAL
C2: MON | F2: TUE | I2: WED | L2: THU | O2: FRI | AC2: ELECTRICITY | AD2: 1 | AE2: =AD2*1500 -> 1500
C3: CHOC | D3: VAN | E3: CAR | F3: CHOC | G3: VAN | H3: CAR | I3: CHOC | J3: VAN | K3: CAR | L3: CHOC | M3: VAN | N3: CAR | O3: CHOC | P3: VAN | Q3: CAR | AC3: FLOUR | AD3: 8 | AE3: =AD3*140 -> 1120
B4: HYPER CHECKERS | AC4: BAK POWD | AD4: 5 | AE4: =AD4*43 -> 215
B5: RIVERSIDE CHECKERS | AC5: SALT | AE5: =AD5*10 -> 0
B6: WHITERIVER CHECKERS | AC6: BSUGAR | AD6: 2 | AE6: =AD6*182 -> 364
B7: HAZYVIEW CHECKERS | AC7: WSUGAR | AD7: 2 | AE7: =AD7*205 -> 410
B8: LYDENBURG CHECKERS | AC8: OIL | AD8: 8 | AE8: =AD8*145 -> 1160
B9: ERMELO CHECKERS | AC9: ELLIS BROWN | AD9: 1 | AE9: =AD9*75 -> 75
B10: ERMELO MERINO MALL CHECKERS | AC10: MILK | AD10: 4 | AE10: =AD10*99 -> 396
B11: MIDDELBURG CHECKERS | AC11: VINEGAR | AD11: 1 | AE11: =AD11*27 -> 27
B12: SAVEWAYS CHECKERS | AC12: RICOFFY | AE12: =AD12*135 -> 0
B13: KLIPFONTEIN CHECKERS | AC13: CELLOTAPE | AD13: 5 | AE13: =AD13*42 -> 210
B14: GRAND TOTAL | C14: =SUM(C4:C13) -> 0 | D14: =SUM(D4:D13) -> 0 | E14: =SUM(E4:E13) -> 0 | F14: =SUM(F4:F13) -> 0 | G14: =SUM(G4:G13) -> 0 | H14: =SUM(H4:H13) -> 0 | I14: =SUM(I4:I13) -> 0 | J14: =SUM(J4:J13) -> 0 | ... Q14: =SUM(Q4:Q13) -> 0 | AC14: CARROTS | AD14: 7 | AE14: =AD14*40 -> 280
B15: TOTAL BATCHES | C15: =C14/7 -> 0 | D15: =D14/7 -> 0 | E15: =E14/11 -> 0 | F15: =F14/7 -> 0 | G15: =G14/7 -> 0 | H15: =H14/11 -> 0 | I15: =I14/7 -> 0 | J15: =J14/7 -> 0 | K15: =K14/11 -> 0 | L15: =L14/7 -> 0 | M15: =M14/7 -> 0 | N15: =N14/11 -> 0 | O15: =O14/7 -> 0 | P15: =P14/7 -> 0 | Q15: =Q14/11 -> 0 | AC15: TOTAL | AE15: =SUM(AE2:AE14) -> 5757
C16: MON | H16: TUE | M16: WED | R16: THU | W16: FRI
C17: CHOC | D17: VAN | E17: COF | F17: CAR | G17: DM | H17: CHOC | I17: VAN | J17: COF | K17: CAR | L17: DM | M17: CHOC | N17: VAN | O17: COF | P17: CAR | Q17: DM | R17: CHOC | S17: VAN | T17: COF | U17: CAR | V17: DM | W17: CHOC | X17: VAN | Y17: COF | Z17: CAR | AA17: DM
B18: BARBERTON PNP
B19: TUISBEDRYF
B20: GROVE SPAR
B21: PLAZA SPAR
B22: HAZYVIEW SPAR
B23: LYDENBURG PNP
B24: COUNTRY KING
B25: CAROLINA SPAR
B26: GRAND TOTAL | C26: =SUM(C19:C25) -> 0 | D26: =SUM(D19:D25) -> 0 | E26: =SUM(E19:E25) -> 0 | F26: =SUM(F19:F25) -> 0 | G26: =SUM(G19:G25) -> 0 | H26: =SUM(H19:H25) -> 0 | I26: =SUM(I19:I25) -> 0 | J26: =SUM(J19:J25) -> 0 | ... AA26: =SUM(AA19:AA25) -> 0
B27: TOTAL BATCHES | C27: =C26/7 -> 0 | D27: =D26/7 -> 0 | E27: =E26/7 -> 0 | F27: =F26/11 -> 0 | G27: =G26/9 -> 0 | H27: =H26/7 -> 0 | I27: =I26/7 -> 0 | J27: =J26/7 -> 0 | K27: =K26/11 -> 0 | L27: =L26/9 -> 0 | M27: =M26/7 -> 0 | N27: =N26/7 -> 0 | O27: =O26/7 -> 0 | P27: =P26/11 -> 0 | Q27: =Q26/9 -> 0 | R27: =R26/7 -> 0 | S27: =S26/7 -> 0 | T27: =T26/7 -> 0 | U27: =U26/11 -> 0 | V27: =V26/9 -> 0 | W27: =W26/7 -> 0 | X27: =X26/7 -> 0 | Y27: =Y26/7 -> 0 | Z27: =Z26/11 -> 0 | AA27: =AA26/9 -> 0

Sheet banking details
B2: NAME | C2: BANK | D2: ACCOUNT NO. | E2: BRANCH CODE
B3: BOY | C3: CAPITEC | D3: 1236902254 | E3: 470010
B4: ZANDILE1 | C4: CAPITEC | D4: 1767726501 | E4: 470010
B5: GOODNESS | C5: TYME BANK | D5: 51045667992 | E5: 678910
B6: ZANDILE TAMATIE | C6: CAPITEC | D6: 1293053757 | E6: 470010
B7: PRIMROSE | C7: CAPITEC | D7: 1371610019 | E7: 470010
B8: PEPPY | C8: CAPITEC | D8: 1277114178 | E8: 470010
B9: ANGEL | C9: CAPITEC | D9: 1277114178 | E9: 470010
B10: LUCY | C10: CAPITEC | D10: 1299672742 | E10: 470010
B11: STHABILE | C11: CAPITEC | D11: 1865867517 | E11: 470010
B12: THANDIWE | C12: CAPITEC | D12: 1517673400 | E12: 470010
B13: NHLANHLA | C13: CAPITEC | D13: 1699410443 | E13: 470010
B14: JABU | C14: TYME BANK | D14: 51016354078 | E14: 678910
... B17: CLARAH | C17: CAPITEC | D17: 1166111367 | E17: 470010
B19: EMPLOYEE | C19: MONTHLY SALARY
B20: PEPPY | C20: =1500+1260+1260 -> 4020
B21: LUCY | C21: =1000+720+1180 -> 2900
B22: ANGEL | C22: =1125+960+960 -> 3045
B23: THANDIWE | C23: =1250+1060+1060 -> 3370
B24: STHABILE | C24: =900+900+960 -> 2760
B25: BOY | C25: =1100+720+1070 -> 2890
B26: ZANDILE 1 | C26: =720+900+1175 -> 2795
B27: ZANDILE 2 | C27: =1000+1430+720 -> 3150
B28: PRIMROSE | C28: =900+960+960 -> 2820
B29: GOODNESS | C29: =1620+1080 -> 2700
B30: LINDIE | C30: =1500+1800+1150+1500 -> 5950
B31: JABU | C31: =1800*4 -> 7200
B32: NHLANHLA | C32: =600*4 -> 2400
B33: GEORGE | C33: =1200*4 -> 4800
B34: CLARA | C34: =1250*4 -> 5000
B35: TOTAL | C35: =SUM(C20:C34) -> 55800

Sheet CAKE COSTING
B2: DARK MOIST CAKE
A5: CAKE TYPE | B5: Baking
A6: Dark Moist Cake | B6: Flour | C6: 145.99 | D6: 12,5kg | E6: 84 | F6: 0.21428571 | G6: 18 | H6: 250ml | I6: 31.283571
B7: Bpowder | C7: 1000 | D7: 20kg | E7: 1111 | F7: 0.00450045 | G7: 5 | H7: 15ml | I7: 4.50045
B8: Salt | C8: 5 | D8: 1kg | E8: 142 | F8: 0.0070422535 | G8: 1 | H8: 5ml | I8: 0.035211268
B9: Cocoa | C9: 4358.8 | D9: 25kg | E9: 312 | F9: 0.0096153846 | G9: 3 | H9: 250ml | I9: 41.911538
B10: Bicarb | C10: 772.8 | D10: 25kg | E10: 1000 | F10: 0.005 | G10: 5 | H10: 15ml | I10: 3.864
B11: Eggs | C11: 449.99 | D11: 180 | E11: 60 | F11: 0.3 | G11: 18 | H11: 1 | I11: 134.997
B12: Bsugar | C12: 172.99 | D12: 10kg | E12: 46 | F12: 0.39130435 | G12: 18 | H12: 250ml | I12: 67.691739
B13: Wsugar | C13: 200 | D13: 10kg | E13: 46 | F13: 0 | G13: 0 | H13: 250ml | I13: 0
B14: Oil | C14: 118 | D14: 5liter | E14: 20 | F14: 0.25 | G14: 5 | H14: 250ml | I14: 29.5
B15: Vanilla | C15: 142.95 | D15: 3liter | E15: 37.5 | F15: 0 | G15: 0 | H15: 80ml | I15: 0
B16: Ellis Brown | C16: 74.99 | D16: 1kg | E16: 25 | F16: 0 | G16: 0 | H16: 80ml | I16: 0
B17: Milk | C17: 91.99 | D17: 6liter | E17: 6 | F17: 0.375 | G17: 2.25 | H17: 1l | I17: 34.49625
B18: Cinnamon | C18: 500 | D18: 5kg | E18: 1000 | F18: 0 | G18: 0 | H18: 15ml | I18: 0
B19: Carrots | C19: 29.99 | D19: 3kg | E19: 3 | F19: 0 | G19: 0 | H19: 1kg | I19: 0
B20: Vinegar | C20: 26.99 | D20: 5liter | E20: 83 | F20: 0.012048193 | G20: 1 | H20: 60ml | I20: 0.32518072
B21: Water | C21: 0 | F21: 8 | G21: 2 | H21: 1l
B22: Ricoffy | C22: 109.99 | D22: 750g | E22: 30 | F22: 0.066666667 | G22: 0 | H22: 80ml | I22: 0
B23: Packaging
B24: Domes | C24: 239 | D24: 100 | E24: 100 | F24: 0.09 | G24: 9 | H24: 1
B25: Fomos | C25: 90 | D25: 75 | E25: 75 | F25: 0.12 | G25: 9 | H25: 1
B26: Bases | C26: 239 | D26: 100 | E26: 100 | F26: 0.09 | G26: 9 | H26: 1
B27: icing | C27: 550 | D27: 25kg
B28: Lables
B29: Sleeves | F29: 7 | G29: 9
B30: Stock | C30: Cost | D30: Size | E30: Life | F30: Amount | G30: x Life | H30: Life Size | I30: =SUM(I6:I28) -> 348.60494
B32: TOTAL COST FOR 1 BATCH: | H32: =I30 -> 348.60494
B34: TOTAL COST FOR 1 DOUBLE LAYER CAKE WITH ICING: | H34: =H32/9 -> 38.733882
B36: CARROT CAKE
A39: CAKE TYPE | B39: Baking
A40: Carrot Cake | B40: Flour | C40: 142.99 | D40: 12,5kg | E40: =(E6) -> 84 | F40: 0.31506849 | G40: 23 | H40: 250ml | I40: 43.476301
B41: Bpowder | C41: 1173 | D41: 20kg | E41: 1111 | F41: 0.0081008101 | G41: 9 | H41: 15ml | I41: 9.5022502
B42: Salt | C42: 5 | D42: 1kg | E42: 142 | F42: 0.0070422535 | G42: 1 | H42: 5ml | I42: 0.035211268
B43: Cocoa | C43: 3450 | D43: 25kg | E43: 312 | F43: 0 | G43: 0 | H43: 250ml | I43: 0
B44: Bicarb | C44: 772.8 | D44: 25kg | E44: 1000 | F44: 0.005 | G44: 5 | H44: 15ml | I44: 3.864
B45: Eggs | C45: 430 | D45: 180 | E45: 60 | F45: 0.46666667 | G45: 28 | H45: 1 | I45: 163.32867
B46: Bsugar | C46: 174.99 | D46: 10kg | E46: 46 | F46: 0.4 | G46: 16 | H46: 250ml | I46: 65.996
B47: Wsugar | C47: 199.99 | D47: 10kg | E47: 46 | F47: 0 | G47: 0 | H47: 250ml | I47: 0
B48: Oil | C48: 129.99 | D48: 5liter | E48: 20 | F48: 0.4 | G48: 8 | H48: 250ml | I48: 51.996
B49: Vanilla | C49: 142.95 | D49: 3liter | E49: 37.5 | F49: 0 | G49: 0 | H49: 80ml | I49: 0
B50: Ellis Brown | C50: 69.99 | D50: 1kg | E50: 25 | F50: 0 | G50: 0 | H50: 80ml | I50: 0
B51: Milk | C51: 99.99 | D51: 6liter | E51: 6 | F51: 0 | G51: 0 | H51: 1l | I51: 0
B52: Cinnamon | C52: 500 | D52: 5kg | E52: 1000 | F52: 0.005 | G52: 5 | H52: 15ml | I52: 2.5
B53: Carrots | C53: 29.99 | D53: 3kg | E53: 3 | F53: 1.6666667 | G53: 5 | H53: 1kg | I53: 49.983333
B54: Vinegar | C54: 26.99 | D54: 5liter | E54: 83 | F54: 0.012048193 | G54: 1 | H54: 60ml | I54: 0.32518072
B55: Water | C55: 0 | F55: 2 | G55: 0.5 | H55: 1l
B56: Ricoffy | C56: 134.99 | D56: 750g | E56: 30 | F56: 0 | G56: 0 | H56: 80ml | I56: 0
B57: Nuts | C57: 160 | D57: 1kg | I57: =(C57/10) -> 16
B58: Packaging
B59: Domes | C59: =(C24) -> 239 | D59: 100 | E59: 100 | F59: 0.11 | G59: 11 | H59: 1 | I59: 28.1897
B60: Fomos | C60: =(C25) -> 90 | D60: 75 | E60: 75 | F60: 0.14666667 | G60: 11 | H60: 1 | I60: 13.2
B61: Bases | C61: =(C26) -> 239 | D61: 100 | E61: 100 | F61: 0.11 | G61: 11 | H61: 1 | I61: 28.1897
B62: Icing | C62: =(C27) -> 550 | G62: 11 | I62: 110
B63: Lables | C63: =(C28) -> 0 | G63: 11 | I63: 55
B64: Stock | C64: Cost | D64: Size | E64: Life | F64: Amount | G64: x Life | H64: Life Size | I64: =SUM(I40:I56)+(I59+I61+I57+I60+I62+I63) -> 641.58634
B66: TOTAL COST FOR 1 BATCH: | H66: =I64 -> 641.58634
B68: TOTAL COST FOR 1 DOUBLE LAYER CAKE WITH ICING: | H68: =H66/9 -> 71.287372
B70: COFFEE CAKE
A73: CAKE TYPE | B73: Baking
A74: Coffee Cake | B74: Flour | C74: 142.99 | D74: 12,5kg | E74: 86 | F74: 0.21917808 | G74: 16 | H74: 250ml | I74: 30.244384
B75: Bpowder | C75: 1173 | D75: 20kg | E75: 1111 | F75: 0.0054005401 | G75: 6 | H75: 15ml | I75: 6.3348335
B76: Salt | C76: 5 | D76: 1kg | E76: 142 | F76: 0.0070422535 | G76: 1 | H76: 5ml | I76: 0.035211268
